Workbook
Name SlicerCache_Table_1_Col_3: #N/A
Name SlicerCache_Table_2_Col_2: #N/A

Sheet events
A1: Order ID | B1: Order Date | C1: Ship Date | D1: Day for Order Turnaround | E1: Range | F1: Order Priority | G1: Country Code | H1: Clean Country Code | I1: Country Name | J1: Country Region | K1: County Sub-region | L1: Product ID | M1: Sales Channel | N1: Units Sold | O1: Unit Price | P1: Unit Cost | Q1: Total Revenue | R1: Total Cost | S1: Total Profit | T1: Total Margin
A2: 152191388 | B2: 41047 | C2: 41082 | D2: 35 | F2: L | G2: ALB | H2: =IF(G2="","UNKNOWN",G2) -> ALB | I2: Albania | J2: Europe | K2: =IF(G2="","Unknown Country",IFERROR(VLOOKUP(TRIM(G2),countries!C:F, 4, FALSE), "Unknown Country")) -> Southern Europe | L2: 7331 | M2: Offline | N2: 5669 | O2: 255.28 | P2: 159.42 | Q2: 1447182.3 | R2: 903751.98 | S2: 543430.34 | T2: =S2/Q2 -> 0.37550924 | V2: Total orders: | W2: =COUNT(A2:A1333) -> 1330
A3: 208238399 | B3: 42245 | C3: 42292 | D3: 47 | F3: L | G3: ALB | H3: =IF(G3="","UNKNOWN",G3) -> ALB | I3: Albania | J3: Europe | K3: =IF(G3="","Unknown Country",IFERROR(VLOOKUP(TRIM(G3),countries!C:F, 4, FALSE), "Unknown Country")) -> Southern Europe | L3: 8293 | M3: Offline | N3: 1224 | O3: 437.2 | P3: 263.33 | Q3: 535132.8 | R3: 322315.92 | S3: 212816.88 | T3: =S3/Q3 -> 0.39768984 | V3: Total profit: | W3: =SUM(S2:S1333) -> 501434459
A4: 246922719 | B4: 42198 | C4: 42214 | D4: 16 | F4: H | G4: ALB | H4: =IF(G4="","UNKNOWN",G4) -> ALB | I4: Albania | J4: Europe | K4: =IF(G4="","Unknown Country",IFERROR(VLOOKUP(TRIM(G4),countries!C:F, 4, FALSE), "Unknown Country")) -> Southern Europe | L4: 8681 | M4: Online | N4: 8775 | O4: 651.21 | P4: 524.96 | Q4: 5714367.8 | R4: 4606524 | S4: 1107843.8 | T4: =S4/Q4 -> 0.19386987 | V4: # of countries served: | W4: =IFERROR(__xludf.DUMMYFUNCTION("COUNTUNIQUE(G2:G1333)"),45.0) -> 45
A5: 270358788 | B5: 41984 | C5: 42028 | D5: 44 | F5: M | G5: ALB | H5: =IF(G5="","UNKNOWN",G5) -> ALB | I5: Albania | J5: Europe | K5: =IF(G5="","Unknown Country",IFERROR(VLOOKUP(TRIM(G5),countries!C:F, 4, FALSE), "Unknown Country")) -> Southern Europe | L5: 1270 | M5: Offline | N5: 4028 | O5: 47.45 | P5: 31.79 | Q5: 191128.6 | R5: 128050.12 | S5: 63078.48 | T5: =S5/Q5 -> 0.33003161
A6: 357930982 | B6: 42385 | C6: 42434 | D6: 49 | F6: C | G6: ALB | H6: =IF(G6="","UNKNOWN",G6) -> ALB | I6: Albania | J6: Europe | K6: =IF(G6="","Unknown Country",IFERROR(VLOOKUP(TRIM(G6),countries!C:F, 4, FALSE), "Unknown Country")) -> Southern Europe | L6: 2455 | M6: Offline | N6: 8586 | O6: 109.28 | P6: 35.84 | Q6: 938278.08 | R6: 307722.24 | S6: 630555.84 | T6: =S2/Q2 -> 0.37550924
A7: 380379998 | B7: 42930 | C7: 42932 | D7: 2 | F7: C | G7: ALB | H7: =IF(G7="","UNKNOWN",G7) -> ALB | I7: Albania | J7: Europe | K7: =IF(G7="","Unknown Country",IFERROR(VLOOKUP(TRIM(G7),countries!C:F, 4, FALSE), "Unknown Country")) -> Southern Europe | L7: 7940 | M7: Online | N7: 1749 | O7: 668.27 | P7: 502.54 | Q7: 1168804.2 | R7: 878942.46 | S7: 289861.77 | T7: =S3/Q3 -> 0.39768984
A8: 406564366 | B8: 41858 | C8: 41876 | D8: 18 | F8: M | G8: ALB | H8: =IF(G8="","UNKNOWN",G8) -> ALB | I8: Albania | J8: Europe | K8: =IF(G8="","Unknown Country",IFERROR(VLOOKUP(TRIM(G8),countries!C:F, 4, FALSE), "Unknown Country")) -> Southern Europe | L8: 5988 | M8: Online | N8: 286 | O8: 154.06 | P8: 90.93 | Q8: 44061.16 | R8: 26005.98 | S8: 18055.18 | T8: =S4/Q4 -> 0.19386987
A9: 470503079 | B9: 42072 | C9: 42084 | D9: 12 | F9: H | G9: ALB | H9: =IF(G9="","UNKNOWN",G9) -> ALB | I9: Albania | J9: Europe | K9: =IF(G9="","Unknown Country",IFERROR(VLOOKUP(TRIM(G9),countries!C:F, 4, FALSE), "Unknown Country")) -> Southern Europe | L9: 2455 | M9: Offline | N9: 1172 | O9: 109.28 | P9: 35.84 | Q9: 128076.16 | R9: 42004.48 | S9: 86071.68 | T9: =S5/Q5 -> 0.33003161
A10: 476633536 | B10: 41187 | C10: 41216 | D10: 29 | F10: C | G10: ALB | H10: =IF(G10="","UNKNOWN",G10) -> ALB | I10: Albania | J10: Europe | K10: =IF(G10="","Unknown Country",IFERROR(VLOOKUP(TRIM(G10),countries!C:F, 4, FALSE), "Unknown Country")) -> Southern Europe | L10: 5988 | M10: Online | N10: 5310 | O10: 154.06 | P10: 90.93 | Q10: 818058.6 | R10: 482838.3 | S10: 335220.3 | T10: =S6/Q6 -> 0.67203514
A11: 570476520 | B11: 40532 | C11: 40536 | D11: 4 | F11: L | G11: ALB | H11: =IF(G11="","UNKNOWN",G11) -> ALB | I11: Albania | J11: Europe | K11: =IF(G11="","Unknown Country",IFERROR(VLOOKUP(TRIM(G11),countries!C:F, 4, FALSE), "Unknown Country")) -> Southern Europe | L11: 7940 | M11: Online | N11: 5534 | O11: 668.27 | P11: 502.54 | Q11: 3698206.2 | R11: 2781056.4 | S11: 917149.82 | T11: =S7/Q7 -> 0.24799856
A12: 576944720 | B12: 42643 | C12: 42652 | D12: 9 | F12: L | G12: ALB | H12: =IF(G12="","UNKNOWN",G12) -> ALB | I12: Albania | J12: Europe | K12: =IF(G12="","Unknown Country",IFERROR(VLOOKUP(TRIM(G12),countries!C:F, 4, FALSE), "Unknown Country")) -> Southern Europe | L12: 8293 | M12: Offline | N12: 9619 | O12: 437.2 | P12: 263.33 | Q12: 4205426.8 | R12: 2532971.3 | S12: 1672455.5 | T12: =S8/Q8 -> 0.40977541
A13: 647943866 | B13: 40640 | C13: 40651 | D13: 11 | F13: M | G13: ALB | H13: =IF(G13="","UNKNOWN",G13) -> ALB | I13: Albania | J13: Europe | K13: =IF(G13="","Unknown Country",IFERROR(VLOOKUP(TRIM(G13),countries!C:F, 4, FALSE), "Unknown Country")) -> Southern Europe | L13: 2455 | M13: Online | N13: 9843 | O13: 109.28 | P13: 35.84 | Q13: 1075643 | R13: 352773.12 | S13: 722869.92 | T13: =S9/Q9 -> 0.67203514
A14: 653087270 | B14: 40514 | C14: 40519 | D14: 5 | F14: H | G14: ALB | H14: =IF(G14="","UNKNOWN",G14) -> ALB | I14: Albania | J14: Europe | K14: =IF(G14="","Unknown Country",IFERROR(VLOOKUP(TRIM(G14),countries!C:F, 4, FALSE), "Unknown Country")) -> Southern Europe | L14: 8969 | M14: Online | N14: 1891 | O14: 152.58 | P14: 97.44 | Q14: 288528.78 | R14: 184259.04 | S14: 104269.74 | T14: =S10/Q10 -> 0.40977541
A15: 694914710 | B15: 40413 | C15: 40446 | D15: 33 | F15: C | G15: ALB | H15: =IF(G15="","UNKNOWN",G15) -> ALB | I15: Albania | J15: Europe | K15: =IF(G15="","Unknown Country",IFERROR(VLOOKUP(TRIM(G15),countries!C:F, 4, FALSE), "Unknown Country")) -> Southern Europe | L15: 8293 | M15: Offline | N15: 9560 | O15: 437.2 | P15: 263.33 | Q15: 4179632 | R15: 2517434.8 | S15: 1662197.2 | T15: =S11/Q11 -> 0.24799856
A16: 728793370 | B16: 40721 | C16: 40767 | D16: 46 | F16: L | G16: ALB | H16: =IF(G16="","UNKNOWN",G16) -> ALB | I16: Albania | J16: Europe | K16: =IF(G16="","Unknown Country",IFERROR(VLOOKUP(TRIM(G16),countries!C:F, 4, FALSE), "Unknown Country")) -> Southern Europe | L16: 8293 | M16: Offline | N16: 5009 | O16: 437.2 | P16: 263.33 | Q16: 2189934.8 | R16: 1319020 | S16: 870914.83 | T16: =S12/Q12 -> 0.39768984
A17: 833473765 | B17: 41392 | C17: 41419 | D17: 27 | F17: H | G17: ALB | H17: =IF(G17="","UNKNOWN",G17) -> ALB | I17: Albania | J17: Europe | K17: =IF(G17="","Unknown Country",IFERROR(VLOOKUP(TRIM(G17),countries!C:F, 4, FALSE), "Unknown Country")) -> Southern Europe | L17: 1270 | M17: Offline | N17: 2264 | O17: 47.45 | P17: 31.79 | Q17: 107426.8 | R17: 71972.56 | S17: 35454.24 | T17: =S13/Q13 -> 0.67203514
... A241: 259006392 | B241: 41416 | C241: 41431 | D241: 15 | F241: C | G241: HRV | H241: =IF(G241="","UNKNOWN",G241) -> HRV | I241: Croatia | J241: Europe | K241: =IF(G241="","Unknown Country",IFERROR(VLOOKUP(TRIM(G241),countries!C:F, 4, FALSE), "Unknown Country")) -> Southern Europe | L241: 8681 | M241: Online | N241: 4602 | O241: 651.21 | P241: 524.96 | Q241: 2996868.4 | R241: 2415865.9 | S241: 581002.5 | T241: =S237/Q237 -> 0.37550924
A242: 309655511 | B242: 41764 | C242: 41780 | D242: 16 | F242: C | G242: HRV | H242: =IF(G242="","UNKNOWN",G242) -> HRV | I242: Croatia | J242: Europe | K242: =IF(G242="","Unknown Country",IFERROR(VLOOKUP(TRIM(G242),countries!C:F, 4, FALSE), "Unknown Country")) -> Southern Europe | L242: 3127 | M242: Offline | O242: 81.73 | P242: 56.67 | Q242: 0 | R242: 0 | S242: 0 | T242: =S238/Q238 -> 0.24799856
A243: 354667699 | B243: 41234 | C243: 41272 | D243: 38 | F243: L | G243: HRV | H243: =IF(G243="","UNKNOWN",G243) -> HRV | I243: Croatia | J243: Europe | K243: =IF(G243="","Unknown Country",IFERROR(VLOOKUP(TRIM(G243),countries!C:F, 4, FALSE), "Unknown Country")) -> Southern Europe | L243: 8681 | M243: Offline | N243: 2908 | O243: 651.21 | P243: 524.96 | Q243: 1893718.7 | R243: 1526583.7 | S243: 367135 | T243: =S239/Q239 -> 0.33003161
A244: 364715468 | B244: 40954 | C244: 40958 | D244: 4 | F244: M | G244: HRV | H244: =IF(G244="","UNKNOWN",G244) -> HRV | I244: Croatia | J244: Europe | K244: =IF(G244="","Unknown Country",IFERROR(VLOOKUP(TRIM(G244),countries!C:F, 4, FALSE), "Unknown Country")) -> Southern Europe | L244: 8293 | M244: Offline | N244: 6267 | O244: 437.2 | P244: 263.33 | Q244: 2739932.4 | R244: 1650289.1 | S244: 1089643.3 | T244: =S240/Q240 -> 0.33003161
A245: 396832883 | B245: 41362 | C245: 41364 | D245: 2 | F245: M | G245: HRV | H245: =IF(G245="","UNKNOWN",G245) -> HRV | I245: Croatia | J245: Europe | K245: =IF(G245="","Unknown Country",IFERROR(VLOOKUP(TRIM(G245),countries!C:F, 4, FALSE), "Unknown Country")) -> Southern Europe | L245: 3127 | M245: Offline | N245: 523 | O245: 81.73 | P245: 56.67 | Q245: 42744.79 | R245: 29638.41 | S245: 13106.38 | T245: =S241/Q241 -> 0.19386987
A246: 488815915 | B246: 40605 | C246: 40650 | D246: 45 | F246: M | G246: HRV | H246: =IF(G246="","UNKNOWN",G246) -> HRV | I246: Croatia | J246: Europe | K246: =IF(G246="","Unknown Country",IFERROR(VLOOKUP(TRIM(G246),countries!C:F, 4, FALSE), "Unknown Country")) -> Southern Europe | L246: 8969 | M246: Offline | N246: 347 | O246: 152.58 | P246: 97.44 | Q246: 52945.26 | R246: 33811.68 | S246: 19133.58 | T246: =S242/Q242 -> #DIV/0!
A247: 530882394 | B247: 40533 | C247: 40576 | D247: 43 | F247: M | G247: HRV | H247: =IF(G247="","UNKNOWN",G247) -> HRV | I247: Croatia | J247: Europe | K247: =IF(G247="","Unknown Country",IFERROR(VLOOKUP(TRIM(G247),countries!C:F, 4, FALSE), "Unknown Country")) -> Southern Europe | L247: 8875 | M247: Online | N247: 8753 | O247: 421.89 | P247: 364.69 | Q247: 3692803.2 | R247: 3192131.6 | S247: 500671.6 | T247: =S243/Q243 -> 0.19386987
A248: 582560193 | B248: 42515 | C248: 42518 | D248: 3 | F248: L | G248: HRV | H248: =IF(G248="","UNKNOWN",G248) -> HRV | I248: Croatia | J248: Europe | K248: =IF(G248="","Unknown Country",IFERROR(VLOOKUP(TRIM(G248),countries!C:F, 4, FALSE), "Unknown Country")) -> Southern Europe | L248: 7940 | M248: Online | N248: 1362 | O248: 668.27 | P248: 502.54 | Q248: 910183.74 | R248: 684459.48 | S248: 225724.26 | T248: =S244/Q244 -> 0.39768984
A249: 650078475 | B249: 40338 | C249: 40347 | D249: 9 | F249: H | G249: HRV | H249: =IF(G249="","UNKNOWN",G249) -> HRV | I249: Croatia | J249: Europe | K249: =IF(G249="","Unknown Country",IFERROR(VLOOKUP(TRIM(G249),countries!C:F, 4, FALSE), "Unknown Country")) -> Southern Europe | L249: 8681 | M249: Online | N249: 1522 | O249: 651.21 | P249: 524.96 | Q249: 991141.62 | R249: 798989.12 | S249: 192152.5 | T249: =S245/Q245 -> 0.30661936
A250: 659196269 | B250: 41390 | C250: 41426 | D250: 36 | F250: L | G250: HRV | H250: =IF(G250="","UNKNOWN",G250) -> HRV | I250: Croatia | J250: Europe | K250: =IF(G250="","Unknown Country",IFERROR(VLOOKUP(TRIM(G250),countries!C:F, 4, FALSE), "Unknown Country")) -> Southern Europe | L250: 7940 | M250: Online | N250: 9680 | O250: 668.27 | P250: 502.54 | Q250: 6468853.6 | R250: 4864587.2 | S250: 1604266.4 | T250: =S246/Q246 -> 0.36138419
A251: 775347936 | B251: 41452 | C251: 41463 | D251: 11 | F251: C | G251: HRV | H251: =IF(G251="","UNKNOWN",G251) -> HRV | I251: Croatia | J251: Europe | K251: =IF(G251="","Unknown Country",IFERROR(VLOOKUP(TRIM(G251),countries!C:F, 4, FALSE), "Unknown Country")) -> Southern Europe | L251: 7331 | M251: Offline | N251: 1539 | O251: 255.28 | P251: 159.42 | Q251: 392875.92 | R251: 245347.38 | S251: 147528.54 | T251: =S247/Q247 -> 0.13558036
A252: 781083571 | B252: 42530 | C252: 42539 | D252: 9 | F252: C | G252: HRV | H252: =IF(G252="","UNKNOWN",G252) -> HRV | I252: Croatia | J252: Europe | K252: =IF(G252="","Unknown Country",IFERROR(VLOOKUP(TRIM(G252),countries!C:F, 4, FALSE), "Unknown Country")) -> Southern Europe | L252: 2455 | M252: Online | N252: 8841 | O252: 109.28 | P252: 35.84 | Q252: 966144.48 | R252: 316861.44 | S252: 649283.04 | T252: =S248/Q248 -> 0.24799856
A253: 906508815 | B253: 41652 | C253: 41662 | D253: 10 | F253: H | G253: HRV | H253: =IF(G253="","UNKNOWN",G253) -> HRV | I253: Croatia | J253: Europe | K253: =IF(G253="","Unknown Country",IFERROR(VLOOKUP(TRIM(G253),countries!C:F, 4, FALSE), "Unknown Country")) -> Southern Europe | L253: 2455 | M253: Online | N253: 4958 | O253: 109.28 | P253: 35.84 | Q253: 541810.24 | R253: 177694.72 | S253: 364115.52 | T253: =S249/Q249 -> 0.19386987
A254: 976323497 | B254: 42772 | C254: 42776 | D254: 4 | F254: M | G254: HRV | H254: =IF(G254="","UNKNOWN",G254) -> HRV | I254: Croatia | J254: Europe | K254: =IF(G254="","Unknown Country",IFERROR(VLOOKUP(TRIM(G254),countries!C:F, 4, FALSE), "Unknown Country")) -> Southern Europe | L254: 1270 | M254: Online | N254: 4674 | O254: 47.45 | P254: 31.79 | Q254: 221781.3 | R254: 148586.46 | S254: 73194.84 | T254: =S250/Q250 -> 0.24799856
... A783: 971578347 | B783: 41759 | C783: 41806 | D783: 47 | F783: L | G783: MCO | H783: =IF(G783="","UNKNOWN",G783) -> MCO | I783: Monaco | J783: Europe | K783: =IF(G783="","Unknown Country",IFERROR(VLOOKUP(TRIM(G783),countries!C:F, 4, FALSE), "Unknown Country")) -> Western Europe | L783: 7940 | M783: Online | N783: 478 | O783: 668.27 | P783: 502.54 | Q783: 319433.06 | R783: 240214.12 | S783: 79218.94 | T783: =S779/Q779 -> 0.19386987
A784: 102230632 | B784: 42868 | C784: 42899 | D784: 31 | F784: L | G784: MNE | H784: =IF(G784="","UNKNOWN",G784) -> MNE | I784: Montenegro | J784: Europe | K784: =IF(G784="","Unknown Country",IFERROR(VLOOKUP(TRIM(G784),countries!C:F, 4, FALSE), "Unknown Country")) -> Southern Europe | L784: 2455 | M784: Online | N784: 1171 | O784: 109.28 | P784: 35.84 | Q784: 127966.88 | R784: 41968.64 | S784: 85998.24
A785: 122144210 | B785: 42852 | C785: 42879 | D785: 27 | F785: C | G785: MNE | H785: =IF(G785="","UNKNOWN",G785) -> MNE | I785: Montenegro | J785: Europe | K785: =IF(G785="","Unknown Country",IFERROR(VLOOKUP(TRIM(G785),countries!C:F, 4, FALSE), "Unknown Country")) -> Southern Europe | L785: 1270 | M785: Offline | N785: 4041 | O785: 47.45 | P785: 31.79 | Q785: 191745.45 | R785: 128463.39 | S785: 63282.06 | T785: =S781/Q781 -> 0.43067574
A786: 234082448 | B786: 41707 | C786: 41707 | D786: 0 | F786: C | G786: MNE | H786: =IF(G786="","UNKNOWN",G786) -> MNE | I786: Montenegro | J786: Europe | K786: =IF(G786="","Unknown Country",IFERROR(VLOOKUP(TRIM(G786),countries!C:F, 4, FALSE), "Unknown Country")) -> Southern Europe | L786: 2455 | M786: Online | N786: 9053 | O786: 109.28 | P786: 35.84 | Q786: 989311.84 | R786: 324459.52 | S786: 664852.32 | T786: =S782/Q782 -> 0.67203514
A787: 243340575 | B787: 42588 | C787: 42617 | D787: 29 | F787: C | G787: MNE | H787: =IF(G787="","UNKNOWN",G787) -> MNE | I787: Montenegro | J787: Europe | K787: =IF(G787="","Unknown Country",IFERROR(VLOOKUP(TRIM(G787),countries!C:F, 4, FALSE), "Unknown Country")) -> Southern Europe | L787: 1270 | M787: Offline | N787: 8739 | O787: 47.45 | P787: 31.79 | Q787: 414665.55 | R787: 277812.81 | S787: 136852.74 | T787: =S783/Q783 -> 0.24799856
A788: 256095016 | B788: 41822 | C788: 41872 | D788: 50 | F788: H | G788: MNE | H788: =IF(G788="","UNKNOWN",G788) -> MNE | I788: Montenegro | J788: Europe | K788: =IF(G788="","Unknown Country",IFERROR(VLOOKUP(TRIM(G788),countries!C:F, 4, FALSE), "Unknown Country")) -> Southern Europe | L788: 8681 | M788: Offline | N788: 3061 | O788: 651.21 | P788: 524.96 | Q788: 1993353.8 | R788: 1606902.6 | S788: 386451.25 | T788: =S784/Q784 -> 0.67203514
A789: 284435451 | B789: 41454 | C789: 41454 | D789: 0 | F789: C | G789: MNE | H789: =IF(G789="","UNKNOWN",G789) -> MNE | I789: Montenegro | J789: Europe | K789: =IF(G789="","Unknown Country",IFERROR(VLOOKUP(TRIM(G789),countries!C:F, 4, FALSE), "Unknown Country")) -> Southern Europe | L789: 3127 | M789: Offline | N789: 9625 | O789: 81.73 | P789: 56.67 | Q789: 786651.25 | R789: 545448.75 | S789: 241202.5 | T789: =S785/Q785 -> 0.33003161
A790: 305616748 | B790: 40335 | C790: 40360 | D790: 25 | F790: M | G790: MNE | H790: =IF(G790="","UNKNOWN",G790) -> MNE | I790: Montenegro | J790: Europe | K790: =IF(G790="","Unknown Country",IFERROR(VLOOKUP(TRIM(G790),countries!C:F, 4, FALSE), "Unknown Country")) -> Southern Europe | L790: 2103 | M790: Offline | N790: 7642 | O790: 205.7 | P790: 117.11 | Q790: 1571959.4 | R790: 894954.62 | S790: 677004.78 | T790: =S786/Q786 -> 0.67203514
A791: 313705861 | B791: 42519 | C791: 42561 | D791: 42 | F791: L | G791: MNE | H791: =IF(G791="","UNKNOWN",G791) -> MNE | I791: Montenegro | J791: Europe | K791: =IF(G791="","Unknown Country",IFERROR(VLOOKUP(TRIM(G791),countries!C:F, 4, FALSE), "Unknown Country")) -> Southern Europe | L791: 4594 | M791: Offline | N791: 1390 | O791: 9.33 | P791: 6.92 | Q791: 12968.7 | R791: 9618.8 | S791: 3349.9 | T791: =S787/Q787 -> 0.33003161
A792: 353320157 | B792: 41140 | C792: 41143 | D792: 3 | F792: L | G792: MNE | H792: =IF(G792="","UNKNOWN",G792) -> MNE | I792: Montenegro | J792: Europe | K792: =IF(G792="","Unknown Country",IFERROR(VLOOKUP(TRIM(G792),countries!C:F, 4, FALSE), "Unknown Country")) -> Southern Europe | L792: 8293 | M792: Offline | N792: 4141 | O792: 437.2 | P792: 263.33 | Q792: 1810445.2 | R792: 1090449.5 | S792: 719995.67 | T792: =S788/Q788 -> 0.19386987
A793: 357434880 | B793: 42146 | C793: 42184 | D793: 38 | F793: C | G793: MNE | H793: =IF(G793="","UNKNOWN",G793) -> MNE | I793: Montenegro | J793: Europe | K793: =IF(G793="","Unknown Country",IFERROR(VLOOKUP(TRIM(G793),countries!C:F, 4, FALSE), "Unknown Country")) -> Southern Europe | L793: 8293 | M793: Online | N793: 1779 | O793: 437.2 | P793: 263.33 | Q793: 777778.8 | R793: 468464.07 | S793: 309314.73 | T793: =S789/Q789 -> 0.30661936
A794: 378714883 | B794: 41229 | C794: 41259 | D794: 30 | F794: M | G794: MNE | H794: =IF(G794="","UNKNOWN",G794) -> MNE | I794: Montenegro | J794: Europe | K794: =IF(G794="","Unknown Country",IFERROR(VLOOKUP(TRIM(G794),countries!C:F, 4, FALSE), "Unknown Country")) -> Southern Europe | L794: 8293 | M794: Offline | N794: 9005 | O794: 437.2 | P794: 263.33 | Q794: 3936986 | R794: 2371286.6 | S794: 1565699.4 | T794: =S790/Q790 -> 0.43067574
A795: 381759297 | B795: 40972 | C795: 40993 | D795: 21 | F795: C | G795: MNE | H795: =IF(G795="","UNKNOWN",G795) -> MNE | I795: Montenegro | J795: Europe | K795: =IF(G795="","Unknown Country",IFERROR(VLOOKUP(TRIM(G795),countries!C:F, 4, FALSE), "Unknown Country")) -> Southern Europe | L795: 2455 | M795: Online | N795: 9914 | O795: 109.28 | P795: 35.84 | Q795: 1083401.9 | R795: 355317.76 | S795: 728084.16 | T795: =S791/Q791 -> 0.25830654
A796: 394456660 | B796: 42400 | C796: 42409 | D796: 9 | F796: H | G796: MNE | H796: =IF(G796="","UNKNOWN",G796) -> MNE | I796: Montenegro | J796: Europe | K796: =IF(G796="","Unknown Country",IFERROR(VLOOKUP(TRIM(G796),countries!C:F, 4, FALSE), "Unknown Country")) -> Southern Europe | L796: 4594 | M796: Online | N796: 7346 | O796: 9.33 | P796: 6.92 | Q796: 68538.18 | R796: 50834.32 | S796: 17703.86 | T796: =S792/Q792 -> 0.39768984
... A835: 990774810 | B835: 41656 | C835: 41688 | D835: 32 | F835: C | G835: NLD | H835: =IF(G835="","UNKNOWN",G835) -> NLD | I835: Netherlands | J835: Europe | K835: =IF(G835="","Unknown Country",IFERROR(VLOOKUP(TRIM(G835),countries!C:F, 4, FALSE), "Unknown Country")) -> Western Europe | L835: 7940 | M835: Offline | N835: 1138 | O835: 668.27 | P835: 502.54 | Q835: 760491.26 | R835: 571890.52 | S835: 188600.74 | T835: =S831/Q831 -> 0.19386987
A836: 100640618 | B836: 41920 | C836: 41930 | D836: 10 | F836: M | G836: NOR | H836: =IF(G836="","UNKNOWN",G836) -> NOR | I836: Norway | J836: Europe | K836: =IF(G836="","Unknown Country",IFERROR(VLOOKUP(TRIM(G836),countries!C:F, 4, FALSE), "Unknown Country")) -> Northern Europe | L836: 2103 | M836: Online | N836: 650 | O836: 205.7 | P836: 117.11 | Q836: 133705 | R836: 76121.5 | S836: 57583.5
A837: 118086564 | B837: 42419 | C837: 42442 | D837: 23 | F837: M | G837: NOR | H837: =IF(G837="","UNKNOWN",G837) -> NOR | I837: Norway | J837: Europe | K837: =IF(G837="","Unknown Country",IFERROR(VLOOKUP(TRIM(G837),countries!C:F, 4, FALSE), "Unknown Country")) -> Northern Europe | L837: 8969 | M837: Online | N837: 3293 | O837: 152.58 | P837: 97.44 | Q837: 502445.94 | R837: 320869.92 | S837: 181576.02 | T837: =S833/Q833 -> 0.30661936
A838: 149274003 | B838: 41393 | C838: 41423 | D838: 30 | F838: C | G838: NOR | H838: =IF(G838="","UNKNOWN",G838) -> NOR | I838: Norway | J838: Europe | K838: =IF(G838="","Unknown Country",IFERROR(VLOOKUP(TRIM(G838),countries!C:F, 4, FALSE), "Unknown Country")) -> Northern Europe | L838: 7940 | M838: Offline | N838: 2350 | O838: 668.27 | P838: 502.54 | Q838: 1570434.5 | R838: 1180969 | S838: 389465.5 | T838: =S834/Q834 -> 0.33003161
A839: 238170993 | B839: 41265 | C839: 41312 | D839: 47 | F839: L | G839: NOR | H839: =IF(G839="","UNKNOWN",G839) -> NOR | I839: Norway | J839: Europe | K839: =IF(G839="","Unknown Country",IFERROR(VLOOKUP(TRIM(G839),countries!C:F, 4, FALSE), "Unknown Country")) -> Northern Europe | L839: 1270 | M839: Offline | N839: 8944 | O839: 47.45 | P839: 31.79 | Q839: 424392.8 | R839: 284329.76 | S839: 140063.04 | T839: =S835/Q835 -> 0.24799856
A840: 330590474 | B840: 40938 | C840: 40982 | D840: 44 | F840: L | G840: NOR | H840: =IF(G840="","UNKNOWN",G840) -> NOR | I840: Norway | J840: Europe | K840: =IF(G840="","Unknown Country",IFERROR(VLOOKUP(TRIM(G840),countries!C:F, 4, FALSE), "Unknown Country")) -> Northern Europe | L840: 8681 | M840: Online | N840: 7923 | O840: 651.21 | P840: 524.96 | Q840: 5159536.8 | R840: 4159258.1 | S840: 1000278.8 | T840: =S836/Q836 -> 0.43067574
A841: 337354791 | B841: 40886 | C841: 40936 | D841: 50 | F841: L | G841: NOR | H841: =IF(G841="","UNKNOWN",G841) -> NOR | I841: Norway | J841: Europe | K841: =IF(G841="","Unknown Country",IFERROR(VLOOKUP(TRIM(G841),countries!C:F, 4, FALSE), "Unknown Country")) -> Northern Europe | L841: 8293 | M841: Offline | N841: 9634 | O841: 437.2 | P841: 263.33 | Q841: 4211984.8 | R841: 2536921.2 | S841: 1675063.6 | T841: =S837/Q837 -> 0.36138419
A842: 357943856 | B842: 41329 | C842: 41350 | D842: 21 | F842: L | G842: NOR | H842: =IF(G842="","UNKNOWN",G842) -> NOR | I842: Norway | J842: Europe | K842: =IF(G842="","Unknown Country",IFERROR(VLOOKUP(TRIM(G842),countries!C:F, 4, FALSE), "Unknown Country")) -> Northern Europe | L842: 7331 | M842: Offline | N842: 2396 | O842: 255.28 | P842: 159.42 | Q842: 611650.88 | R842: 381970.32 | S842: 229680.56 | T842: =S838/Q838 -> 0.24799856
A843: 381774747 | B843: 41918 | C843: 41935 | D843: 17 | F843: C | G843: NOR | H843: =IF(G843="","UNKNOWN",G843) -> NOR | I843: Norway | J843: Europe | K843: =IF(G843="","Unknown Country",IFERROR(VLOOKUP(TRIM(G843),countries!C:F, 4, FALSE), "Unknown Country")) -> Northern Europe | L843: 4594 | M843: Offline | N843: 4486 | O843: 9.33 | P843: 6.92 | Q843: 41854.38 | R843: 31043.12 | S843: 10811.26 | T843: =S839/Q839 -> 0.33003161
A844: 384128224 | B844: 40257 | C844: 40294 | D844: 37 | F844: M | G844: NOR | H844: =IF(G844="","UNKNOWN",G844) -> NOR | I844: Norway | J844: Europe | K844: =IF(G844="","Unknown Country",IFERROR(VLOOKUP(TRIM(G844),countries!C:F, 4, FALSE), "Unknown Country")) -> Northern Europe | L844: 7940 | M844: Offline | N844: 933 | O844: 668.27 | P844: 502.54 | Q844: 623495.91 | R844: 468869.82 | S844: 154626.09 | T844: =S840/Q840 -> 0.19386987
A845: 392217338 | B845: 42441 | C845: 42444 | D845: 3 | F845: L | G845: NOR | H845: =IF(G845="","UNKNOWN",G845) -> NOR | I845: Norway | J845: Europe | K845: =IF(G845="","Unknown Country",IFERROR(VLOOKUP(TRIM(G845),countries!C:F, 4, FALSE), "Unknown Country")) -> Northern Europe | L845: 8969 | M845: Offline | N845: 4681 | O845: 152.58 | P845: 97.44 | Q845: 714226.98 | R845: 456116.64 | S845: 258110.34 | T845: =S841/Q841 -> 0.39768984
A846: 416682088 | B846: 41095 | C846: 41135 | D846: 40 | F846: H | G846: NOR | H846: =IF(G846="","UNKNOWN",G846) -> NOR | I846: Norway | J846: Europe | K846: =IF(G846="","Unknown Country",IFERROR(VLOOKUP(TRIM(G846),countries!C:F, 4, FALSE), "Unknown Country")) -> Northern Europe | L846: 5988 | M846: Offline | N846: 4344 | O846: 154.06 | P846: 90.93 | Q846: 669236.64 | R846: 394999.92 | S846: 274236.72 | T846: =S842/Q842 -> 0.37550924
A847: 445952498 | B847: 42161 | C847: 42192 | D847: 31 | F847: C | G847: NOR | H847: =IF(G847="","UNKNOWN",G847) -> NOR | I847: Norway | J847: Europe | K847: =IF(G847="","Unknown Country",IFERROR(VLOOKUP(TRIM(G847),countries!C:F, 4, FALSE), "Unknown Country")) -> Northern Europe | L847: 2103 | M847: Offline | N847: 6109 | O847: 205.7 | P847: 117.11 | Q847: 1256621.3 | R847: 715424.99 | S847: 541196.31 | T847: =S843/Q843 -> 0.25830654
A848: 477633464 | B848: 42138 | C848: 42162 | D848: 24 | F848: H | G848: NOR | H848: =IF(G848="","UNKNOWN",G848) -> NOR | I848: Norway | J848: Europe | K848: =IF(G848="","Unknown Country",IFERROR(VLOOKUP(TRIM(G848),countries!C:F, 4, FALSE), "Unknown Country")) -> Northern Europe | L848: 8293 | M848: Online | N848: 1211 | O848: 437.2 | P848: 263.33 | Q848: 529449.2 | R848: 318892.63 | S848: 210556.57 | T848: =S844/Q844 -> 0.24799856
... A1024: 937875640 | B1024: 40846 | C1024: 40877 | D1024: 31 | F1024: C | G1024: SMR | H1024: =IF(G1024="","UNKNOWN",G1024) -> SMR | I1024: San Marino | J1024: Europe | K1024: =IF(G1024="","Unknown Country",IFERROR(VLOOKUP(TRIM(G1024),countries!C:F, 4, FALSE), "Unknown Country")) -> Southern Europe | L1024: 2455 | M1024: Online | N1024: 7098 | O1024: 109.28 | P1024: 35.84 | Q1024: 775669.44 | R1024: 254392.32 | S1024: 521277.12 | T1024: =S1020/Q1020 -> 0.24799856
A1025: 100983083 | B1025: 42593 | C1025: 42593 | D1025: 0 | F1025: C | G1025: SRB | H1025: =IF(G1025="","UNKNOWN",G1025) -> SRB | I1025: Serbia | J1025: Europe | K1025: =IF(G1025="","Unknown Country",IFERROR(VLOOKUP(TRIM(G1025),countries!C:F, 4, FALSE), "Unknown Country")) -> Southern Europe | L1025: 2103 | M1025: Offline | N1025: 1993 | O1025: 205.7 | P1025: 117.11 | Q1025: 409960.1 | R1025: 233400.23 | S1025: 176559.87
A1026: 103435266 | B1026: 41132 | C1026: 41170 | D1026: 38 | F1026: H | G1026: SRB | H1026: =IF(G1026="","UNKNOWN",G1026) -> SRB | I1026: Serbia | J1026: Europe | K1026: =IF(G1026="","Unknown Country",IFERROR(VLOOKUP(TRIM(G1026),countries!C:F, 4, FALSE), "Unknown Country")) -> Southern Europe | L1026: 1270 | M1026: Offline | N1026: 7648 | O1026: 47.45 | P1026: 31.79 | Q1026: 362897.6 | R1026: 243129.92 | S1026: 119767.68 | T1026: =S1022/Q1022 -> 0.19386987
A1027: 209736573 | B1027: 41875 | C1027: 41906 | D1027: 31 | F1027: C | G1027: SRB | H1027: =IF(G1027="","UNKNOWN",G1027) -> SRB | I1027: Serbia | J1027: Europe | K1027: =IF(G1027="","Unknown Country",IFERROR(VLOOKUP(TRIM(G1027),countries!C:F, 4, FALSE), "Unknown Country")) -> Southern Europe | L1027: 8681 | M1027: Offline | N1027: 4568 | O1027: 651.21 | P1027: 524.96 | Q1027: 2974727.3 | R1027: 2398017.3 | S1027: 576710 | T1027: =S1023/Q1023 -> 0.19386987
A1028: 265191352 | B1028: 41869 | C1028: 41908 | D1028: 39 | F1028: M | G1028: SRB | H1028: =IF(G1028="","UNKNOWN",G1028) -> SRB | I1028: Serbia | J1028: Europe | K1028: =IF(G1028="","Unknown Country",IFERROR(VLOOKUP(TRIM(G1028),countries!C:F, 4, FALSE), "Unknown Country")) -> Southern Europe | L1028: 8969 | M1028: Offline | N1028: 4869 | O1028: 152.58 | P1028: 97.44 | Q1028: 742912.02 | R1028: 474435.36 | S1028: 268476.66 | T1028: =S1024/Q1024 -> 0.67203514
A1029: 266614854 | B1029: 41540 | C1029: 41557 | D1029: 17 | F1029: M | G1029: SRB | H1029: =IF(G1029="","UNKNOWN",G1029) -> SRB | I1029: Serbia | J1029: Europe | K1029: =IF(G1029="","Unknown Country",IFERROR(VLOOKUP(TRIM(G1029),countries!C:F, 4, FALSE), "Unknown Country")) -> Southern Europe | L1029: 7940 | M1029: Online | N1029: 6115 | O1029: 668.27 | P1029: 502.54 | Q1029: 4086471 | R1029: 3073032.1 | S1029: 1013438.9 | T1029: =S1025/Q1025 -> 0.43067574
A1030: 285343968 | B1030: 41882 | C1030: 41887 | D1030: 5 | F1030: C | G1030: SRB | H1030: =IF(G1030="","UNKNOWN",G1030) -> SRB | I1030: Serbia | J1030: Europe | K1030: =IF(G1030="","Unknown Country",IFERROR(VLOOKUP(TRIM(G1030),countries!C:F, 4, FALSE), "Unknown Country")) -> Southern Europe | L1030: 5988 | M1030: Online | N1030: 8476 | O1030: 154.06 | P1030: 90.93 | Q1030: 1305812.6 | R1030: 770722.68 | S1030: 535089.88 | T1030: =S1026/Q1026 -> 0.33003161
A1031: 302015721 | B1031: 41720 | C1031: 41746 | D1031: 26 | F1031: H | G1031: SRB | H1031: =IF(G1031="","UNKNOWN",G1031) -> SRB | I1031: Serbia | J1031: Europe | K1031: =IF(G1031="","Unknown Country",IFERROR(VLOOKUP(TRIM(G1031),countries!C:F, 4, FALSE), "Unknown Country")) -> Southern Europe | L1031: 7331 | M1031: Online | N1031: 2018 | O1031: 255.28 | P1031: 159.42 | Q1031: 515155.04 | R1031: 321709.56 | S1031: 193445.48 | T1031: =S1027/Q1027 -> 0.19386987
A1032: 308582627 | B1032: 41266 | C1032: 41314 | D1032: 48 | F1032: C | G1032: SRB | H1032: =IF(G1032="","UNKNOWN",G1032) -> SRB | I1032: Serbia | J1032: Europe | K1032: =IF(G1032="","Unknown Country",IFERROR(VLOOKUP(TRIM(G1032),countries!C:F, 4, FALSE), "Unknown Country")) -> Southern Europe | L1032: 1270 | M1032: Offline | N1032: 5312 | O1032: 47.45 | P1032: 31.79 | Q1032: 252054.4 | R1032: 168868.48 | S1032: 83185.92 | T1032: =S1028/Q1028 -> 0.36138419
A1033: 350550401 | B1033: 40993 | C1033: 41021 | D1033: 28 | F1033: H | G1033: SRB | H1033: =IF(G1033="","UNKNOWN",G1033) -> SRB | I1033: Serbia | J1033: Europe | K1033: =IF(G1033="","Unknown Country",IFERROR(VLOOKUP(TRIM(G1033),countries!C:F, 4, FALSE), "Unknown Country")) -> Southern Europe | L1033: 8293 | M1033: Online | N1033: 4508 | O1033: 437.2 | P1033: 263.33 | Q1033: 1970897.6 | R1033: 1187091.6 | S1033: 783805.96 | T1033: =S1029/Q1029 -> 0.24799856
A1034: 380610454 | B1034: 40898 | C1034: 40906 | D1034: 8 | F1034: C | G1034: SRB | H1034: =IF(G1034="","UNKNOWN",G1034) -> SRB | I1034: Serbia | J1034: Europe | K1034: =IF(G1034="","Unknown Country",IFERROR(VLOOKUP(TRIM(G1034),countries!C:F, 4, FALSE), "Unknown Country")) -> Southern Europe | L1034: 8875 | M1034: Offline | N1034: 9946 | O1034: 421.89 | P1034: 364.69 | Q1034: 4196117.9 | R1034: 3627206.7 | S1034: 568911.2 | T1034: =S1030/Q1030 -> 0.40977541
A1035: 392518174 | B1035: 40719 | C1035: 40727 | D1035: 8 | F1035: M | G1035: SRB | H1035: =IF(G1035="","UNKNOWN",G1035) -> SRB | I1035: Serbia | J1035: Europe | K1035: =IF(G1035="","Unknown Country",IFERROR(VLOOKUP(TRIM(G1035),countries!C:F, 4, FALSE), "Unknown Country")) -> Southern Europe | L1035: 5988 | M1035: Offline | N1035: 3705 | O1035: 154.06 | P1035: 90.93 | Q1035: 570792.3 | R1035: 336895.65 | S1035: 233896.65 | T1035: =S1031/Q1031 -> 0.37550924
A1036: 393842971 | B1036: 40190 | C1036: 40209 | D1036: 19 | F1036: L | G1036: SRB | H1036: =IF(G1036="","UNKNOWN",G1036) -> SRB | I1036: Serbia | J1036: Europe | K1036: =IF(G1036="","Unknown Country",IFERROR(VLOOKUP(TRIM(G1036),countries!C:F, 4, FALSE), "Unknown Country")) -> Southern Europe | L1036: 2455 | M1036: Offline | N1036: 5742 | O1036: 109.28 | P1036: 35.84 | Q1036: 627485.76 | R1036: 205793.28 | S1036: 421692.48 | T1036: =S1032/Q1032 -> 0.33003161
A1037: 395562589 | B1037: 40463 | C1037: 40513 | D1037: 50 | F1037: C | G1037: SRB | H1037: =IF(G1037="","UNKNOWN",G1037) -> SRB | I1037: Serbia | J1037: Europe | K1037: =IF(G1037="","Unknown Country",IFERROR(VLOOKUP(TRIM(G1037),countries!C:F, 4, FALSE), "Unknown Country")) -> Southern Europe | L1037: 1270 | M1037: Online | N1037: 4615 | O1037: 47.45 | P1037: 31.79 | Q1037: 218981.75 | R1037: 146710.85 | S1037: 72270.9 | T1037: =S1033/Q1033 -> 0.39768984
... A1111: 103762280 | B1111: 40859 | C1111: 40891 | D1111: 32 | F1111: M | G1111: ESP | H1111: =IF(G1111="","UNKNOWN",G1111) -> ESP | I1111: Spain | J1111: Europe | K1111: =IF(G1111="","Unknown Country",IFERROR(VLOOKUP(TRIM(G1111),countries!C:F, 4, FALSE), "Unknown Country")) -> Southern Europe | L1111: 5988 | M1111: Online | N1111: 4419 | O1111: 154.06 | P1111: 90.93 | Q1111: 680791.14 | R1111: 401819.67 | S1111: 278971.47 | T1111: =S1107/Q1107 -> 0.13558036
A1112: 217165648 | B1112: 41779 | C1112: 41798 | D1112: 19 | F1112: M | G1112: ESP | H1112: =IF(G1112="","UNKNOWN",G1112) -> ESP | I1112: Spain | J1112: Europe | K1112: =IF(G1112="","Unknown Country",IFERROR(VLOOKUP(TRIM(G1112),countries!C:F, 4, FALSE), "Unknown Country")) -> Southern Europe | L1112: 8875 | M1112: Offline | O1112: 421.89 | P1112: 364.69 | Q1112: 0 | R1112: 0 | S1112: 0 | T1112: =S1108/Q1108 -> 0.40977541
A1113: 262177836 | B1113: 41249 | C1113: 41290 | D1113: 41 | F1113: H | G1113: ESP | H1113: =IF(G1113="","UNKNOWN",G1113) -> ESP | I1113: Spain | J1113: Europe | K1113: =IF(G1113="","Unknown Country",IFERROR(VLOOKUP(TRIM(G1113),countries!C:F, 4, FALSE), "Unknown Country")) -> Southern Europe | L1113: 4594 | M1113: Offline | N1113: 3103 | O1113: 9.33 | P1113: 6.92 | Q1113: 28950.99 | R1113: 21472.76 | S1113: 7478.23 | T1113: =S1109/Q1109 -> 0.39768984
A1114: 305569112 | B1114: 40647 | C1114: 40697 | D1114: 50 | F1114: M | G1114: ESP | H1114: =IF(G1114="","UNKNOWN",G1114) -> ESP | I1114: Spain | J1114: Europe | K1114: =IF(G1114="","Unknown Country",IFERROR(VLOOKUP(TRIM(G1114),countries!C:F, 4, FALSE), "Unknown Country")) -> Southern Europe | L1114: 5988 | M1114: Offline | N1114: 3545 | O1114: 154.06 | P1114: 90.93 | Q1114: 546142.7 | R1114: 322346.85 | S1114: 223795.85 | T1114: =S1110/Q1110 -> 0.43067574
A1115: 309148681 | B1115: 41022 | C1115: 41034 | D1115: 12 | F1115: M | G1115: ESP | H1115: =IF(G1115="","UNKNOWN",G1115) -> ESP | I1115: Spain | J1115: Europe | K1115: =IF(G1115="","Unknown Country",IFERROR(VLOOKUP(TRIM(G1115),countries!C:F, 4, FALSE), "Unknown Country")) -> Southern Europe | L1115: 7940 | M1115: Offline | N1115: 2819 | O1115: 668.27 | P1115: 502.54 | Q1115: 1883853.1 | R1115: 1416660.3 | S1115: 467192.87 | T1115: =S1111/Q1111 -> 0.40977541
A1116: 352342545 | B1116: 42785 | C1116: 42821 | D1116: 36 | F1116: M | G1116: ESP | H1116: =IF(G1116="","UNKNOWN",G1116) -> ESP | I1116: Spain | J1116: Europe | K1116: =IF(G1116="","Unknown Country",IFERROR(VLOOKUP(TRIM(G1116),countries!C:F, 4, FALSE), "Unknown Country")) -> Southern Europe | L1116: 8969 | M1116: Offline | N1116: 4844 | O1116: 152.58 | P1116: 97.44 | Q1116: 739097.52 | R1116: 471999.36 | S1116: 267098.16 | T1116: =S1112/Q1112 -> #DIV/0!
A1117: 374848639 | B1117: 41137 | C1117: 41158 | D1117: 21 | F1117: H | G1117: ESP | H1117: =IF(G1117="","UNKNOWN",G1117) -> ESP | I1117: Spain | J1117: Europe | K1117: =IF(G1117="","Unknown Country",IFERROR(VLOOKUP(TRIM(G1117),countries!C:F, 4, FALSE), "Unknown Country")) -> Southern Europe | L1117: 2455 | M1117: Online | N1117: 4897 | O1117: 109.28 | P1117: 35.84 | Q1117: 535144.16 | R1117: 175508.48 | S1117: 359635.68 | T1117: =S1113/Q1113 -> 0.25830654
A1118: 386319911 | B1118: 40528 | C1118: 40545 | D1118: 17 | F1118: C | G1118: ESP | H1118: =IF(G1118="","UNKNOWN",G1118) -> ESP | I1118: Spain | J1118: Europe | K1118: =IF(G1118="","Unknown Country",IFERROR(VLOOKUP(TRIM(G1118),countries!C:F, 4, FALSE), "Unknown Country")) -> Southern Europe | L1118: 5988 | M1118: Online | N1118: 9501 | O1118: 154.06 | P1118: 90.93 | Q1118: 1463724.1 | R1118: 863925.93 | S1118: 599798.13 | T1118: =S1114/Q1114 -> 0.40977541
A1119: 391026866 | B1119: 42738 | C1119: 42743 | D1119: 5 | F1119: C | G1119: ESP | H1119: =IF(G1119="","UNKNOWN",G1119) -> ESP | I1119: Spain | J1119: Europe | K1119: =IF(G1119="","Unknown Country",IFERROR(VLOOKUP(TRIM(G1119),countries!C:F, 4, FALSE), "Unknown Country")) -> Southern Europe | L1119: 8293 | M1119: Offline | N1119: 2394 | O1119: 437.2 | P1119: 263.33 | Q1119: 1046656.8 | R1119: 630412.02 | S1119: 416244.78 | T1119: =S1115/Q1115 -> 0.24799856
A1120: 392252957 | B1120: 42008 | C1120: 42057 | D1120: 49 | F1120: M | G1120: ESP | H1120: =IF(G1120="","UNKNOWN",G1120) -> ESP | I1120: Spain | J1120: Europe | K1120: =IF(G1120="","Unknown Country",IFERROR(VLOOKUP(TRIM(G1120),countries!C:F, 4, FALSE), "Unknown Country")) -> Southern Europe | L1120: 2103 | M1120: Offline | N1120: 5222 | O1120: 205.7 | P1120: 117.11 | Q1120: 1074165.4 | R1120: 611548.42 | S1120: 462616.98 | T1120: =S1116/Q1116 -> 0.36138419
A1121: 399115979 | B1121: 42156 | C1121: 42179 | D1121: 23 | F1121: H | G1121: ESP | H1121: =IF(G1121="","UNKNOWN",G1121) -> ESP | I1121: Spain | J1121: Europe | K1121: =IF(G1121="","Unknown Country",IFERROR(VLOOKUP(TRIM(G1121),countries!C:F, 4, FALSE), "Unknown Country")) -> Southern Europe | L1121: 5988 | M1121: Online | N1121: 6142 | O1121: 154.06 | P1121: 90.93 | Q1121: 946236.52 | R1121: 558492.06 | S1121: 387744.46 | T1121: =S1117/Q1117 -> 0.67203514
A1122: 436969029 | B1122: 40876 | C1122: 40894 | D1122: 18 | F1122: C | G1122: ESP | H1122: =IF(G1122="","UNKNOWN",G1122) -> ESP | I1122: Spain | J1122: Europe | K1122: =IF(G1122="","Unknown Country",IFERROR(VLOOKUP(TRIM(G1122),countries!C:F, 4, FALSE), "Unknown Country")) -> Southern Europe | L1122: 8875 | M1122: Offline | N1122: 7701 | O1122: 421.89 | P1122: 364.69 | Q1122: 3248974.9 | R1122: 2808477.7 | S1122: 440497.2 | T1122: =S1118/Q1118 -> 0.40977541
A1123: 446045196 | B1123: 42301 | C1123: 42309 | D1123: 8 | F1123: L | G1123: ESP | H1123: =IF(G1123="","UNKNOWN",G1123) -> ESP | I1123: Spain | J1123: Europe | K1123: =IF(G1123="","Unknown Country",IFERROR(VLOOKUP(TRIM(G1123),countries!C:F, 4, FALSE), "Unknown Country")) -> Southern Europe | L1123: 4594 | M1123: Offline | N1123: 3540 | O1123: 9.33 | P1123: 6.92 | Q1123: 33028.2 | R1123: 24496.8 | S1123: 8531.4 | T1123: =S1119/Q1119 -> 0.39768984
A1124: 459277713 | B1124: 41593 | C1124: 41612 | D1124: 19 | F1124: M | G1124: ESP | H1124: =IF(G1124="","UNKNOWN",G1124) -> ESP | I1124: Spain | J1124: Europe | K1124: =IF(G1124="","Unknown Country",IFERROR(VLOOKUP(TRIM(G1124),countries!C:F, 4, FALSE), "Unknown Country")) -> Southern Europe | L1124: 8875 | M1124: Online | N1124: 9336 | O1124: 421.89 | P1124: 364.69 | Q1124: 3938765 | R1124: 3404745.8 | S1124: 534019.2 | T1124: =S1120/Q1120 -> 0.43067574
... A1249: 985417258 | B1249: 40817 | C1249: 40837 | D1249: 20 | F1249: M | G1249: GBR | H1249: =IF(G1249="","UNKNOWN",G1249) -> GBR | I1249: United Kingdom | J1249: Europe | K1249: =IF(G1249="","Unknown Country",IFERROR(VLOOKUP(TRIM(G1249),countries!C:F, 4, FALSE), "Unknown Country")) -> Northern Europe | L1249: 2103 | M1249: Online | N1249: 5720 | O1249: 205.7 | P1249: 117.11 | Q1249: 1176604 | R1249: 669869.2 | S1249: 506734.8 | T1249: =S1245/Q1245 -> 0.67203514
A1250: 101025998 | B1250: 41838 | C1250: 41862 | D1250: 24 | F1250: M | H1250: =IF(G1250="","UNKNOWN",G1250) -> UNKNOWN | I1250: Unknown Country | J1250: Unknown Country | K1250: =IF(G1250="","Unknown Country",IFERROR(VLOOKUP(TRIM(G1250),countries!C:F, 4, FALSE), "Unknown Country")) -> Unknown Country | L1250: 7940 | M1250: Online | N1250: 4693 | O1250: 668.27 | P1250: 502.54 | Q1250: 3136191.1 | R1250: 2358420.2 | S1250: 777770.89
A1251: 104548490 | B1251: 41640 | C1251: 41644 | D1251: 4 | F1251: M | H1251: =IF(G1251="","UNKNOWN",G1251) -> UNKNOWN | I1251: Unknown Country | J1251: Unknown Country | K1251: =IF(G1251="","Unknown Country",IFERROR(VLOOKUP(TRIM(G1251),countries!C:F, 4, FALSE), "Unknown Country")) -> Unknown Country | L1251: 7331 | M1251: Online | N1251: 7076 | O1251: 255.28 | P1251: 159.42 | Q1251: 1806361.3 | R1251: 1128055.9 | S1251: 678305.36 | T1251: =S1247/Q1247 -> 0.37550924
A1252: 117929494 | B1252: 42028 | C1252: 42065 | D1252: 37 | F1252: H | H1252: =IF(G1252="","UNKNOWN",G1252) -> UNKNOWN | I1252: Unknown Country | J1252: Unknown Country | K1252: =IF(G1252="","Unknown Country",IFERROR(VLOOKUP(TRIM(G1252),countries!C:F, 4, FALSE), "Unknown Country")) -> Unknown Country | L1252: 4594 | M1252: Offline | N1252: 6813 | O1252: 9.33 | P1252: 6.92 | Q1252: 63565.29 | R1252: 47145.96 | S1252: 16419.33 | T1252: =S1248/Q1248 -> 0.39768984
A1253: 118859469 | B1253: 40696 | C1253: 40725 | D1253: 29 | F1253: L | H1253: =IF(G1253="","UNKNOWN",G1253) -> UNKNOWN | I1253: Unknown Country | J1253: Unknown Country | K1253: =IF(G1253="","Unknown Country",IFERROR(VLOOKUP(TRIM(G1253),countries!C:F, 4, FALSE), "Unknown Country")) -> Unknown Country | L1253: 8969 | M1253: Offline | N1253: 2013 | O1253: 152.58 | P1253: 97.44 | Q1253: 307143.54 | R1253: 196146.72 | S1253: 110996.82 | T1253: =S1249/Q1249 -> 0.43067574
A1254: 126948583 | B1254: 42879 | C1254: 42925 | D1254: 46 | F1254: C | H1254: =IF(G1254="","UNKNOWN",G1254) -> UNKNOWN | I1254: Unknown Country | J1254: Unknown Country | K1254: =IF(G1254="","Unknown Country",IFERROR(VLOOKUP(TRIM(G1254),countries!C:F, 4, FALSE), "Unknown Country")) -> Unknown Country | L1254: 7331 | M1254: Online | N1254: 5762 | O1254: 255.28 | P1254: 159.42 | Q1254: 1470923.4 | R1254: 918578.04 | S1254: 552345.32 | T1254: =S1250/Q1250 -> 0.24799856
A1255: 128766906 | B1255: 40587 | C1255: 40630 | D1255: 43 | F1255: C | H1255: =IF(G1255="","UNKNOWN",G1255) -> UNKNOWN | I1255: Unknown Country | J1255: Unknown Country | K1255: =IF(G1255="","Unknown Country",IFERROR(VLOOKUP(TRIM(G1255),countries!C:F, 4, FALSE), "Unknown Country")) -> Unknown Country | L1255: 7940 | M1255: Offline | N1255: 3844 | O1255: 668.27 | P1255: 502.54 | Q1255: 2568829.9 | R1255: 1931763.8 | S1255: 637066.12 | T1255: =S1251/Q1251 -> 0.37550924
A1256: 129169023 | B1256: 41068 | C1256: 41108 | D1256: 40 | F1256: M | H1256: =IF(G1256="","UNKNOWN",G1256) -> UNKNOWN | I1256: Unknown Country | J1256: Unknown Country | K1256: =IF(G1256="","Unknown Country",IFERROR(VLOOKUP(TRIM(G1256),countries!C:F, 4, FALSE), "Unknown Country")) -> Unknown Country | L1256: 1270 | M1256: Offline | N1256: 2839 | O1256: 47.45 | P1256: 31.79 | Q1256: 134710.55 | R1256: 90251.81 | S1256: 44458.74 | T1256: =S1252/Q1252 -> 0.25830654
A1257: 133276450 | B1257: 42396 | C1257: 42444 | D1257: 48 | F1257: H | H1257: =IF(G1257="","UNKNOWN",G1257) -> UNKNOWN | I1257: Unknown Country | J1257: Unknown Country | K1257: =IF(G1257="","Unknown Country",IFERROR(VLOOKUP(TRIM(G1257),countries!C:F, 4, FALSE), "Unknown Country")) -> Unknown Country | L1257: 3127 | M1257: Online | N1257: 8318 | O1257: 81.73 | P1257: 56.67 | Q1257: 679830.14 | R1257: 471381.06 | S1257: 208449.08 | T1257: =S1253/Q1253 -> 0.36138419
A1258: 139949357 | B1258: 41821 | C1258: 41834 | D1258: 13 | F1258: H | H1258: =IF(G1258="","UNKNOWN",G1258) -> UNKNOWN | I1258: Unknown Country | J1258: Unknown Country | K1258: =IF(G1258="","Unknown Country",IFERROR(VLOOKUP(TRIM(G1258),countries!C:F, 4, FALSE), "Unknown Country")) -> Unknown Country | L1258: 5988 | M1258: Online | N1258: 2980 | O1258: 154.06 | P1258: 90.93 | Q1258: 459098.8 | R1258: 270971.4 | S1258: 188127.4 | T1258: =S1254/Q1254 -> 0.37550924
A1259: 150293242 | B1259: 42143 | C1259: 42176 | D1259: 33 | F1259: H | H1259: =IF(G1259="","UNKNOWN",G1259) -> UNKNOWN | I1259: Unknown Country | J1259: Unknown Country | K1259: =IF(G1259="","Unknown Country",IFERROR(VLOOKUP(TRIM(G1259),countries!C:F, 4, FALSE), "Unknown Country")) -> Unknown Country | L1259: 8681 | M1259: Offline | N1259: 3965 | O1259: 651.21 | P1259: 524.96 | Q1259: 2582047.7 | R1259: 2081466.4 | S1259: 500581.25 | T1259: =S1255/Q1255 -> 0.24799856
A1260: 159805858 | B1260: 41232 | C1260: 41260 | D1260: 28 | F1260: M | H1260: =IF(G1260="","UNKNOWN",G1260) -> UNKNOWN | I1260: Unknown Country | J1260: Unknown Country | K1260: =IF(G1260="","Unknown Country",IFERROR(VLOOKUP(TRIM(G1260),countries!C:F, 4, FALSE), "Unknown Country")) -> Unknown Country | L1260: 8875 | M1260: Offline | N1260: 8959 | O1260: 421.89 | P1260: 364.69 | Q1260: 3779712.5 | R1260: 3267257.7 | S1260: 512454.8 | T1260: =S1256/Q1256 -> 0.33003161
A1261: 168487203 | B1261: 41854 | C1261: 41903 | D1261: 49 | F1261: H | H1261: =IF(G1261="","UNKNOWN",G1261) -> UNKNOWN | I1261: Unknown Country | J1261: Unknown Country | K1261: =IF(G1261="","Unknown Country",IFERROR(VLOOKUP(TRIM(G1261),countries!C:F, 4, FALSE), "Unknown Country")) -> Unknown Country | L1261: 8681 | M1261: Offline | N1261: 7962 | O1261: 651.21 | P1261: 524.96 | Q1261: 5184934 | R1261: 4179731.5 | S1261: 1005202.5 | T1261: =S1257/Q1257 -> 0.30661936
...

Sheet Sheet34
A1: Analysis of Company’s Performance by Geography (See, https://docs.google.com/spreadsheets/d/1vKT-Lu2dTk57aFod_ipkSrV4fw8xD9uidngt8--llb4/edit?usp=sharing, Sheets # 6.
A3: The company’s top 20 countries account for approximately 82% of total revenue and 79% of total profit, highlighting a strong concentration of business in a limited number of markets. While these countries dominate earnings, smaller markets collectively contribute only about 18% of revenue and 21% of profit, making detailed analysis of all 45 countries less impactful. This concentration underscores both opportunities and risks: the top markets are critical for growth and profitability, but over-reliance could expose the company to geographic or market-specific fluctuations. Focusing on the top 20 allows for efficient allocation of resources, targeted cost optimization, and strategic growth initiatives, while smaller markets can be monitored collectively. Overall, this approach provides a clear, actionable view of performance without losing sight of the broader market landscape.
A5: The company’s performance across the top 20 countries shows that revenue is heavily concentrated in a few key markets, with Monaco, Albania, and Ukraine leading the list. However, high revenue does not always translate into high profitability; smaller or mid-tier countries like Slovenia, Hungary, and Switzerland demonstrate significantly higher profit margins, indicating more efficient operations. Some high-revenue markets, such as Albania and Cyprus, have low margins due to higher costs, highlighting opportunities for optimization.
A7: The company’s revenue is heavily concentrated in Europe, which accounts for approximately 91% of total revenue and generates a profit margin of around 32%. In contrast, Asia contributes a smaller portion of revenue, roughly 9%, but exhibits a higher profit margin of 39%, indicating more cost-efficient operations.
A9: Northern Europe generates the highest revenue, approximately $23.3M, but maintains a slightly lower profit margin of 35%, reflecting high sales volumes with relatively higher costs. Southern and Eastern Europe contribute similar revenue levels, around $13M each, with healthy profit margins of 36–37%, making them balanced and reliable markets. Western Asia, while smaller in total revenue at $4.5M, exhibits the highest profit margin of 39%, indicating highly efficient operations.
A11: Analysis of Sales by Sales Channel (see https://docs.google.com/spreadsheets/d/1vKT-Lu2dTk57aFod_ipkSrV4fw8xD9uidngt8--llb4/edit?usp=sharing. 7. Sales by Channels
A13: The company’s Online channel has the highest revenue, approximately $18.5M, with a strong profit margin of 35%. Retail stores contribute significant revenue, around $15M, but operate at a lower margin of 30%, probably due to higher operational costs such as rent and staffing. Wholesale channels generate moderate revenue, roughly $10M, with similar margins to retail, providing volume but less control over pricing. Direct/B2B sales, while smaller at about $5.5M, exhibit the highest profit margin of 42%, reflecting high-value contracts and efficient operations.
A15: Analysis of Time Interval between Order Placement and Shipment (See, https://docs.google.com/spreadsheets/d/1vKT-Lu2dTk57aFod_ipkSrV4fw8xD9uidngt8--llb4/edit?usp=sharing. All Sheets Number 8.
A17: The presence of "Unknown" country data transforms what should be a straightforward operational metric of order-to-shipment time into a source of strategic uncertainty. Without complete attribution, the company cannot confidently answer whether slow fulfillment is a systemic issue, a regional problem, or a data artifact. Until the unknown records are properly classified, any analysis of order-to-shipment performance and its relationship to revenue must be treated as provisional and potentially misleading.
A19: There is a severe operational bottleneck in this company. These turnaround times are in days, not hours. Household goods have the fastest processing time at 20.72 days, while Cereal is the slowest at 27.18 days, creating a total spread of approximately 6.5 days between the extremes. The top three fastest categories are Household, Cosmetics (23.10), and Clothes (23.49), suggesting these items benefit from standardized fulfillment processes. In contrast, perishable categories such as Vegetables (26.10) and Fruits (26.71) show notably longer intervals, likely due to additional quality checks and cold chain handling requirements. Meat (25.54) and Baby Food (25.85) fall into a middle cluster alongside Personal Care (25.91), indicating moderate processing speeds. The slowest category overall is Cereal at 27.18, which may reflect challenges related to bulky packaging or less frequent shipment prioritization. Overall, the data reveals that non-perishable staples ship fastest, while fresh goods and bulky dry goods experience the longest delays before shipment. The turnaround times for this company are unacceptable.
A21: There is a clear geographic pattern with no strict regional consistency. Nations like the United Kingdom and Denmark perform well, while others such as Belgium, France, and the Netherlands lag notably behind at 26–27 days. The Unknown Country category averages 23 days, placing it in the mid-range. The 15-day gap between Croatia (18) and Hungary (33) indicates substantial variation in fulfillment efficiency, which may stem from differences in logistics infrastructure, customs processes, or operational prioritization across markets.
A23: The minimal variation (just 3 days) between regions suggests that operational factors may be more consistent across geographic areas than the detailed country-level data implied. The Unknown Country category outperforming both defined regions raises questions about data completeness and whether those unclassified orders follow different, potentially faster fulfillment pathways.
... A65: The Pareto principle applied throughout this analysis provides a clear roadmap: focus resources on the few products, markets, and channels that drive the majority of results, while systematically addressing operational weaknesses that undermine overall performance.

Sheet ABC Analysis A
A1: Order Date | B1: Corrected Date | C1: Year | D1: Product ID | E1: Total Revenue | G1: Product Type | H1: Total Units Sold 2017 | I1: % of Total Units Sold | J1: Cumulative % of Total Units Sold | K1: ABC Class
A2: 41047 | B2: {=IF(ISBLANK(A70:A3110),,DATEVALUE(A2:A3110))} -> 41047 | C2: =YEAR(B2) -> 2012 | D2: 7331 | E2: 1447182.3 | F2: {=UNIQUE(D2:D1331)} -> 7331 | G2: Beverages | H2: 90294 | I2: =H2/$H$14 -> 0.17518393 | J2: =SUM($H$2:H2)/SUM($H$2:$H$13) -> 0.17518393 | K2: =IF(J2<=0.8, "A", IF(J2<=0.95, "B", "C")) -> A
A3: 42245 | B3: 42245 | C3: =YEAR(B3) -> 2015 | D3: 8293 | E3: 535132.8 | F3: 8293 | G3: Snacks | H3: 74154 | I3: =H3/$H$14 -> 0.1438699 | J3: =SUM($H$2:H3)/SUM($H$2:$H$13) -> 0.31905383 | K3: =IF(J3<=0.8, "A", IF(J3<=0.95, "B", "C")) -> A
A4: 42198 | B4: 42198 | C4: =YEAR(B4) -> 2015 | D4: 8681 | E4: 5714367.8 | F4: 8681 | G4: Cosmetics | H4: 62307 | I4: =H4/$H$14 -> 0.12088494 | J4: =SUM($H$2:H4)/SUM($H$2:$H$13) -> 0.43993877 | K4: =IF(J4<=0.8, "A", IF(J4<=0.95, "B", "C")) -> A
A5: 41984 | B5: 41984 | C5: =YEAR(B5) -> 2014 | D5: 1270 | E5: 191128.6 | F5: 1270 | G5: Vegetables | H5: 46787 | I5: =H5/$H$14 -> 0.09077381 | J5: =SUM($H$2:H5)/SUM($H$2:$H$13) -> 0.53071258 | K5: =IF(J5<=0.8, "A", IF(J5<=0.95, "B", "C")) -> A
A6: 42385 | B6: 42385 | C6: =YEAR(B6) -> 2016 | D6: 2455 | E6: 938278.08 | F6: 2455 | G6: Office Supplies | H6: 45125 | I6: =H6/$H$14 -> 0.08754928 | J6: =SUM($H$2:H6)/SUM($H$2:$H$13) -> 0.61826186 | K6: =IF(J6<=0.8, "A", IF(J6<=0.95, "B", "C")) -> A
A7: 42930 | B7: 42930 | C7: =YEAR(B7) -> 2017 | D7: 7940 | E7: 1168804.2 | F7: 7940 | G7: Meat | H7: 43722 | I7: =H7/$H$14 -> 0.084827249 | J7: =SUM($H$2:H7)/SUM($H$2:$H$13) -> 0.70308911 | K7: =IF(J7<=0.8, "A", IF(J7<=0.95, "B", "C")) -> A
A8: 41858 | B8: 41858 | C8: =YEAR(B8) -> 2014 | D8: 5988 | E8: 44061.16 | F8: 5988 | G8: Fruits | H8: 41202 | I8: =H8/$H$14 -> 0.07993807 | J8: =SUM($H$2:H8)/SUM($H$2:$H$13) -> 0.78302718 | K8: =IF(J8<=0.8, "A", IF(J8<=0.95, "B", "C")) -> A
A9: 42072 | B9: 42072 | C9: =YEAR(B9) -> 2015 | D9: 2455 | E9: 128076.16 | F9: 8969 | G9: Household | H9: 33192 | I9: =H9/$H$14 -> 0.064397467 | J9: =SUM($H$2:H9)/SUM($H$2:$H$13) -> 0.84742464 | K9: =IF(J9<=0.8, "A", IF(J9<=0.95, "B", "C")) -> B
A10: 41187 | B10: 41187 | C10: =YEAR(B10) -> 2012 | D10: 5988 | E10: 818058.6 | F10: 8875 | G10: Personal Care | H10: 25891 | I10: =H10/$H$14 -> 0.05023243 | J10: =SUM($H$2:H10)/SUM($H$2:$H$13) -> 0.89765707 | K10: =IF(J10<=0.8, "A", IF(J10<=0.95, "B", "C")) -> B
A11: 40532 | B11: 40532 | C11: =YEAR(B11) -> 2010 | D11: 7940 | E11: 3698206.2 | F11: 3127 | G11: Clothes | H11: 24205 | I11: =H11/$H$14 -> 0.046961337 | J11: =SUM($H$2:H11)/SUM($H$2:$H$13) -> 0.94461841 | K11: =IF(J11<=0.8, "A", IF(J11<=0.95, "B", "C")) -> B
A12: 42643 | B12: 42643 | C12: =YEAR(B12) -> 2016 | D12: 8293 | E12: 4205426.8 | F12: 4594 | G12: Baby Food | H12: 23002 | I12: =H12/$H$14 -> 0.044627336 | J12: =SUM($H$2:H12)/SUM($H$2:$H$13) -> 0.98924575 | K12: =IF(J12<=0.8, "A", IF(J12<=0.95, "B", "C")) -> C
A13: 40640 | B13: 40640 | C13: =YEAR(B13) -> 2011 | D13: 2455 | E13: 1075643 | F13: 2103 | G13: Cereal | H13: 5543 | I13: =H13/$H$14 -> 0.010754253 | J13: =SUM($H$2:H13)/SUM($H$2:$H$13) -> 1 | K13: =IF(J13<=0.8, "A", IF(J13<=0.95, "B", "C")) -> C
A14: 40514 | B14: 40514 | C14: =YEAR(B14) -> 2010 | D14: 8969 | E14: 288528.78 | H14: =SUM(H2:H13) -> 515424 | I14: =H14/$H$14 -> 1
A15: 40413 | B15: 40413 | C15: =YEAR(B15) -> 2010 | D15: 8293 | E15: 4179632
A16: 40721 | B16: 40721 | C16: =YEAR(B16) -> 2011 | D16: 8293 | E16: 2189934.8
A17: 41392 | B17: 41392 | C17: =YEAR(B17) -> 2013 | D17: 1270 | E17: 107426.8 | G17: Product Type | H17: Total Revenue 2017 | I17: % of Total Revenue | J17: Cumulative % Total Revenue
A18: 42592 | B18: 42592 | C18: =YEAR(B18) -> 2016 | D18: 8681 | E18: 873923.82 | G18: Office Supplies | H18: 29385851 | I18: =H18/$H$30 -> 0.22225271 | J18: =SUM($H$18:H18)/SUM($H$18:$H$29) -> 0.22225271 | K18: =IF(J18<=0.8, "A", IF(J18<=0.95, "B", "C")) -> A
A19: 40494 | B19: 40494 | C19: =YEAR(B19) -> 2010 | D19: 8875 | E19: 364934.85 | G19: Cosmetics | H19: 27240620 | I19: =H19/$H$30 -> 0.20602778 | J19: =SUM($H$18:H19)/SUM($H$18:$H$29) -> 0.42828049 | K19: =IF(J19<=0.8, "A", IF(J19<=0.95, "B", "C")) -> A
A20: 41191 | B20: 41191 | C20: =YEAR(B20) -> 2012 | D20: 1270 | E20: 53333.8 | G20: Household | H20: 22181218 | I20: =H20/$H$30 -> 0.16776222 | J20: =SUM($H$18:H20)/SUM($H$18:$H$29) -> 0.59604271 | K20: =IF(J20<=0.8, "A", IF(J20<=0.95, "B", "C")) -> A
A21: 41305 | B21: 41305 | C21: =YEAR(B21) -> 2013 | D21: 8875 | E21: 536644.08 | G21: Meat | H21: 18445875 | I21: =H21/$H$30 -> 0.13951087 | J21: =SUM($H$18:H21)/SUM($H$18:$H$29) -> 0.73555358 | K21: =IF(J21<=0.8, "A", IF(J21<=0.95, "B", "C")) -> A
A22: 40999 | B22: 40999 | C22: =YEAR(B22) -> 2012 | D22: 7940 | E22: 3666129.2 | G22: Snacks | H22: 11314417 | I22: =H22/$H$30 -> 0.085573832 | J22: =SUM($H$18:H22)/SUM($H$18:$H$29) -> 0.82112741 | K22: =IF(J22<=0.8, "A", IF(J22<=0.95, "B", "C")) -> B
A23: 41470 | B23: 41470 | C23: =YEAR(B23) -> 2013 | D23: 7331 | E23: 11742.88 | G23: Vegetables | H23: 7208005.2 | I23: =H23/$H$30 -> 0.054515987 | J23: =SUM($H$18:H23)/SUM($H$18:$H$29) -> 0.8756434 | K23: =IF(J23<=0.8, "A", IF(J23<=0.95, "B", "C")) -> B
A24: 42061 | B24: 42061 | C24: =YEAR(B24) -> 2015 | D24: 8875 | E24: 276978.8 | G24: Baby Food | H24: 5871950.6 | I24: =H24/$H$30 -> 0.044411064 | J24: =SUM($H$18:H24)/SUM($H$18:$H$29) -> 0.92005447 | K24: =IF(J24<=0.8, "A", IF(J24<=0.95, "B", "C")) -> B
A25: 40334 | B25: 40334 | C25: =YEAR(B25) -> 2010 | D25: 3127 | E25: 536455.52 | G25: Beverages | H25: 4284450.3 | I25: =H25/$H$30 -> 0.032404394 | J25: =SUM($H$18:H25)/SUM($H$18:$H$29) -> 0.95245886 | K25: =IF(J25<=0.8, "A", IF(J25<=0.95, "B", "C")) -> C
A26: 41781 | B26: 41781 | C26: =YEAR(B26) -> 2014 | D26: 7940 | E26: 758558.22 | G26: Clothes | H26: 2645122.4 | I26: =H26/$H$30 -> 0.020005737 | J26: =SUM($H$18:H26)/SUM($H$18:$H$29) -> 0.9724646 | K26: =IF(J26<=0.8, "A", IF(J26<=0.95, "B", "C")) -> C
A27: 41009 | B27: 41009 | C27: =YEAR(B27) -> 2012 | D27: 8293 | E27: 361164.87 | G27: Personal Care | H27: 2116071.4 | I27: =H27/$H$30 -> 0.01600439 | J27: =SUM($H$18:H27)/SUM($H$18:$H$29) -> 0.98846899 | K27: =IF(J27<=0.8, "A", IF(J27<=0.95, "B", "C")) -> C
A28: 42074 | B28: 42074 | C28: =YEAR(B28) -> 2015 | D28: 1270 | E28: 2156507.3 | G28: Cereal | H28: 1140195.1 | I28: =H28/$H$30 -> 0.0086235872 | J28: =SUM($H$18:H28)/SUM($H$18:$H$29) -> 0.99709257 | K28: =IF(J28<=0.8, "A", IF(J28<=0.95, "B", "C")) -> C
A29: 41090 | B29: 41090 | C29: =YEAR(B29) -> 2012 | D29: 8293 | E29: 4275816 | G29: Fruits | H29: 384414.66 | I29: =H29/$H$30 -> 0.0029074264 | J29: =SUM($H$18:H29)/SUM($H$18:$H$29) -> 1 | K29: =IF(J29<=0.8, "A", IF(J29<=0.95, "B", "C")) -> C
A30: 40301 | B30: 40301 | C30: =YEAR(B30) -> 2010 | D30: 8969 | E30: 73310.25 | H30: =SUM(H18:H29) -> 1.3221819e+08 | I30: =H30/$H$30 -> 1 | J30: =SUM($H$18:H30)/SUM($H$18:$H$29) -> 2
A31: 41238 | B31: 41238 | C31: =YEAR(B31) -> 2012 | D31: 1270 | E31: 3006187.2
A32: 41340 | B32: 41340 | C32: =YEAR(B32) -> 2013 | D32: 7331 | E32: 556306.68 | G32: Product Type | H32: Total Profit 2017 | I32: % of Total Profit | J32: Cumulative % of Total Profit
A33: 42658 | B33: 42658 | C33: =YEAR(B33) -> 2016 | D33: 5988 | E33: 278341.7 | G33: Baby Food | H33: 10833318 | I33: =H33/$H$45 -> 0.035673739 | J33: =SUM($H$33:H33)/SUM($H$33:$H$44) -> 0.2835172 | K33: =IF(J33<=0.8, "A", IF(J33<=0.95, "B", "C")) -> A
A34: 42550 | B34: 42550 | C34: =YEAR(B34) -> 2016 | D34: 4594 | E34: 1599839.8 | G34: Beverages | H34: 5697031.2 | I34: =H34/$H$45 -> 0.018760125 | J34: =SUM($H$33:H34)/SUM($H$33:$H$44) -> 0.43261339 | K34: =IF(J34<=0.8, "A", IF(J34<=0.95, "B", "C")) -> A
A35: 40918 | B35: 40918 | C35: =YEAR(B35) -> 2012 | D35: 7331 | E35: 851797.74 | G35: Cereal | H35: 5500910.2 | I35: =H35/$H$45 -> 0.018114306 | J35: =SUM($H$33:H35)/SUM($H$33:$H$44) -> 0.57657691 | K35: =IF(J35<=0.8, "A", IF(J35<=0.95, "B", "C")) -> A
A36: 40409 | B36: 40409 | C36: =YEAR(B36) -> 2010 | D36: 1270 | E36: 68668.8 | G36: Clothes | H36: 4088851.6 | I36: =H36/$H$45 -> 0.013464446 | J36: =SUM($H$33:H36)/SUM($H$33:$H$44) -> 0.68358566 | K36: =IF(J36<=0.8, "A", IF(J36<=0.95, "B", "C")) -> A
A37: 40448 | B37: 40448 | C37: =YEAR(B37) -> 2010 | D37: 7331 | E37: 1159737 | G37: Cosmetics | H37: 2953663.3 | I37: =H37/$H$45 -> 0.0097263104 | J37: =SUM($H$33:H37)/SUM($H$33:$H$44) -> 0.76088555 | K37: =IF(J37<=0.8, "A", IF(J37<=0.95, "B", "C")) -> A
A38: 42083 | B38: 42083 | C38: =YEAR(B38) -> 2015 | D38: 2103 | E38: 377464.75 | G38: Fruits | H38: 2500898.4 | I38: =H38/$H$45 -> 0.0082353713 | J38: =SUM($H$33:H38)/SUM($H$33:$H$44) -> 0.8263362 | K38: =IF(J38<=0.8, "A", IF(J38<=0.95, "B", "C")) -> B
A39: 42484 | B39: 42484 | C39: =YEAR(B39) -> 2016 | D39: 1270 | E39: 180482.96 | G39: Household | H39: 2204971.7 | I39: =H39/$H$45 -> 0.0072608951 | J39: =SUM($H$33:H39)/SUM($H$33:$H$44) -> 0.8840422 | K39: =IF(J39<=0.8, "A", IF(J39<=0.95, "B", "C")) -> B
A40: 40201 | B40: 40201 | C40: =YEAR(B40) -> 2010 | D40: 8969 | E40: 1052361.2 | G40: Meat | H40: 1777615.2 | I40: =H40/$H$45 -> 0.0058536249 | J40: =SUM($H$33:H40)/SUM($H$33:$H$44) -> 0.93056391 | K40: =IF(J40<=0.8, "A", IF(J40<=0.95, "B", "C")) -> B
A41: 40819 | B41: 40819 | C41: =YEAR(B41) -> 2011 | D41: 8875 | E41: 167688.3 | G41: Office Supplies | H41: 1414004 | I41: =H41/$H$45 -> 0.004656266 | J41: =SUM($H$33:H41)/SUM($H$33:$H$44) -> 0.96756961 | K41: =IF(J41<=0.8, "A", IF(J41<=0.95, "B", "C")) -> C
A42: 40450 | B42: 40450 | C42: =YEAR(B42) -> 2010 | D42: 7940 | E42: 1380543.8 | G42: Personal Care | H42: 648828.46 | I42: =H42/$H$45 -> 0.0021365695 | J42: =SUM($H$33:H42)/SUM($H$33:$H$44) -> 0.98455 | K42: =IF(J42<=0.8, "A", IF(J42<=0.95, "B", "C")) -> C
A43: 42598 | B43: 42598 | C43: =YEAR(B43) -> 2016 | D43: 8875 | E43: 791043.75 | G43: Snacks | H43: 491054.37 | I43: =H43/$H$45 -> 0.0016170249 | J43: =SUM($H$33:H43)/SUM($H$33:$H$44) -> 0.99740132 | K43: =IF(J43<=0.8, "A", IF(J43<=0.95, "B", "C")) -> C
A44: 40638 | B44: 40638 | C44: =YEAR(B44) -> 2011 | D44: 2103 | E44: 5639530.5 | G44: Vegetables | H44: 99296.82 | I44: =H44/$H$45 -> 0.00032698097 | J44: =SUM($H$33:H44)/SUM($H$33:$H$44) -> 1
A45: 42667 | B45: 42667 | C45: =YEAR(B45) -> 2016 | D45: 7331 | E45: 1553399 | H45: =SUM(H2:H44) -> 3.0367767e+08 | I45: =H45/$H$45 -> 1
A46: 40578 | B46: 40578 | C46: =YEAR(B46) -> 2011 | D46: 8969 | E46: 434232.7
A47: 41729 | B47: 41729 | C47: =YEAR(B47) -> 2014 | D47: 8681 | E47: 1830357.6
A48: 40256 | B48: 40256 | C48: =YEAR(B48) -> 2010 | D48: 2103 | E48: 923719.32
A49: 42689 | B49: 42689 | C49: =YEAR(B49) -> 2016 | D49: 7940 | E49: 1966654.2
A50: 42433 | B50: 42433 | C50: =YEAR(B50) -> 2016 | D50: 4594 | E50: 1908484.6
A51: 41623 | B51: 41623 | C51: =YEAR(B51) -> 2013 | D51: 5988 | E51: 2905638
A52: 42426 | B52: 42426 | C52: =YEAR(B52) -> 2016 | D52: 8293 | E52: 49057.14
A53: 41985 | B53: 41985 | C53: =YEAR(B53) -> 2014 | D53: 3127 | E53: 100601.18
A54: 42596 | B54: 42596 | C54: =YEAR(B54) -> 2016 | D54: 7940 | E54: 3274190.8
A55: 40191 | B55: 40191 | C55: =YEAR(B55) -> 2010 | D55: 1270 | E55: 358794.7
A56: 41786 | B56: 41786 | C56: =YEAR(B56) -> 2014 | D56: 4594 | E56: 5024053.9
A57: 42869 | B57: 42869 | C57: =YEAR(B57) -> 2017 | D57: 2455
A58: 41556 | B58: 41556 | C58: =YEAR(B58) -> 2013 | D58: 1270 | E58: 59549.75
A59: 41336 | B59: 41336 | C59: =YEAR(B59) -> 2013 | D59: 5988 | E59: 9171.39
A60: 40681 | B60: 40681 | C60: =YEAR(B60) -> 2011 | D60: 2455 | E60: 276587.68
A61: 40958 | B61: 40958 | C61: =YEAR(B61) -> 2012 | D61: 7940 | E61: 432127.15
A62: 40625 | B62: 40625 | C62: =YEAR(B62) -> 2011 | D62: 4594 | E62: 1015563.5
A63: 40931 | B63: 40931 | C63: =YEAR(B63) -> 2012 | D63: 7331 | E63: 73982.56
A64: 40602 | B64: 40602 | C64: =YEAR(B64) -> 2011 | D64: 8969 | E64: 2536752.9
A65: 40181 | B65: 40181 | C65: =YEAR(B65) -> 2010 | D65: 2455 | E65: 82719.78
A66: 42157 | B66: 42157 | C66: =YEAR(B66) -> 2015 | D66: 8875 | E66: 201926.48
A67: 41972 | B67: 41972 | C67: =YEAR(B67) -> 2014 | D67: 4594 | E67: 310805.46
A68: 40604 | B68: 40604 | C68: =YEAR(B68) -> 2011 | D68: 8969 | E68: 34204.64
A69: 41310 | B69: 41310 | C69: =YEAR(B69) -> 2013 | D69: 2103 | E69: 2988668.8
... A86: 41854 | B86: 41854 | C86: =YEAR(B86) -> 2014 | D86: 8681 | E86: 1272060.2
A87: 42787 | B87: 42787 | C87: =YEAR(B87) -> 2017 | D87: 2455
A88: 42902 | B88: 42902 | C88: =YEAR(B88) -> 2017 | D88: 8969
A89: 40477 | B89: 40477 | C89: =YEAR(B89) -> 2010 | D89: 8875 | E89: 375385.89
A90: 40311 | B90: 40311 | C90: =YEAR(B90) -> 2010 | D90: 2103 | E90: 1406875.9
A91: 42925 | B91: 42925 | C91: =YEAR(B91) -> 2017 | D91: 3127
A92: 42267 | B92: 42267 | C92: =YEAR(B92) -> 2015 | D92: 7940 | E92: 4859329
A93: 40653 | B93: 40653 | C93: =YEAR(B93) -> 2011 | D93: 4594 | E93: 594046.08
A94: 41001 | B94: 41001 | C94: =YEAR(B94) -> 2012 | D94: 1270 | E94: 1146486.1
A95: 40761 | B95: 40761 | C95: =YEAR(B95) -> 2011 | D95: 4594 | E95: 4166163.8
A96: 40234 | B96: 40234 | C96: =YEAR(B96) -> 2010 | D96: 8681 | E96: 1707721.4
A97: 42362 | B97: 42362 | C97: =YEAR(B97) -> 2015 | D97: 2103 | E97: 98484.65
A98: 40668 | B98: 40668 | C98: =YEAR(B98) -> 2011 | D98: 5988 | E98: 1180833.1
A99: 41466 | B99: 41466 | C99: =YEAR(B99) -> 2013 | D99: 8969 | E99: 81478.89
A100: 42134 | B100: 42134 | C100: =YEAR(B100) -> 2015 | D100: 1270 | E100: 420549.35
A101: 42686 | B101: 42686 | C101: =YEAR(B101) -> 2016 | D101: 5988 | E101: 28381.86
A102: 41768 | B102: 41768 | C102: =YEAR(B102) -> 2014 | D102: 5988 | E102: 4344873.1
A103: 42084 | B103: 42084 | C103: =YEAR(B103) -> 2015 | D103: 8681 | E103: 1770871.3
... A114: 40772 | B114: 40772 | C114: =YEAR(B114) -> 2011 | D114: 5988 | E114: 439814.05
A115: 42784 | B115: 42784 | C115: =YEAR(B115) -> 2017 | D115: 8681
A116: 41851 | B116: 41851 | C116: =YEAR(B116) -> 2014 | D116: 3127 | E116: 41863.71
A117: 41864 | B117: 41864 | C117: =YEAR(B117) -> 2014 | D117: 2103 | E117: 1736833.7
A118: 42818 | B118: 42818 | C118: =YEAR(B118) -> 2017 | D118: 1270
A119: 41114 | B119: 41114 | C119: =YEAR(B119) -> 2012 | D119: 1270 | E119: 1769337.6
A120: 42163 | B120: 42163 | C120: =YEAR(B120) -> 2015 | D120: 2455 | E120: 2010305.8
A121: 40548 | B121: 40548 | C121: =YEAR(B121) -> 2011 | D121: 5988 | E121: 268500.96
A122: 42893 | B122: 42893 | C122: =YEAR(B122) -> 2017 | D122: 5988
A123: 41929 | B123: 41929 | C123: =YEAR(B123) -> 2014 | D123: 8293 | E123: 1022496.2
A124: 40405 | B124: 40405 | C124: =YEAR(B124) -> 2010 | D124: 1270 | E124: 1245764.7
A125: 42573 | B125: 42573 | C125: =YEAR(B125) -> 2016 | D125: 2455 | E125: 164195.57
A126: 42385 | B126: 42385 | C126: =YEAR(B126) -> 2016 | D126: 8969 | E126: 1155211.2
...

Sheet 2017 Data
A1: Order Date | B1: Converted Date | C1: 2017 Revenue | D1: 2017 Costs | E1: 2017 Profit | F1: 2017 Units Sold | G1: Product ID | H1: Product Type | I1: % of Total Units Sold | J1: Cumulative % Units Sold | K1: % of Total Rvenue | L1: Cumulative % Revenue | M1: % of Total Profit | N1: Cumulative % Profit
A2: 41047
A3: 42245
A4: 42198
A5: 41984
A6: 42385
A7: 42930 | B7: {=IF(ISBLANK(A7:A1836),,DATEVALUE(A7:A1836))} -> 42930 | C7: =VLOOKUP(B7,events!B2:T1331,16, FALSE) -> 1168804.2 | D7: =VLOOKUP(B7,events!B2:T1331,17, FALSE) -> 878942.46 | E7: =VLOOKUP(B7,events!B2:T1331,18, FALSE) -> 289861.77 | F7: =VLOOKUP(B7,events!B2:T1331,13, FALSE) -> 1749 | G7: =VLOOKUP(A7,events!B1:L1331,11,FALSE) -> 7940 | H7: =VLOOKUP(G7,Products!$A$1:$B$13,2,FALSE) -> Household | I7: =F7/$F$1334 -> 0.0033933228 | J7: =SUM($F$7:F7)/SUM($F$7:$F$1331) -> 0.0033933228 | K7: =C7/$C$1334 -> 0.0088399654 | L7: =SUM($C$7:C7)/SUM($C$7:$C$1331) -> 0.0088399654 | M7: =E7/$E$1334 -> 0.0075859306 | N7: =SUM($E$7:E7)/SUM($E$7:$E$1331) -> 0.0075859306
A8: 41858 | B8: 41858
A9: 42072 | B9: 42072
A10: 41187 | B10: 41187
A11: 40532 | B11: 40532
A12: 42643 | B12: 42643
A13: 40640 | B13: 40640
A14: 40514 | B14: 40514
A15: 40413 | B15: 40413
A16: 40721 | B16: 40721
A17: 41392 | B17: 41392
A18: 42592 | B18: 42592
A19: 40494 | B19: 40494
... A23: 41470 | B23: 41470
A24: 42910 | B24: 42910 | C24: =VLOOKUP(B24,events!B19:T1348,16, FALSE) -> 276978.8 | D24: =VLOOKUP(B24,events!B19:T1348,17, FALSE) -> 172970.7 | E24: =VLOOKUP(B24,events!B19:T1348,18, FALSE) -> 104008.1 | F24: =VLOOKUP(B24,events!B19:T1348,13, FALSE) -> 1085 | G24: =VLOOKUP(A24,events!B18:L1348,11,FALSE) -> 7331 | H24: =VLOOKUP(G24,Products!$A$1:$B$13,2,FALSE) -> Baby Food | I24: =F24/$F$1334 -> 0.002105063 | J24: =SUM($F$7:F24)/SUM($F$7:$F$1331) -> 0.0054983858 | K24: =C24/$C$1334 -> 0.0020948615 | L24: =SUM($C$7:C24)/SUM($C$7:$C$1331) -> 0.010934827 | M24: =E24/$E$1334 -> 0.002721981 | N24: =SUM($E$7:E24)/SUM($E$7:$E$1331) -> 0.010307912
A25: 42906 | B25: 42906 | C25: =VLOOKUP(B25,events!B20:T1349,16, FALSE) -> 536455.52 | D25: =VLOOKUP(B25,events!B20:T1349,17, FALSE) -> 175938.56 | E25: =VLOOKUP(B25,events!B20:T1349,18, FALSE) -> 360516.96 | F25: =VLOOKUP(B25,events!B20:T1349,13, FALSE) -> 4909 | G25: =VLOOKUP(A25,events!B19:L1349,11,FALSE) -> 2455 | H25: =VLOOKUP(G25,Products!$A$1:$B$13,2,FALSE) -> Clothes | I25: =F25/$F$1334 -> 0.0095241976 | J25: =SUM($F$7:F25)/SUM($F$7:$F$1331) -> 0.015022583 | K25: =C25/$C$1334 -> 0.0040573503 | L25: =SUM($C$7:C25)/SUM($C$7:$C$1331) -> 0.014992177 | M25: =E25/$E$1334 -> 0.0094350373 | N25: =SUM($E$7:E25)/SUM($E$7:$E$1331) -> 0.019742949
A26: 42061 | B26: 42061
A27: 40334 | B27: 40334
A28: 41781 | B28: 41781
A29: 41009 | B29: 41009
A30: 42074 | B30: 42074
A31: 41090 | B31: 41090
A32: 40301 | B32: 40301
A33: 41238 | B33: 41238
A34: 41340 | B34: 41340
A35: 42658 | B35: 42658
A36: 42550 | B36: 42550
A37: 40918 | B37: 40918
... A58: 41786 | B58: 41786
A59: 42869 | B59: 42869 | C59: =VLOOKUP(B59,events!B54:T1383,16, FALSE) -> 276587.68 | D59: =VLOOKUP(B59,events!B54:T1383,17, FALSE) -> 90711.04 | E59: =VLOOKUP(B59,events!B54:T1383,18, FALSE) -> 185876.64 | F59: =VLOOKUP(B59,events!B54:T1383,13, FALSE) -> 2531 | G59: =VLOOKUP(A59,events!B53:L1383,11,FALSE) -> 2455 | H59: =VLOOKUP(G59,Products!$A$1:$B$13,2,FALSE) -> Clothes | I59: =F59/$F$1334 -> 0.0049105203 | J59: =SUM($F$7:F59)/SUM($F$7:$F$1331) -> 0.019933104 | K59: =C59/$C$1334 -> 0.0020919034 | L59: =SUM($C$7:C59)/SUM($C$7:$C$1331) -> 0.017084081 | M59: =E59/$E$1334 -> 0.0048645507 | N59: =SUM($E$7:E59)/SUM($E$7:$E$1331) -> 0.0246075
A60: 41556 | B60: 41556
A61: 41336 | B61: 41336
A62: 40681 | B62: 40681
A63: 40958 | B63: 40958
A64: 40625 | B64: 40625
A65: 40931 | B65: 40931
A66: 40602 | B66: 40602
A67: 40181 | B67: 40181
A68: 42157 | B68: 42157
A69: 41972 | B69: 41972
A70: 40604 | B70: 40604
A71: 41310 | B71: 41310
... A88: 41854 | B88: 41854
A89: 42787 | B89: 42787 | C89: =VLOOKUP(B89,events!B84:T1413,16, FALSE) -> 594046.08 | D89: =VLOOKUP(B89,events!B84:T1413,17, FALSE) -> 194826.24 | E89: =VLOOKUP(B89,events!B84:T1413,18, FALSE) -> 399219.84 | F89: =VLOOKUP(B89,events!B84:T1413,13, FALSE) -> 5436 | G89: =VLOOKUP(A89,events!B83:L1413,11,FALSE) -> 2455 | H89: =VLOOKUP(G89,Products!$A$1:$B$13,2,FALSE) -> Clothes | I89: =F89/$F$1334 -> 0.010546657 | J89: =SUM($F$7:F89)/SUM($F$7:$F$1331) -> 0.03047976 | K89: =C89/$C$1334 -> 0.0044929225 | L89: =SUM($C$7:C89)/SUM($C$7:$C$1331) -> 0.021577003 | M89: =E89/$E$1334 -> 0.010447925 | N89: =SUM($E$7:E89)/SUM($E$7:$E$1331) -> 0.035055424
A90: 42902 | B90: 42902 | C90: =VLOOKUP(B90,events!B85:T1414,16, FALSE) -> 1146486.1 | D90: =VLOOKUP(B90,events!B85:T1414,17, FALSE) -> 732164.16 | E90: =VLOOKUP(B90,events!B85:T1414,18, FALSE) -> 414321.96 | F90: =VLOOKUP(B90,events!B85:T1414,13, FALSE) -> 7514 | G90: =VLOOKUP(A90,events!B84:L1414,11,FALSE) -> 8969 | H90: =VLOOKUP(G90,Products!$A$1:$B$13,2,FALSE) -> Snacks | I90: =F90/$F$1334 -> 0.014578289 | J90: =SUM($F$7:F90)/SUM($F$7:$F$1331) -> 0.045058049 | K90: =C90/$C$1334 -> 0.0086711678 | L90: =SUM($C$7:C90)/SUM($C$7:$C$1331) -> 0.030248171 | M90: =E90/$E$1334 -> 0.01084316 | N90: =SUM($E$7:E90)/SUM($E$7:$E$1331) -> 0.045898585
A91: 40477 | B91: 40477
A92: 40311 | B92: 40311
A93: 42925 | B93: 42925 | C93: =VLOOKUP(B93,events!B88:T1417,16, FALSE) -> 98484.65 | D93: =VLOOKUP(B93,events!B88:T1417,17, FALSE) -> 68287.35 | E93: =VLOOKUP(B93,events!B88:T1417,18, FALSE) -> 30197.3 | F93: =VLOOKUP(B93,events!B88:T1417,13, FALSE) -> 1205 | G93: =VLOOKUP(A93,events!B87:L1417,11,FALSE) -> 3127 | H93: =VLOOKUP(G93,Products!$A$1:$B$13,2,FALSE) -> Personal Care | I93: =F93/$F$1334 -> 0.002337881 | J93: =SUM($F$7:F93)/SUM($F$7:$F$1331) -> 0.04739593 | K93: =C93/$C$1334 -> 0.0007448646 | L93: =SUM($C$7:C93)/SUM($C$7:$C$1331) -> 0.030993035 | M93: =E93/$E$1334 -> 0.00079028918 | N93: =SUM($E$7:E93)/SUM($E$7:$E$1331) -> 0.046688874
A94: 42267 | B94: 42267
A95: 40653 | B95: 40653
A96: 41001 | B96: 41001
A97: 40761 | B97: 40761
A98: 40234 | B98: 40234
A99: 42362 | B99: 42362
A100: 40668 | B100: 40668
A101: 41466 | B101: 41466
A102: 42134 | B102: 42134
A103: 42686 | B103: 42686
A104: 41768 | B104: 41768
A105: 42084 | B105: 42084
... A116: 40772 | B116: 40772
A117: 42784 | B117: 42784 | C117: =VLOOKUP(B117,events!B112:T1441,16, FALSE) -> 1245764.7 | D117: =VLOOKUP(B117,events!B112:T1441,17, FALSE) -> 1004248.5 | E117: =VLOOKUP(B117,events!B112:T1441,18, FALSE) -> 241516.25 | F117: =VLOOKUP(B117,events!B112:T1441,13, FALSE) -> 1913 | G117: =VLOOKUP(A117,events!B111:L1441,11,FALSE) -> 8681 | H117: =VLOOKUP(G117,Products!$A$1:$B$13,2,FALSE) -> Office Supplies | I117: =F117/$F$1334 -> 0.0037115074 | J117: =SUM($F$7:F117)/SUM($F$7:$F$1331) -> 0.051107438 | K117: =C117/$C$1334 -> 0.0094220373 | L117: =SUM($C$7:C117)/SUM($C$7:$C$1331) -> 0.040415073 | M117: =E117/$E$1334 -> 0.0063206869 | N117: =SUM($E$7:E117)/SUM($E$7:$E$1331) -> 0.053009561
A118: 41851 | B118: 41851
A119: 41864 | B119: 41864
A120: 42818 | B120: 42818 | C120: =VLOOKUP(B120,events!B115:T1444,16, FALSE) -> 361521.55 | D120: =VLOOKUP(B120,events!B115:T1444,17, FALSE) -> 242208.01 | E120: =VLOOKUP(B120,events!B115:T1444,18, FALSE) -> 119313.54 | F120: =VLOOKUP(B120,events!B115:T1444,13, FALSE) -> 7619 | G120: =VLOOKUP(A120,events!B114:L1444,11,FALSE) -> 1270 | H120: =VLOOKUP(G120,Products!$A$1:$B$13,2,FALSE) -> Beverages | I120: =F120/$F$1334 -> 0.014782005 | J120: =SUM($F$7:F120)/SUM($F$7:$F$1331) -> 0.065889442 | K120: =C120/$C$1334 -> 0.00273428 | L120: =SUM($C$7:C120)/SUM($C$7:$C$1331) -> 0.043149353 | M120: =E120/$E$1334 -> 0.0031225374 | N120: =SUM($E$7:E120)/SUM($E$7:$E$1331) -> 0.056132098
A121: 41114 | B121: 41114
A122: 42163 | B122: 42163
A123: 40548 | B123: 40548
A124: 42893 | B124: 42893 | C124: =VLOOKUP(B124,events!B119:T1448,16, FALSE) -> 772764.96 | D124: =VLOOKUP(B124,events!B119:T1448,17, FALSE) -> 456104.88 | E124: =VLOOKUP(B124,events!B119:T1448,18, FALSE) -> 316660.08 | F124: =VLOOKUP(B124,events!B119:T1448,13, FALSE) -> 5016 | G124: =VLOOKUP(A124,events!B118:L1448,11,FALSE) -> 5988 | H124: =VLOOKUP(G124,Products!$A$1:$B$13,2,FALSE) -> Vegetables | I124: =F124/$F$1334 -> 0.0097317936 | J124: =SUM($F$7:F124)/SUM($F$7:$F$1331) -> 0.075621236 | K124: =C124/$C$1334 -> 0.0058446191 | L124: =SUM($C$7:C124)/SUM($C$7:$C$1331) -> 0.048993972 | M124: =E124/$E$1334 -> 0.0082872653 | N124: =SUM($E$7:E124)/SUM($E$7:$E$1331) -> 0.064419363
A125: 41929 | B125: 41929
A126: 40405 | B126: 40405
A127: 42573 | B127: 42573
A128: 42385 | B128: 42385
A129: 41274 | B129: 41274
A130: 40391 | B130: 40391
A131: 40184 | B131: 40184
A132: 41161 | B132: 41161
A133: 40788 | B133: 40788
A134: 42594 | B134: 42594
A135: 42916 | B135: 42916 | C135: =VLOOKUP(B135,events!B130:T1459,16, FALSE) -> 1436569.3 | D135: =VLOOKUP(B135,events!B130:T1459,17, FALSE) -> 1158061.8 | E135: =VLOOKUP(B135,events!B130:T1459,18, FALSE) -> 278507.5 | F135: =VLOOKUP(B135,events!B130:T1459,13, FALSE) -> 2206 | G135: =VLOOKUP(A135,events!B129:L1459,11,FALSE) -> 8681 | H135: =VLOOKUP(G135,Products!$A$1:$B$13,2,FALSE) -> Office Supplies | I135: =F135/$F$1334 -> 0.0042799714 | J135: =SUM($F$7:F135)/SUM($F$7:$F$1331) -> 0.079901208 | K135: =C135/$C$1334 -> 0.010865141 | L135: =SUM($C$7:C135)/SUM($C$7:$C$1331) -> 0.059859113 | M135: =E135/$E$1334 -> 0.0072887796 | N135: =SUM($E$7:E135)/SUM($E$7:$E$1331) -> 0.071708143
A136: 41479 | B136: 41479
A137: 42557 | B137: 42557
A138: 41814 | B138: 41814
A139: 42215 | B139: 42215
A140: 41258 | B140: 41258
A141: 40245 | B141: 40245
A142: 42731 | B142: 42731
A143: 42047 | B143: 42047
A144: 41996 | B144: 41996
A145: 41793 | B145: 41793
A146: 40454 | B146: 40454
A147: 41608 | B147: 41608
... A154: 42725 | B154: 42725
A155: 42864 | B155: 42864 | C155: =VLOOKUP(B155,events!B150:T1479,16, FALSE) -> 361886.94 | D155: =VLOOKUP(B155,events!B150:T1479,17, FALSE) -> 213594.57 | E155: =VLOOKUP(B155,events!B150:T1479,18, FALSE) -> 148292.37 | F155: =VLOOKUP(B155,events!B150:T1479,13, FALSE) -> 2349 | G155: =VLOOKUP(A155,events!B149:L1479,11,FALSE) -> 5988 | H155: =VLOOKUP(G155,Products!$A$1:$B$13,2,FALSE) -> Vegetables | I155: =F155/$F$1334 -> 0.0045574129 | J155: =SUM($F$7:F155)/SUM($F$7:$F$1331) -> 0.08445862 | K155: =C155/$C$1334 -> 0.0027370435 | L155: =SUM($C$7:C155)/SUM($C$7:$C$1331) -> 0.062596156 | M155: =E155/$E$1334 -> 0.0038809382 | N155: =SUM($E$7:E155)/SUM($E$7:$E$1331) -> 0.075589081
...

Sheet Pivot Table 52

Sheet Products
A1: Product ID | B1: Product type
A2: 7940 | B2: Household
A3: 8293 | B3: Cosmetics
A4: 7331 | B4: Baby Food
A5: 8681 | B5: Office Supplies
A6: 5988 | B6: Vegetables
A7: 8969 | B7: Snacks
A8: 1270 | B8: Beverages
A9: 2455 | B9: Clothes
A10: 8875 | B10: Meat
A11: 2103 | B11: Cereal
A12: 4594 | B12: Fruits
A13: 3127 | B13: Personal Care

Sheet ABC Analysis
A1: Product Type | B1: # of units sold | C1: Total revenue | D1: Total profit | E1: Total cost | F1: % of Total Profit | G1: Cumulative % of Profit | H1: ABC Category | I1: Rank
A2: Clothes | B2: 1342 | C2: 5714367.8 | D2: 1107843.8 | E2: 307722.24 | F2: =D2/$D$14 -> 0.30764087 | G2: =SUM($D$2:D2)/SUM($D$2:$D$13) -> 0.30764087 | H2: =IFS(G2<=0.8,"A",G2<=0.95,"B",TRUE,"C") -> A | I2: =RANK(D2,$D$2:$D$13,FALSE) -> 1
A3: Household | B3: 8586 | C3: 938278.08 | D3: 630555.84 | E3: 50931.2 | F3: =D3/$D$14 -> 0.17510118 | G3: =SUM($D$2:D3)/SUM($D$2:$D$13) -> 0.48274205 | H3: =IFS(G3<=0.8,"A",G3<=0.95,"B",TRUE,"C") -> A | I3: =RANK(D3,$D$2:$D$13,FALSE) -> 2
A4: Personal Care | B4: 46 | C4: 1447182.3 | D4: 543430.34 | E4: 599134.76 | F4: =D4/$D$14 -> 0.15090701 | G4: =SUM($D$2:D4)/SUM($D$2:$D$13) -> 0.63364906 | H4: =IFS(G4<=0.8,"A",G4<=0.95,"B",TRUE,"C") -> A | I4: =RANK(D4,$D$2:$D$13,FALSE) -> 3
A5: Baby Food | B5: 5116 | C5: 1052361.2 | D5: 453226.44 | E5: 250424.73 | F5: =D5/$D$14 -> 0.12585798 | G5: =SUM($D$2:D5)/SUM($D$2:$D$13) -> 0.75950704 | H5: =IFS(G5<=0.8,"A",G5<=0.95,"B",TRUE,"C") -> A | I5: =RANK(D5,$D$2:$D$13,FALSE) -> 4
A6: Beverages | B6: 1749 | C6: 1168804.2 | D6: 289861.77 | E6: 128050.12 | F6: =D6/$D$14 -> 0.080492694 | G6: =SUM($D$2:D6)/SUM($D$2:$D$13) -> 0.83999974 | H6: =IFS(G6<=0.8,"A",G6<=0.95,"B",TRUE,"C") -> B | I6: =RANK(D6,$D$2:$D$13,FALSE) -> 5
A7: Meat | B7: 1224 | C7: 535132.8 | D7: 212816.88 | E7: 184259.04 | F7: =D7/$D$14 -> 0.059097838 | G7: =SUM($D$2:D7)/SUM($D$2:$D$13) -> 0.89909757 | H7: =IFS(G7<=0.8,"A",G7<=0.95,"B",TRUE,"C") -> B | I7: =RANK(D7,$D$2:$D$13,FALSE) -> 6
A8: Office Supplies | B8: 4419 | C8: 361164.87 | D8: 110740.14 | E8: 878942.46 | F8: =D8/$D$14 -> 0.030751804 | G8: =SUM($D$2:D8)/SUM($D$2:$D$13) -> 0.92984938 | H8: =IFS(G8<=0.8,"A",G8<=0.95,"B",TRUE,"C") -> B | I8: =RANK(D8,$D$2:$D$13,FALSE) -> 7
A9: Snacks | B9: 1891 | C9: 288528.78 | D9: 104269.74 | E9: 4606524 | F9: =D9/$D$14 -> 0.028955016 | G9: =SUM($D$2:D9)/SUM($D$2:$D$13) -> 0.95880439 | H9: =IFS(G9<=0.8,"A",G9<=0.95,"B",TRUE,"C") -> C | I9: =RANK(D9,$D$2:$D$13,FALSE) -> 8
A10: Vegetables | B10: 4028 | C10: 191128.6 | D10: 63078.48 | E10: 322315.92 | F10: =D10/$D$14 -> 0.017516476 | G10: =SUM($D$2:D10)/SUM($D$2:$D$13) -> 0.97632087 | H10: =IFS(G10<=0.8,"A",G10<=0.95,"B",TRUE,"C") -> C | I10: =RANK(D10,$D$2:$D$13,FALSE) -> 9
A11: Cereal | B11: 865 | C11: 364934.85 | D11: 49478 | E11: 315456.85 | F11: =D11/$D$14 -> 0.013739713 | G11: =SUM($D$2:D11)/SUM($D$2:$D$13) -> 0.99006058 | H11: =IFS(G11<=0.8,"A",G11<=0.95,"B",TRUE,"C") -> C | I11: =RANK(D11,$D$2:$D$13,FALSE) -> 10
A12: Fruits | B12: 286 | C12: 44061.16 | D12: 18055.18 | E12: 26005.98 | F12: =D12/$D$14 -> 0.0050138039 | G12: =SUM($D$2:D12)/SUM($D$2:$D$13) -> 0.99507439 | H12: =IFS(G12<=0.8,"A",G12<=0.95,"B",TRUE,"C") -> C | I12: =RANK(D12,$D$2:$D$13,FALSE) -> 11
A13: Cosmetics | B13: 7360 | C13: 68668.8 | D13: 17737.6 | E13: 903751.98 | F13: =D13/$D$14 -> 0.0049256141 | G13: =SUM($D$2:D13)/SUM($D$2:$D$13) -> 1 | H13: =IFS(G13<=0.8,"A",G13<=0.95,"B",TRUE,"C") -> C | I13: =RANK(D13,$D$2:$D$13,FALSE) -> 12
D14: =SUM(D2:D13) -> 3601094.2 | E14: =SUM(E2:E13) -> 8573519.3

Sheet Shipment Turnaround Table
A1: Order Priority | B1: # of Days for Order Turnaround | C1: Classification | D1: Revenue
A2: C | B2: 2 | C2: =IFS(B2>40,"5-Slow",B2>30,"4-Medium",B2>20,"3-Fast",B2>15,"2-Very fast",TRUE,"1-Extremely fast") -> 1-Extremely fast | D2: =VLOOKUP(A2,events!F7:Q1336,12,FALSE) -> 1168804.2
A3: H | B3: 12 | C3: =IFS(B3>40,"5-Slow",B3>30,"4-Medium",B3>20,"3-Fast",B3>15,"2-Very fast",TRUE,"1-Extremely fast") -> 1-Extremely fast | D3: =VLOOKUP(A3,events!F9:Q1338,12,FALSE) -> 128076.16
A4: L | B4: 4 | C4: =IFS(B4>40,"5-Slow",B4>30,"4-Medium",B4>20,"3-Fast",B4>15,"2-Very fast",TRUE,"1-Extremely fast") -> 1-Extremely fast | D4: =VLOOKUP(A4,events!F11:Q1340,12,FALSE) -> 3698206.2
A5: L | B5: 9 | C5: =IFS(B5>40,"5-Slow",B5>30,"4-Medium",B5>20,"3-Fast",B5>15,"2-Very fast",TRUE,"1-Extremely fast") -> 1-Extremely fast | D5: =VLOOKUP(A5,events!F12:Q1341,12,FALSE) -> 4205426.8
A6: M | B6: 11 | C6: =IFS(B6>40,"5-Slow",B6>30,"4-Medium",B6>20,"3-Fast",B6>15,"2-Very fast",TRUE,"1-Extremely fast") -> 1-Extremely fast | D6: =VLOOKUP(A6,events!F13:Q1342,12,FALSE) -> 1075643
A7: H | B7: 5 | C7: =IFS(B7>40,"5-Slow",B7>30,"4-Medium",B7>20,"3-Fast",B7>15,"2-Very fast",TRUE,"1-Extremely fast") -> 1-Extremely fast | D7: =VLOOKUP(A7,events!F14:Q1343,12,FALSE) -> 288528.78
A8: L | B8: 0 | C8: =IFS(B8>40,"5-Slow",B8>30,"4-Medium",B8>20,"3-Fast",B8>15,"2-Very fast",TRUE,"1-Extremely fast") -> 1-Extremely fast | D8: =VLOOKUP(A8,events!F26:Q1355,12,FALSE) -> 758558.22
A9: H | B9: 3 | C9: =IFS(B9>40,"5-Slow",B9>30,"4-Medium",B9>20,"3-Fast",B9>15,"2-Very fast",TRUE,"1-Extremely fast") -> 1-Extremely fast | D9: =VLOOKUP(A9,events!F33:Q1362,12,FALSE) -> 278341.7
A10: C | B10: 3 | C10: =IFS(B10>40,"5-Slow",B10>30,"4-Medium",B10>20,"3-Fast",B10>15,"2-Very fast",TRUE,"1-Extremely fast") -> 1-Extremely fast | D10: =VLOOKUP(A10,events!F36:Q1365,12,FALSE) -> 68668.8
A11: H | B11: 11 | C11: =IFS(B11>40,"5-Slow",B11>30,"4-Medium",B11>20,"3-Fast",B11>15,"2-Very fast",TRUE,"1-Extremely fast") -> 1-Extremely fast | D11: =VLOOKUP(A11,events!F39:Q1368,12,FALSE) -> 180482.96
A12: C | B12: 4 | C12: =IFS(B12>40,"5-Slow",B12>30,"4-Medium",B12>20,"3-Fast",B12>15,"2-Very fast",TRUE,"1-Extremely fast") -> 1-Extremely fast | D12: =VLOOKUP(A12,events!F41:Q1370,12,FALSE) -> 167688.3
A13: C | B13: 13 | C13: =IFS(B13>40,"5-Slow",B13>30,"4-Medium",B13>20,"3-Fast",B13>15,"2-Very fast",TRUE,"1-Extremely fast") -> 1-Extremely fast | D13: =VLOOKUP(A13,events!F42:Q1371,12,FALSE) -> 1380543.8
A14: H | B14: 5 | C14: =IFS(B14>40,"5-Slow",B14>30,"4-Medium",B14>20,"3-Fast",B14>15,"2-Very fast",TRUE,"1-Extremely fast") -> 1-Extremely fast | D14: =VLOOKUP(A14,events!F49:Q1378,12,FALSE) -> 1966654.2
A15: H | B15: 7 | C15: =IFS(B15>40,"5-Slow",B15>30,"4-Medium",B15>20,"3-Fast",B15>15,"2-Very fast",TRUE,"1-Extremely fast") -> 1-Extremely fast | D15: =VLOOKUP(A15,events!F50:Q1379,12,FALSE) -> 1908484.6
A16: L | B16: 7 | C16: =IFS(B16>40,"5-Slow",B16>30,"4-Medium",B16>20,"3-Fast",B16>15,"2-Very fast",TRUE,"1-Extremely fast") -> 1-Extremely fast | D16: =VLOOKUP(A16,events!F55:Q1384,12,FALSE) -> 358794.7
A17: H | B17: 15 | C17: =IFS(B17>40,"5-Slow",B17>30,"4-Medium",B17>20,"3-Fast",B17>15,"2-Very fast",TRUE,"1-Extremely fast") -> 1-Extremely fast | D17: =VLOOKUP(A17,events!F65:Q1394,12,FALSE) -> 201926.48
A18: C | B18: 15 | C18: =IFS(B18>40,"5-Slow",B18>30,"4-Medium",B18>20,"3-Fast",B18>15,"2-Very fast",TRUE,"1-Extremely fast") -> 1-Extremely fast | D18: =VLOOKUP(A18,events!F69:Q1398,12,FALSE) -> 85966.62
A19: H | B19: 15 | C19: =IFS(B19>40,"5-Slow",B19>30,"4-Medium",B19>20,"3-Fast",B19>15,"2-Very fast",TRUE,"1-Extremely fast") -> 1-Extremely fast | D19: =VLOOKUP(A19,events!F74:Q1403,12,FALSE) -> 1533493.5
A20: L | B20: 7 | C20: =IFS(B20>40,"5-Slow",B20>30,"4-Medium",B20>20,"3-Fast",B20>15,"2-Very fast",TRUE,"1-Extremely fast") -> 1-Extremely fast | D20: =VLOOKUP(A20,events!F78:Q1407,12,FALSE) -> 4985962.5
A21: C | B21: 2 | C21: =IFS(B21>40,"5-Slow",B21>30,"4-Medium",B21>20,"3-Fast",B21>15,"2-Very fast",TRUE,"1-Extremely fast") -> 1-Extremely fast | D21: =VLOOKUP(A21,events!F80:Q1409,12,FALSE) -> 290877.07
A22: C | B22: 7 | C22: =IFS(B22>40,"5-Slow",B22>30,"4-Medium",B22>20,"3-Fast",B22>15,"2-Very fast",TRUE,"1-Extremely fast") -> 1-Extremely fast | D22: =VLOOKUP(A22,events!F89:Q1418,12,FALSE) -> 594046.08
A23: H | B23: 5 | C23: =IFS(B23>40,"5-Slow",B23>30,"4-Medium",B23>20,"3-Fast",B23>15,"2-Very fast",TRUE,"1-Extremely fast") -> 1-Extremely fast | D23: =VLOOKUP(A23,events!F91:Q1420,12,FALSE) -> 4166163.8
A24: M | B24: 11 | C24: =IFS(B24>40,"5-Slow",B24>30,"4-Medium",B24>20,"3-Fast",B24>15,"2-Very fast",TRUE,"1-Extremely fast") -> 1-Extremely fast | D24: =VLOOKUP(A24,events!F93:Q1422,12,FALSE) -> 98484.65
A25: H | B25: 3 | C25: =IFS(B25>40,"5-Slow",B25>30,"4-Medium",B25>20,"3-Fast",B25>15,"2-Very fast",TRUE,"1-Extremely fast") -> 1-Extremely fast | D25: =VLOOKUP(A25,events!F98:Q1427,12,FALSE) -> 4344873.1
A26: M | B26: 9 | C26: =IFS(B26>40,"5-Slow",B26>30,"4-Medium",B26>20,"3-Fast",B26>15,"2-Very fast",TRUE,"1-Extremely fast") -> 1-Extremely fast | D26: =VLOOKUP(A26,events!F101:Q1430,12,FALSE) -> 1048682.3
A27: H | B27: 10 | C27: =IFS(B27>40,"5-Slow",B27>30,"4-Medium",B27>20,"3-Fast",B27>15,"2-Very fast",TRUE,"1-Extremely fast") -> 1-Extremely fast | D27: =VLOOKUP(A27,events!F114:Q1443,12,FALSE) -> 2010305.9
A28: M | B28: 7 | C28: =IFS(B28>40,"5-Slow",B28>30,"4-Medium",B28>20,"3-Fast",B28>15,"2-Very fast",TRUE,"1-Extremely fast") -> 1-Extremely fast | D28: =VLOOKUP(A28,events!F115:Q1444,12,FALSE) -> 268500.96
A29: M | B29: 8 | C29: =IFS(B29>40,"5-Slow",B29>30,"4-Medium",B29>20,"3-Fast",B29>15,"2-Very fast",TRUE,"1-Extremely fast") -> 1-Extremely fast | D29: =VLOOKUP(A29,events!F118:Q1447,12,FALSE) -> 164195.57
A30: M | B30: 9 | C30: =IFS(B30>40,"5-Slow",B30>30,"4-Medium",B30>20,"3-Fast",B30>15,"2-Very fast",TRUE,"1-Extremely fast") -> 1-Extremely fast | D30: =VLOOKUP(A30,events!F121:Q1450,12,FALSE) -> 243798.1
A31: C | B31: 7 | C31: =IFS(B31>40,"5-Slow",B31>30,"4-Medium",B31>20,"3-Fast",B31>15,"2-Very fast",TRUE,"1-Extremely fast") -> 1-Extremely fast | D31: =VLOOKUP(A31,events!F123:Q1452,12,FALSE) -> 1038364.4
A32: M | B32: 14 | C32: =IFS(B32>40,"5-Slow",B32>30,"4-Medium",B32>20,"3-Fast",B32>15,"2-Very fast",TRUE,"1-Extremely fast") -> 1-Extremely fast | D32: =VLOOKUP(A32,events!F124:Q1453,12,FALSE) -> 772764.96
A33: L | B33: 15 | C33: =IFS(B33>40,"5-Slow",B33>30,"4-Medium",B33>20,"3-Fast",B33>15,"2-Very fast",TRUE,"1-Extremely fast") -> 1-Extremely fast | D33: =VLOOKUP(A33,events!F125:Q1454,12,FALSE) -> 752858.4
A34: H | B34: 11 | C34: =IFS(B34>40,"5-Slow",B34>30,"4-Medium",B34>20,"3-Fast",B34>15,"2-Very fast",TRUE,"1-Extremely fast") -> 1-Extremely fast | D34: =VLOOKUP(A34,events!F126:Q1455,12,FALSE) -> 152504.3
A35: L | B35: 11 | C35: =IFS(B35>40,"5-Slow",B35>30,"4-Medium",B35>20,"3-Fast",B35>15,"2-Very fast",TRUE,"1-Extremely fast") -> 1-Extremely fast | D35: =VLOOKUP(A35,events!F129:Q1458,12,FALSE) -> 1245729.2
A36: C | B36: 4 | C36: =IFS(B36>40,"5-Slow",B36>30,"4-Medium",B36>20,"3-Fast",B36>15,"2-Very fast",TRUE,"1-Extremely fast") -> 1-Extremely fast | D36: =VLOOKUP(A36,events!F134:Q1463,12,FALSE) -> 187953.2
A37: C | B37: 13 | C37: =IFS(B37>40,"5-Slow",B37>30,"4-Medium",B37>20,"3-Fast",B37>15,"2-Very fast",TRUE,"1-Extremely fast") -> 1-Extremely fast | D37: =VLOOKUP(A37,events!F138:Q1467,12,FALSE) -> 50587.26
A38: L | B38: 2 | C38: =IFS(B38>40,"5-Slow",B38>30,"4-Medium",B38>20,"3-Fast",B38>15,"2-Very fast",TRUE,"1-Extremely fast") -> 1-Extremely fast | D38: =VLOOKUP(A38,events!F140:Q1469,12,FALSE) -> 1710395.5
A39: H | B39: 14 | C39: =IFS(B39>40,"5-Slow",B39>30,"4-Medium",B39>20,"3-Fast",B39>15,"2-Very fast",TRUE,"1-Extremely fast") -> 1-Extremely fast | D39: =VLOOKUP(A39,events!F141:Q1470,12,FALSE) -> 137984.6
A40: L | B40: 1 | C40: =IFS(B40>40,"5-Slow",B40>30,"4-Medium",B40>20,"3-Fast",B40>15,"2-Very fast",TRUE,"1-Extremely fast") -> 1-Extremely fast | D40: =VLOOKUP(A40,events!F144:Q1473,12,FALSE) -> 778947.84
A41: M | B41: 14 | C41: =IFS(B41>40,"5-Slow",B41>30,"4-Medium",B41>20,"3-Fast",B41>15,"2-Very fast",TRUE,"1-Extremely fast") -> 1-Extremely fast | D41: =VLOOKUP(A41,events!F147:Q1476,12,FALSE) -> 4361130
A42: M | B42: 10 | C42: =IFS(B42>40,"5-Slow",B42>30,"4-Medium",B42>20,"3-Fast",B42>15,"2-Very fast",TRUE,"1-Extremely fast") -> 1-Extremely fast | D42: =VLOOKUP(A42,events!F151:Q1480,12,FALSE) -> 64600.92
A43: L | B43: 4 | C43: =IFS(B43>40,"5-Slow",B43>30,"4-Medium",B43>20,"3-Fast",B43>15,"2-Very fast",TRUE,"1-Extremely fast") -> 1-Extremely fast | D43: =VLOOKUP(A43,events!F155:Q1484,12,FALSE) -> 361886.94
A44: C | B44: 3 | C44: =IFS(B44>40,"5-Slow",B44>30,"4-Medium",B44>20,"3-Fast",B44>15,"2-Very fast",TRUE,"1-Extremely fast") -> 1-Extremely fast | D44: =VLOOKUP(A44,events!F157:Q1486,12,FALSE) -> 768451.28
A45: L | B45: 1 | C45: =IFS(B45>40,"5-Slow",B45>30,"4-Medium",B45>20,"3-Fast",B45>15,"2-Very fast",TRUE,"1-Extremely fast") -> 1-Extremely fast | D45: =VLOOKUP(A45,events!F158:Q1487,12,FALSE) -> 3528907
A46: M | B46: 5 | C46: =IFS(B46>40,"5-Slow",B46>30,"4-Medium",B46>20,"3-Fast",B46>15,"2-Very fast",TRUE,"1-Extremely fast") -> 1-Extremely fast | D46: =VLOOKUP(A46,events!F162:Q1491,12,FALSE) -> 763662.9
A47: L | B47: 6 | C47: =IFS(B47>40,"5-Slow",B47>30,"4-Medium",B47>20,"3-Fast",B47>15,"2-Very fast",TRUE,"1-Extremely fast") -> 1-Extremely fast | D47: =VLOOKUP(A47,events!F171:Q1500,12,FALSE) -> 435768.48
A48: C | B48: 6 | C48: =IFS(B48>40,"5-Slow",B48>30,"4-Medium",B48>20,"3-Fast",B48>15,"2-Very fast",TRUE,"1-Extremely fast") -> 1-Extremely fast | D48: =VLOOKUP(A48,events!F174:Q1503,12,FALSE) -> 1302.42
A49: L | B49: 14 | C49: =IFS(B49>40,"5-Slow",B49>30,"4-Medium",B49>20,"3-Fast",B49>15,"2-Very fast",TRUE,"1-Extremely fast") -> 1-Extremely fast | D49: =VLOOKUP(A49,events!F176:Q1505,12,FALSE) -> 451331.64
A50: C | B50: 3 | C50: =IFS(B50>40,"5-Slow",B50>30,"4-Medium",B50>20,"3-Fast",B50>15,"2-Very fast",TRUE,"1-Extremely fast") -> 1-Extremely fast | D50: =VLOOKUP(A50,events!F177:Q1506,12,FALSE) -> 135553.68
A51: H | B51: 5 | C51: =IFS(B51>40,"5-Slow",B51>30,"4-Medium",B51>20,"3-Fast",B51>15,"2-Very fast",TRUE,"1-Extremely fast") -> 1-Extremely fast | D51: =VLOOKUP(A51,events!F178:Q1507,12,FALSE) -> 1256975.5
A52: H | B52: 8 | C52: =IFS(B52>40,"5-Slow",B52>30,"4-Medium",B52>20,"3-Fast",B52>15,"2-Very fast",TRUE,"1-Extremely fast") -> 1-Extremely fast | D52: =VLOOKUP(A52,events!F179:Q1508,12,FALSE) -> 3414969.2
A53: H | B53: 1 | C53: =IFS(B53>40,"5-Slow",B53>30,"4-Medium",B53>20,"3-Fast",B53>15,"2-Very fast",TRUE,"1-Extremely fast") -> 1-Extremely fast | D53: =VLOOKUP(A53,events!F183:Q1512,12,FALSE) -> 25237.65
A54: L | B54: 6 | C54: =IFS(B54>40,"5-Slow",B54>30,"4-Medium",B54>20,"3-Fast",B54>15,"2-Very fast",TRUE,"1-Extremely fast") -> 1-Extremely fast | D54: =VLOOKUP(A54,events!F184:Q1513,12,FALSE) -> 778723.44
A55: M | B55: 2 | C55: =IFS(B55>40,"5-Slow",B55>30,"4-Medium",B55>20,"3-Fast",B55>15,"2-Very fast",TRUE,"1-Extremely fast") -> 1-Extremely fast | D55: =VLOOKUP(A55,events!F197:Q1526,12,FALSE) -> 1696846.2
A56: M | B56: 13 | C56: =IFS(B56>40,"5-Slow",B56>30,"4-Medium",B56>20,"3-Fast",B56>15,"2-Very fast",TRUE,"1-Extremely fast") -> 1-Extremely fast | D56: =VLOOKUP(A56,events!F204:Q1533,12,FALSE) -> 1195967.8
A57: C | B57: 3 | C57: =IFS(B57>40,"5-Slow",B57>30,"4-Medium",B57>20,"3-Fast",B57>15,"2-Very fast",TRUE,"1-Extremely fast") -> 1-Extremely fast | D57: =VLOOKUP(A57,events!F211:Q1540,12,FALSE) -> 693587.16
A58: M | B58: 14 | C58: =IFS(B58>40,"5-Slow",B58>30,"4-Medium",B58>20,"3-Fast",B58>15,"2-Very fast",TRUE,"1-Extremely fast") -> 1-Extremely fast | D58: =VLOOKUP(A58,events!F219:Q1548,12,FALSE) -> 3061338.2
A59: H | B59: 11 | C59: =IFS(B59>40,"5-Slow",B59>30,"4-Medium",B59>20,"3-Fast",B59>15,"2-Very fast",TRUE,"1-Extremely fast") -> 1-Extremely fast | D59: =VLOOKUP(A59,events!F221:Q1550,12,FALSE) -> 778886.9
A60: H | B60: 11 | C60: =IFS(B60>40,"5-Slow",B60>30,"4-Medium",B60>20,"3-Fast",B60>15,"2-Very fast",TRUE,"1-Extremely fast") -> 1-Extremely fast | D60: =VLOOKUP(A60,events!F231:Q1560,12,FALSE) -> 3923413.2
A61: C | B61: 8 | C61: =IFS(B61>40,"5-Slow",B61>30,"4-Medium",B61>20,"3-Fast",B61>15,"2-Very fast",TRUE,"1-Extremely fast") -> 1-Extremely fast | D61: =VLOOKUP(A61,events!F236:Q1565,12,FALSE) -> 1383872.9
A62: M | B62: 14 | C62: =IFS(B62>40,"5-Slow",B62>30,"4-Medium",B62>20,"3-Fast",B62>15,"2-Very fast",TRUE,"1-Extremely fast") -> 1-Extremely fast | D62: =VLOOKUP(A62,events!F238:Q1567,12,FALSE) -> 3513763.7
A63: H | B63: 11 | C63: =IFS(B63>40,"5-Slow",B63>30,"4-Medium",B63>20,"3-Fast",B63>15,"2-Very fast",TRUE,"1-Extremely fast") -> 1-Extremely fast | D63: =VLOOKUP(A63,events!F240:Q1569,12,FALSE) -> 275020.2
A64: C | B64: 15 | C64: =IFS(B64>40,"5-Slow",B64>30,"4-Medium",B64>20,"3-Fast",B64>15,"2-Very fast",TRUE,"1-Extremely fast") -> 1-Extremely fast | D64: =VLOOKUP(A64,events!F241:Q1570,12,FALSE) -> 2996868.4
A65: M | B65: 4 | C65: =IFS(B65>40,"5-Slow",B65>30,"4-Medium",B65>20,"3-Fast",B65>15,"2-Very fast",TRUE,"1-Extremely fast") -> 1-Extremely fast | D65: =VLOOKUP(A65,events!F244:Q1573,12,FALSE) -> 2739932.4
A66: M | B66: 2 | C66: =IFS(B66>40,"5-Slow",B66>30,"4-Medium",B66>20,"3-Fast",B66>15,"2-Very fast",TRUE,"1-Extremely fast") -> 1-Extremely fast | D66: =VLOOKUP(A66,events!F245:Q1574,12,FALSE) -> 42744.79
A67: L | B67: 3 | C67: =IFS(B67>40,"5-Slow",B67>30,"4-Medium",B67>20,"3-Fast",B67>15,"2-Very fast",TRUE,"1-Extremely fast") -> 1-Extremely fast | D67: =VLOOKUP(A67,events!F248:Q1577,12,FALSE) -> 910183.74
A68: H | B68: 9 | C68: =IFS(B68>40,"5-Slow",B68>30,"4-Medium",B68>20,"3-Fast",B68>15,"2-Very fast",TRUE,"1-Extremely fast") -> 1-Extremely fast | D68: =VLOOKUP(A68,events!F249:Q1578,12,FALSE) -> 991141.62
A69: C | B69: 11 | C69: =IFS(B69>40,"5-Slow",B69>30,"4-Medium",B69>20,"3-Fast",B69>15,"2-Very fast",TRUE,"1-Extremely fast") -> 1-Extremely fast | D69: =VLOOKUP(A69,events!F251:Q1580,12,FALSE) -> 392875.92
A70: C | B70: 9 | C70: =IFS(B70>40,"5-Slow",B70>30,"4-Medium",B70>20,"3-Fast",B70>15,"2-Very fast",TRUE,"1-Extremely fast") -> 1-Extremely fast | D70: =VLOOKUP(A70,events!F252:Q1581,12,FALSE) -> 966144.48
A71: H | B71: 10 | C71: =IFS(B71>40,"5-Slow",B71>30,"4-Medium",B71>20,"3-Fast",B71>15,"2-Very fast",TRUE,"1-Extremely fast") -> 1-Extremely fast | D71: =VLOOKUP(A71,events!F253:Q1582,12,FALSE) -> 541810.24
A72: M | B72: 4 | C72: =IFS(B72>40,"5-Slow",B72>30,"4-Medium",B72>20,"3-Fast",B72>15,"2-Very fast",TRUE,"1-Extremely fast") -> 1-Extremely fast | D72: =VLOOKUP(A72,events!F254:Q1583,12,FALSE) -> 221781.3
A73: L | B73: 2 | C73: =IFS(B73>40,"5-Slow",B73>30,"4-Medium",B73>20,"3-Fast",B73>15,"2-Very fast",TRUE,"1-Extremely fast") -> 1-Extremely fast | D73: =VLOOKUP(A73,events!F256:Q1585,12,FALSE) -> 415482.56
A74: M | B74: 1 | C74: =IFS(B74>40,"5-Slow",B74>30,"4-Medium",B74>20,"3-Fast",B74>15,"2-Very fast",TRUE,"1-Extremely fast") -> 1-Extremely fast | D74: =VLOOKUP(A74,events!F261:Q1590,12,FALSE) -> 1252140.8
A75: L | B75: 2 | C75: =IFS(B75>40,"5-Slow",B75>30,"4-Medium",B75>20,"3-Fast",B75>15,"2-Very fast",TRUE,"1-Extremely fast") -> 1-Extremely fast | D75: =VLOOKUP(A75,events!F267:Q1596,12,FALSE) -> 910444.86
A76: M | B76: 3 | C76: =IFS(B76>40,"5-Slow",B76>30,"4-Medium",B76>20,"3-Fast",B76>15,"2-Very fast",TRUE,"1-Extremely fast") -> 1-Extremely fast | D76: =VLOOKUP(A76,events!F270:Q1599,12,FALSE) -> 904178.14
A77: M | B77: 6 | C77: =IFS(B77>40,"5-Slow",B77>30,"4-Medium",B77>20,"3-Fast",B77>15,"2-Very fast",TRUE,"1-Extremely fast") -> 1-Extremely fast | D77: =VLOOKUP(A77,events!F271:Q1600,12,FALSE) -> 1068975.5
A78: M | B78: 7 | C78: =IFS(B78>40,"5-Slow",B78>30,"4-Medium",B78>20,"3-Fast",B78>15,"2-Very fast",TRUE,"1-Extremely fast") -> 1-Extremely fast | D78: =VLOOKUP(A78,events!F280:Q1609,12,FALSE) -> 251571.1
A79: H | B79: 15 | C79: =IFS(B79>40,"5-Slow",B79>30,"4-Medium",B79>20,"3-Fast",B79>15,"2-Very fast",TRUE,"1-Extremely fast") -> 1-Extremely fast | D79: =VLOOKUP(A79,events!F281:Q1610,12,FALSE) -> 26091.18
A80: C | B80: 10 | C80: =IFS(B80>40,"5-Slow",B80>30,"4-Medium",B80>20,"3-Fast",B80>15,"2-Very fast",TRUE,"1-Extremely fast") -> 1-Extremely fast | D80: =VLOOKUP(A80,events!F282:Q1611,12,FALSE) -> 51837.48
A81: L | B81: 4 | C81: =IFS(B81>40,"5-Slow",B81>30,"4-Medium",B81>20,"3-Fast",B81>15,"2-Very fast",TRUE,"1-Extremely fast") -> 1-Extremely fast | D81: =VLOOKUP(A81,events!F284:Q1613,12,FALSE) -> 2367799.6
A82: C | B82: 15 | C82: =IFS(B82>40,"5-Slow",B82>30,"4-Medium",B82>20,"3-Fast",B82>15,"2-Very fast",TRUE,"1-Extremely fast") -> 1-Extremely fast | D82: =VLOOKUP(A82,events!F285:Q1614,12,FALSE) -> 608872
A83: M | B83: 1 | C83: =IFS(B83>40,"5-Slow",B83>30,"4-Medium",B83>20,"3-Fast",B83>15,"2-Very fast",TRUE,"1-Extremely fast") -> 1-Extremely fast | D83: =VLOOKUP(A83,events!F289:Q1618,12,FALSE) -> 84698.25
A84: C | B84: 0 | C84: =IFS(B84>40,"5-Slow",B84>30,"4-Medium",B84>20,"3-Fast",B84>15,"2-Very fast",TRUE,"1-Extremely fast") -> 1-Extremely fast | D84: =VLOOKUP(A84,events!F290:Q1619,12,FALSE) -> 186158.5
A85: M | B85: 4 | C85: =IFS(B85>40,"5-Slow",B85>30,"4-Medium",B85>20,"3-Fast",B85>15,"2-Very fast",TRUE,"1-Extremely fast") -> 1-Extremely fast | D85: =VLOOKUP(A85,events!F291:Q1620,12,FALSE) -> 190757.82
A86: M | B86: 6 | C86: =IFS(B86>40,"5-Slow",B86>30,"4-Medium",B86>20,"3-Fast",B86>15,"2-Very fast",TRUE,"1-Extremely fast") -> 1-Extremely fast | D86: =VLOOKUP(A86,events!F297:Q1626,12,FALSE) -> 510554.84
A87: H | B87: 12 | C87: =IFS(B87>40,"5-Slow",B87>30,"4-Medium",B87>20,"3-Fast",B87>15,"2-Very fast",TRUE,"1-Extremely fast") -> 1-Extremely fast | D87: =VLOOKUP(A87,events!F301:Q1630,12,FALSE) -> 967654.96
A88: M | B88: 11 | C88: =IFS(B88>40,"5-Slow",B88>30,"4-Medium",B88>20,"3-Fast",B88>15,"2-Very fast",TRUE,"1-Extremely fast") -> 1-Extremely fast | D88: =VLOOKUP(A88,events!F306:Q1635,12,FALSE) -> 1425097.2
A89: L | B89: 6 | C89: =IFS(B89>40,"5-Slow",B89>30,"4-Medium",B89>20,"3-Fast",B89>15,"2-Very fast",TRUE,"1-Extremely fast") -> 1-Extremely fast | D89: =VLOOKUP(A89,events!F308:Q1637,12,FALSE) -> 6285079.3
A90: M | B90: 3 | C90: =IFS(B90>40,"5-Slow",B90>30,"4-Medium",B90>20,"3-Fast",B90>15,"2-Very fast",TRUE,"1-Extremely fast") -> 1-Extremely fast | D90: =VLOOKUP(A90,events!F309:Q1638,12,FALSE) -> 64899.48
A91: H | B91: 14 | C91: =IFS(B91>40,"5-Slow",B91>30,"4-Medium",B91>20,"3-Fast",B91>15,"2-Very fast",TRUE,"1-Extremely fast") -> 1-Extremely fast | D91: =VLOOKUP(A91,events!F311:Q1640,12,FALSE) -> 206776.8
A92: M | B92: 5 | C92: =IFS(B92>40,"5-Slow",B92>30,"4-Medium",B92>20,"3-Fast",B92>15,"2-Very fast",TRUE,"1-Extremely fast") -> 1-Extremely fast | D92: =VLOOKUP(A92,events!F312:Q1641,12,FALSE) -> 3567979.6
A93: C | B93: 3 | C93: =IFS(B93>40,"5-Slow",B93>30,"4-Medium",B93>20,"3-Fast",B93>15,"2-Very fast",TRUE,"1-Extremely fast") -> 1-Extremely fast | D93: =VLOOKUP(A93,events!F316:Q1645,12,FALSE) -> 291340.48
A94: H | B94: 4 | C94: =IFS(B94>40,"5-Slow",B94>30,"4-Medium",B94>20,"3-Fast",B94>15,"2-Very fast",TRUE,"1-Extremely fast") -> 1-Extremely fast | D94: =VLOOKUP(A94,events!F317:Q1646,12,FALSE) -> 470013.28
A95: L | B95: 4 | C95: =IFS(B95>40,"5-Slow",B95>30,"4-Medium",B95>20,"3-Fast",B95>15,"2-Very fast",TRUE,"1-Extremely fast") -> 1-Extremely fast | D95: =VLOOKUP(A95,events!F318:Q1647,12,FALSE) -> 602528.66
A96: H | B96: 2 | C96: =IFS(B96>40,"5-Slow",B96>30,"4-Medium",B96>20,"3-Fast",B96>15,"2-Very fast",TRUE,"1-Extremely fast") -> 1-Extremely fast | D96: =VLOOKUP(A96,events!F322:Q1651,12,FALSE) -> 2413417.1
A97: L | B97: 5 | C97: =IFS(B97>40,"5-Slow",B97>30,"4-Medium",B97>20,"3-Fast",B97>15,"2-Very fast",TRUE,"1-Extremely fast") -> 1-Extremely fast | D97: =VLOOKUP(A97,events!F324:Q1653,12,FALSE) -> 690700.23
A98: C | B98: 2 | C98: =IFS(B98>40,"5-Slow",B98>30,"4-Medium",B98>20,"3-Fast",B98>15,"2-Very fast",TRUE,"1-Extremely fast") -> 1-Extremely fast | D98: =VLOOKUP(A98,events!F326:Q1655,12,FALSE) -> 179765.6
A99: M | B99: 7 | C99: =IFS(B99>40,"5-Slow",B99>30,"4-Medium",B99>20,"3-Fast",B99>15,"2-Very fast",TRUE,"1-Extremely fast") -> 1-Extremely fast | D99: =VLOOKUP(A99,events!F330:Q1659,12,FALSE) -> 1826184.4
A100: L | B100: 0 | C100: =IFS(B100>40,"5-Slow",B100>30,"4-Medium",B100>20,"3-Fast",B100>15,"2-Very fast",TRUE,"1-Extremely fast") -> 1-Extremely fast | D100: =VLOOKUP(A100,events!F334:Q1663,12,FALSE) -> 326503.12
...

Sheet 10.Product Sales by Week
A1: Product Units Sold | B1: Product Type
A2: Day of week | B2: Baby Food | C2: Beverages | D2: Cereal | E2: Clothes | F2: Cosmetics | G2: Fruits | H2: Household | I2: Meat | J2: Office Supplies | K2: Personal Care | L2: Snacks | M2: Vegetables
A3: 1 - Mon | B3: 25829 | C3: 67094 | D3: 18751 | E3: 30254 | F3: 22347 | G3: 52692 | H3: 71735 | I3: 59763 | J3: 47566 | K3: 6040 | L3: 77832 | M3: 36257
A4: 2 - Tue | B4: 35907 | C4: 39619 | D4: 50181 | E4: 47791 | F4: 61258 | G4: 23022 | H4: 6126 | I4: 43948 | J4: 33431 | K4: 39096 | L4: 35443 | M4: 34074
A5: 3 - Wed | B5: 30579 | C5: 40767 | D5: 34564 | E5: 18557 | F5: 17729 | G5: 23285 | H5: 63860 | I5: 27467 | J5: 36474 | K5: 36656 | L5: 16796 | M5: 22193
A6: 4 - Thu | B6: 20012 | C6: 40585 | D6: 27447 | E6: 48047 | F6: 35422 | G6: 34334 | H6: 19202 | I6: 30745 | J6: 21478 | K6: 34486 | L6: 18823 | M6: 51576
A7: 5 - Fri | B7: 16257 | C7: 26965 | D7: 35369 | E7: 35480 | F7: 69633 | G7: 16825 | H7: 31108 | I7: 18376 | J7: 33407 | K7: 40408 | L7: 43126 | M7: 35440
A8: 6 - Sat | B8: 40455 | C8: 27483 | D8: 39770 | E8: 58144 | F8: 33401 | G8: 45995 | H8: 30021 | I8: 33717 | J8: 16201 | K8: 41548 | L8: 30430 | M8: 27092
A9: 7 - Sun | B9: 37887 | C9: 58217 | D9: 46204 | E9: 46665 | F9: 15802 | G9: 61349 | H9: 18481 | I9: 25241 | J9: 60825 | K9: 48228 | L9: 29733 | M9: 65836

Sheet 9ca.Regions Revenue Year-on-Yea
A1: Order Date | B1: Year | C1: Country Region | D1: Total Revenue
A2: 41047 | B2: =IFERROR(__xludf.DUMMYFUNCTION("YEAR(TO_DATE(A2))"),2012.0) -> 2012 | C2: Europe | D2: 1447182.3
A3: 42245 | B3: =IFERROR(__xludf.DUMMYFUNCTION("YEAR(TO_DATE(A3))"),2015.0) -> 2015 | C3: Europe | D3: 535132.8
A4: 42198 | B4: =IFERROR(__xludf.DUMMYFUNCTION("YEAR(TO_DATE(A4))"),2015.0) -> 2015 | C4: Europe | D4: 5714367.8
A5: 41984 | B5: =IFERROR(__xludf.DUMMYFUNCTION("YEAR(TO_DATE(A5))"),2014.0) -> 2014 | C5: Europe | D5: 191128.6
A6: 42385 | B6: =IFERROR(__xludf.DUMMYFUNCTION("YEAR(TO_DATE(A6))"),2016.0) -> 2016 | C6: Europe | D6: 938278.08
A7: 42930 | B7: =IFERROR(__xludf.DUMMYFUNCTION("YEAR(TO_DATE(A7))"),2017.0) -> 2017 | C7: Europe | D7: 1168804.2
A8: 41858 | B8: =IFERROR(__xludf.DUMMYFUNCTION("YEAR(TO_DATE(A8))"),2014.0) -> 2014 | C8: Europe | D8: 44061.16
A9: 42072 | B9: =IFERROR(__xludf.DUMMYFUNCTION("YEAR(TO_DATE(A9))"),2015.0) -> 2015 | C9: Europe | D9: 128076.16
A10: 41187 | B10: =IFERROR(__xludf.DUMMYFUNCTION("YEAR(TO_DATE(A10))"),2012.0) -> 2012 | C10: Europe | D10: 818058.6
A11: 40532 | B11: =IFERROR(__xludf.DUMMYFUNCTION("YEAR(TO_DATE(A11))"),2010.0) -> 2010 | C11: Europe | D11: 3698206.2
A12: 42643 | B12: =IFERROR(__xludf.DUMMYFUNCTION("YEAR(TO_DATE(A12))"),2016.0) -> 2016 | C12: Europe | D12: 4205426.8
A13: 40640 | B13: =IFERROR(__xludf.DUMMYFUNCTION("YEAR(TO_DATE(A13))"),2011.0) -> 2011 | C13: Europe | D13: 1075643
A14: 40514 | B14: =IFERROR(__xludf.DUMMYFUNCTION("YEAR(TO_DATE(A14))"),2010.0) -> 2010 | C14: Europe | D14: 288528.78
A15: 40413 | B15: =IFERROR(__xludf.DUMMYFUNCTION("YEAR(TO_DATE(A15))"),2010.0) -> 2010 | C15: Europe | D15: 4179632
A16: 40721 | B16: =IFERROR(__xludf.DUMMYFUNCTION("YEAR(TO_DATE(A16))"),2011.0) -> 2011 | C16: Europe | D16: 2189934.8
A17: 41392 | B17: =IFERROR(__xludf.DUMMYFUNCTION("YEAR(TO_DATE(A17))"),2013.0) -> 2013 | C17: Europe | D17: 107426.8
A18: 42592 | B18: =IFERROR(__xludf.DUMMYFUNCTION("YEAR(TO_DATE(A18))"),2016.0) -> 2016 | C18: Europe | D18: 873923.82
A19: 40494 | B19: =IFERROR(__xludf.DUMMYFUNCTION("YEAR(TO_DATE(A19))"),2010.0) -> 2010 | C19: Europe | D19: 364934.85
A20: 41191 | B20: =IFERROR(__xludf.DUMMYFUNCTION("YEAR(TO_DATE(A20))"),2012.0) -> 2012 | C20: Europe | D20: 53333.8
A21: 41305 | B21: =IFERROR(__xludf.DUMMYFUNCTION("YEAR(TO_DATE(A21))"),2013.0) -> 2013 | C21: Europe | D21: 536644.08
A22: 40999 | B22: =IFERROR(__xludf.DUMMYFUNCTION("YEAR(TO_DATE(A22))"),2012.0) -> 2012 | C22: Europe | D22: 3666129.2
A23: 41470 | B23: =IFERROR(__xludf.DUMMYFUNCTION("YEAR(TO_DATE(A23))"),2013.0) -> 2013 | C23: Europe | D23: 11742.88
A24: 42910 | B24: =IFERROR(__xludf.DUMMYFUNCTION("YEAR(TO_DATE(A24))"),2017.0) -> 2017 | C24: Europe | D24: 276978.8
A25: 42906 | B25: =IFERROR(__xludf.DUMMYFUNCTION("YEAR(TO_DATE(A25))"),2017.0) -> 2017 | C25: Europe | D25: 536455.52
A26: 42061 | B26: =IFERROR(__xludf.DUMMYFUNCTION("YEAR(TO_DATE(A26))"),2015.0) -> 2015 | C26: Europe | D26: 758558.22
A27: 40334 | B27: =IFERROR(__xludf.DUMMYFUNCTION("YEAR(TO_DATE(A27))"),2010.0) -> 2010 | C27: Europe | D27: 361164.87
A28: 41781 | B28: =IFERROR(__xludf.DUMMYFUNCTION("YEAR(TO_DATE(A28))"),2014.0) -> 2014 | C28: Europe | D28: 2156507.3
A29: 41009 | B29: =IFERROR(__xludf.DUMMYFUNCTION("YEAR(TO_DATE(A29))"),2012.0) -> 2012 | C29: Europe | D29: 4275816
A30: 42074 | B30: =IFERROR(__xludf.DUMMYFUNCTION("YEAR(TO_DATE(A30))"),2015.0) -> 2015 | C30: Europe | D30: 73310.25
A31: 41090 | B31: =IFERROR(__xludf.DUMMYFUNCTION("YEAR(TO_DATE(A31))"),2012.0) -> 2012 | C31: Europe | D31: 3006187.2
A32: 40301 | B32: =IFERROR(__xludf.DUMMYFUNCTION("YEAR(TO_DATE(A32))"),2010.0) -> 2010 | C32: Europe | D32: 556306.68
A33: 41238 | B33: =IFERROR(__xludf.DUMMYFUNCTION("YEAR(TO_DATE(A33))"),2012.0) -> 2012 | C33: Europe | D33: 278341.7
A34: 41340 | B34: =IFERROR(__xludf.DUMMYFUNCTION("YEAR(TO_DATE(A34))"),2013.0) -> 2013 | C34: Europe | D34: 1599839.8
A35: 42658 | B35: =IFERROR(__xludf.DUMMYFUNCTION("YEAR(TO_DATE(A35))"),2016.0) -> 2016 | C35: Europe | D35: 851797.74
A36: 42550 | B36: =IFERROR(__xludf.DUMMYFUNCTION("YEAR(TO_DATE(A36))"),2016.0) -> 2016 | C36: Europe | D36: 68668.8
A37: 40918 | B37: =IFERROR(__xludf.DUMMYFUNCTION("YEAR(TO_DATE(A37))"),2012.0) -> 2012 | C37: Europe | D37: 1159737
A38: 40409 | B38: =IFERROR(__xludf.DUMMYFUNCTION("YEAR(TO_DATE(A38))"),2010.0) -> 2010 | C38: Europe | D38: 377464.75
A39: 40448 | B39: =IFERROR(__xludf.DUMMYFUNCTION("YEAR(TO_DATE(A39))"),2010.0) -> 2010 | C39: Europe | D39: 180482.96
A40: 42083 | B40: =IFERROR(__xludf.DUMMYFUNCTION("YEAR(TO_DATE(A40))"),2015.0) -> 2015 | C40: Europe | D40: 1052361.2
A41: 42484 | B41: =IFERROR(__xludf.DUMMYFUNCTION("YEAR(TO_DATE(A41))"),2016.0) -> 2016 | C41: Europe | D41: 167688.3
A42: 40201 | B42: =IFERROR(__xludf.DUMMYFUNCTION("YEAR(TO_DATE(A42))"),2010.0) -> 2010 | C42: Europe | D42: 1380543.8
A43: 40819 | B43: =IFERROR(__xludf.DUMMYFUNCTION("YEAR(TO_DATE(A43))"),2011.0) -> 2011 | C43: Europe | D43: 791043.75
A44: 40450 | B44: =IFERROR(__xludf.DUMMYFUNCTION("YEAR(TO_DATE(A44))"),2010.0) -> 2010 | C44: Europe | D44: 5639530.5
A45: 42598 | B45: =IFERROR(__xludf.DUMMYFUNCTION("YEAR(TO_DATE(A45))"),2016.0) -> 2016 | C45: Europe | D45: 1553399
A46: 40638 | B46: =IFERROR(__xludf.DUMMYFUNCTION("YEAR(TO_DATE(A46))"),2011.0) -> 2011 | C46: Europe | D46: 434232.7
A47: 42667 | B47: =IFERROR(__xludf.DUMMYFUNCTION("YEAR(TO_DATE(A47))"),2016.0) -> 2016 | C47: Europe | D47: 1830357.6
A48: 40578 | B48: =IFERROR(__xludf.DUMMYFUNCTION("YEAR(TO_DATE(A48))"),2011.0) -> 2011 | C48: Europe | D48: 923719.32
A49: 41729 | B49: =IFERROR(__xludf.DUMMYFUNCTION("YEAR(TO_DATE(A49))"),2014.0) -> 2014 | C49: Europe | D49: 1966654.2
A50: 40256 | B50: =IFERROR(__xludf.DUMMYFUNCTION("YEAR(TO_DATE(A50))"),2010.0) -> 2010 | C50: Europe | D50: 1908484.6
A51: 42689 | B51: =IFERROR(__xludf.DUMMYFUNCTION("YEAR(TO_DATE(A51))"),2016.0) -> 2016 | C51: Europe | D51: 2905638
A52: 42433 | B52: =IFERROR(__xludf.DUMMYFUNCTION("YEAR(TO_DATE(A52))"),2016.0) -> 2016 | C52: Europe | D52: 49057.14
A53: 41623 | B53: =IFERROR(__xludf.DUMMYFUNCTION("YEAR(TO_DATE(A53))"),2013.0) -> 2013 | C53: Europe | D53: 100601.18
A54: 42426 | B54: =IFERROR(__xludf.DUMMYFUNCTION("YEAR(TO_DATE(A54))"),2016.0) -> 2016 | C54: Europe | D54: 3274190.8
A55: 41985 | B55: =IFERROR(__xludf.DUMMYFUNCTION("YEAR(TO_DATE(A55))"),2014.0) -> 2014 | C55: Europe | D55: 358794.7
A56: 42596 | B56: =IFERROR(__xludf.DUMMYFUNCTION("YEAR(TO_DATE(A56))"),2016.0) -> 2016 | C56: Europe | D56: 5024053.9
A57: 40191 | B57: =IFERROR(__xludf.DUMMYFUNCTION("YEAR(TO_DATE(A57))"),2010.0) -> 2010 | C57: Europe | D57: 59549.75
A58: 41786 | B58: =IFERROR(__xludf.DUMMYFUNCTION("YEAR(TO_DATE(A58))"),2014.0) -> 2014 | C58: Europe | D58: 9171.39
A59: 42869 | B59: =IFERROR(__xludf.DUMMYFUNCTION("YEAR(TO_DATE(A59))"),2017.0) -> 2017 | C59: Europe | D59: 276587.68
A60: 41556 | B60: =IFERROR(__xludf.DUMMYFUNCTION("YEAR(TO_DATE(A60))"),2013.0) -> 2013 | C60: Europe | D60: 432127.15
A61: 41336 | B61: =IFERROR(__xludf.DUMMYFUNCTION("YEAR(TO_DATE(A61))"),2013.0) -> 2013 | C61: Europe | D61: 1015563.5
A62: 40681 | B62: =IFERROR(__xludf.DUMMYFUNCTION("YEAR(TO_DATE(A62))"),2011.0) -> 2011 | C62: Europe | D62: 73982.56
A63: 40958 | B63: =IFERROR(__xludf.DUMMYFUNCTION("YEAR(TO_DATE(A63))"),2012.0) -> 2012 | C63: Asia | D63: 2536752.9
A64: 40625 | B64: =IFERROR(__xludf.DUMMYFUNCTION("YEAR(TO_DATE(A64))"),2011.0) -> 2011 | C64: Asia | D64: 82719.78
A65: 40931 | B65: =IFERROR(__xludf.DUMMYFUNCTION("YEAR(TO_DATE(A65))"),2012.0) -> 2012 | C65: Asia | D65: 201926.48
A66: 40602 | B66: =IFERROR(__xludf.DUMMYFUNCTION("YEAR(TO_DATE(A66))"),2011.0) -> 2011 | C66: Asia | D66: 310805.46
A67: 40181 | B67: =IFERROR(__xludf.DUMMYFUNCTION("YEAR(TO_DATE(A67))"),2010.0) -> 2010 | C67: Asia | D67: 34204.64
A68: 42157 | B68: =IFERROR(__xludf.DUMMYFUNCTION("YEAR(TO_DATE(A68))"),2015.0) -> 2015 | C68: Asia | D68: 2988668.8
A69: 41972 | B69: =IFERROR(__xludf.DUMMYFUNCTION("YEAR(TO_DATE(A69))"),2014.0) -> 2014 | C69: Asia | D69: 85966.62
A70: 40604 | B70: =IFERROR(__xludf.DUMMYFUNCTION("YEAR(TO_DATE(A70))"),2011.0) -> 2011 | C70: Asia | D70: 607115.82
A71: 41310 | B71: =IFERROR(__xludf.DUMMYFUNCTION("YEAR(TO_DATE(A71))"),2013.0) -> 2013 | C71: Asia | D71: 740520
A72: 40699 | B72: =IFERROR(__xludf.DUMMYFUNCTION("YEAR(TO_DATE(A72))"),2011.0) -> 2011 | C72: Asia | D72: 313739.4
A73: 42080 | B73: =IFERROR(__xludf.DUMMYFUNCTION("YEAR(TO_DATE(A73))"),2015.0) -> 2015 | C73: Asia | D73: 32878.92
A74: 40198 | B74: =IFERROR(__xludf.DUMMYFUNCTION("YEAR(TO_DATE(A74))"),2010.0) -> 2010 | C74: Asia | D74: 1533493.5
A75: 41155 | B75: =IFERROR(__xludf.DUMMYFUNCTION("YEAR(TO_DATE(A75))"),2012.0) -> 2012 | C75: Asia | D75: 702351.77
A76: 42711 | B76: =IFERROR(__xludf.DUMMYFUNCTION("YEAR(TO_DATE(A76))"),2016.0) -> 2016 | C76: Asia | D76: 939303.82
A77: 40796 | B77: =IFERROR(__xludf.DUMMYFUNCTION("YEAR(TO_DATE(A77))"),2011.0) -> 2011 | C77: Asia | D77: 1037962.2
A78: 42256 | B78: =IFERROR(__xludf.DUMMYFUNCTION("YEAR(TO_DATE(A78))"),2015.0) -> 2015 | C78: Asia | D78: 4985962.5
A79: 42644 | B79: =IFERROR(__xludf.DUMMYFUNCTION("YEAR(TO_DATE(A79))"),2016.0) -> 2016 | C79: Asia | D79: 144286.38
A80: 40194 | B80: =IFERROR(__xludf.DUMMYFUNCTION("YEAR(TO_DATE(A80))"),2010.0) -> 2010 | C80: Asia | D80: 290877.07
A81: 41085 | B81: =IFERROR(__xludf.DUMMYFUNCTION("YEAR(TO_DATE(A81))"),2012.0) -> 2012 | C81: Asia | D81: 2218719.5
A82: 41486 | B82: =IFERROR(__xludf.DUMMYFUNCTION("YEAR(TO_DATE(A82))"),2013.0) -> 2013 | C82: Asia | D82: 266557.26
A83: 42317 | B83: =IFERROR(__xludf.DUMMYFUNCTION("YEAR(TO_DATE(A83))"),2015.0) -> 2015 | C83: Asia | D83: 3117767.1
A84: 42710 | B84: =IFERROR(__xludf.DUMMYFUNCTION("YEAR(TO_DATE(A84))"),2016.0) -> 2016 | C84: Asia | D84: 526913.31
A85: 40219 | B85: =IFERROR(__xludf.DUMMYFUNCTION("YEAR(TO_DATE(A85))"),2010.0) -> 2010 | C85: Asia | D85: 1272060.2
A86: 40522 | B86: =IFERROR(__xludf.DUMMYFUNCTION("YEAR(TO_DATE(A86))"),2010.0) -> 2010 | C86: Asia | D86: 375385.89
A87: 42505 | B87: =IFERROR(__xludf.DUMMYFUNCTION("YEAR(TO_DATE(A87))"),2016.0) -> 2016 | C87: Asia | D87: 1406875.9
A88: 41854 | B88: =IFERROR(__xludf.DUMMYFUNCTION("YEAR(TO_DATE(A88))"),2014.0) -> 2014 | C88: Asia | D88: 4859329
A89: 42787 | B89: =IFERROR(__xludf.DUMMYFUNCTION("YEAR(TO_DATE(A89))"),2017.0) -> 2017 | C89: Asia | D89: 594046.08
A90: 42902 | B90: =IFERROR(__xludf.DUMMYFUNCTION("YEAR(TO_DATE(A90))"),2017.0) -> 2017 | C90: Asia | D90: 1146486.1
A91: 40477 | B91: =IFERROR(__xludf.DUMMYFUNCTION("YEAR(TO_DATE(A91))"),2010.0) -> 2010 | C91: Asia | D91: 4166163.8
A92: 40311 | B92: =IFERROR(__xludf.DUMMYFUNCTION("YEAR(TO_DATE(A92))"),2010.0) -> 2010 | C92: Europe | D92: 1707721.4
A93: 42925 | B93: =IFERROR(__xludf.DUMMYFUNCTION("YEAR(TO_DATE(A93))"),2017.0) -> 2017 | C93: Europe | D93: 98484.65
A94: 42267 | B94: =IFERROR(__xludf.DUMMYFUNCTION("YEAR(TO_DATE(A94))"),2015.0) -> 2015 | C94: Europe | D94: 1180833.1
A95: 40653 | B95: =IFERROR(__xludf.DUMMYFUNCTION("YEAR(TO_DATE(A95))"),2011.0) -> 2011 | C95: Europe | D95: 81478.89
A96: 41001 | B96: =IFERROR(__xludf.DUMMYFUNCTION("YEAR(TO_DATE(A96))"),2012.0) -> 2012 | C96: Europe | D96: 420549.35
A97: 40761 | B97: =IFERROR(__xludf.DUMMYFUNCTION("YEAR(TO_DATE(A97))"),2011.0) -> 2011 | C97: Europe | D97: 28381.86
A98: 40234 | B98: =IFERROR(__xludf.DUMMYFUNCTION("YEAR(TO_DATE(A98))"),2010.0) -> 2010 | C98: Europe | D98: 4344873.1
A99: 42362 | B99: =IFERROR(__xludf.DUMMYFUNCTION("YEAR(TO_DATE(A99))"),2015.0) -> 2015 | C99: Europe | D99: 1770871.3
A100: 40668 | B100: =IFERROR(__xludf.DUMMYFUNCTION("YEAR(TO_DATE(A100))"),2011.0) -> 2011 | C100: Europe | D100: 957020.72
...

Sheet 9ca. Regions Revenue Year-on-Ye

Sheet 9cb.Regions Revenue by Month
A1: Order Date | B1: Month | D1: Country Region | E1: Ordered Month | F1: Total Revenue
A2: 40931 | B2: =TEXT(A2,"MMMM") -> January | C2: =MONTH(A2) -> 1 | D2: Asia | E2: =C2 & " " & B2 -> 1 January | F2: 201926.48
A3: 42016 | B3: =TEXT(A3,"MMMM") -> January | C3: =MONTH(A3) -> 1 | D3: Europe | E3: =C3 & " " & B3 -> 1 January | F3: 763662.9
A4: 41652 | B4: =TEXT(A4,"MMMM") -> January | C4: =MONTH(A4) -> 1 | D4: Europe | E4: =C4 & " " & B4 -> 1 January | F4: 541810.24
A5: 40196 | B5: =TEXT(A5,"MMMM") -> January | C5: =MONTH(A5) -> 1 | D5: Asia | E5: =C5 & " " & B5 -> 1 January | F5: 165676.72
A6: 40931 | B6: =TEXT(A6,"MMMM") -> January | C6: =MONTH(A6) -> 1 | D6: Europe | E6: =C6 & " " & B6 -> 1 January | F6: 6111997.4
A7: 41645 | B7: =TEXT(A7,"MMMM") -> January | C7: =MONTH(A7) -> 1 | D7: Europe | E7: =C7 & " " & B7 -> 1 January | F7: 1118321.5
A8: 41666 | B8: =TEXT(A8,"MMMM") -> January | C8: =MONTH(A8) -> 1 | D8: Europe | E8: =C8 & " " & B8 -> 1 January | F8: 64730.16
A9: 42016 | B9: =TEXT(A9,"MMMM") -> January | C9: =MONTH(A9) -> 1 | D9: Europe | E9: =C9 & " " & B9 -> 1 January | F9: 3872280.4
A10: 40938 | B10: =TEXT(A10,"MMMM") -> January | C10: =MONTH(A10) -> 1 | D10: Europe | E10: =C10 & " " & B10 -> 1 January | F10: 5159536.8
A11: 40189 | B11: =TEXT(A11,"MMMM") -> January | C11: =MONTH(A11) -> 1 | D11: Europe | E11: =C11 & " " & B11 -> 1 January | F11: 1592436.6
A12: 40189 | B12: =TEXT(A12,"MMMM") -> January | C12: =MONTH(A12) -> 1 | D12: Europe | E12: =C12 & " " & B12 -> 1 January | F12: 1299523.9
A13: 40910 | B13: =TEXT(A13,"MMMM") -> January | C13: =MONTH(A13) -> 1 | D13: Europe | E13: =C13 & " " & B13 -> 1 January | F13: 243038.9
... A1331: 40447 | B1331: =TEXT(A1331,"MMMM") -> September | C1331: =MONTH(A1331) -> 9 | D1331: Unknown Country | E1331: =C1331 & " " & B1331 -> 9 September | F1331: 680720.4

Sheet 9cb.Regions Revenue by Month Pi

Sheet 9aa.Product Sales by Year
A1: Order Date | B1: Year | C1: Product Name | D1: Total Revenue
A2: 41047 | B2: =IFERROR(__xludf.DUMMYFUNCTION("YEAR(TO_DATE(A2))"),2012.0) -> 2012 | C2: Baby Food | D2: 1447182.3
A3: 42245 | B3: =IFERROR(__xludf.DUMMYFUNCTION("YEAR(TO_DATE(A3))"),2015.0) -> 2015 | C3: Cosmetics | D3: 535132.8
A4: 42198 | B4: =IFERROR(__xludf.DUMMYFUNCTION("YEAR(TO_DATE(A4))"),2015.0) -> 2015 | C4: Office Supplies | D4: 5714367.8
A5: 41984 | B5: =IFERROR(__xludf.DUMMYFUNCTION("YEAR(TO_DATE(A5))"),2014.0) -> 2014 | C5: Beverages | D5: 191128.6
A6: 42385 | B6: =IFERROR(__xludf.DUMMYFUNCTION("YEAR(TO_DATE(A6))"),2016.0) -> 2016 | C6: Clothes | D6: 938278.08
A7: 42930 | B7: =IFERROR(__xludf.DUMMYFUNCTION("YEAR(TO_DATE(A7))"),2017.0) -> 2017 | C7: Household | D7: 1168804.2
A8: 41858 | B8: =IFERROR(__xludf.DUMMYFUNCTION("YEAR(TO_DATE(A8))"),2014.0) -> 2014 | C8: Vegetables | D8: 44061.16
A9: 42072 | B9: =IFERROR(__xludf.DUMMYFUNCTION("YEAR(TO_DATE(A9))"),2015.0) -> 2015 | C9: Clothes | D9: 128076.16
A10: 41187 | B10: =IFERROR(__xludf.DUMMYFUNCTION("YEAR(TO_DATE(A10))"),2012.0) -> 2012 | C10: Vegetables | D10: 818058.6
A11: 40532 | B11: =IFERROR(__xludf.DUMMYFUNCTION("YEAR(TO_DATE(A11))"),2010.0) -> 2010 | C11: Household | D11: 3698206.2
A12: 42643 | B12: =IFERROR(__xludf.DUMMYFUNCTION("YEAR(TO_DATE(A12))"),2016.0) -> 2016 | C12: Cosmetics | D12: 4205426.8
A13: 40640 | B13: =IFERROR(__xludf.DUMMYFUNCTION("YEAR(TO_DATE(A13))"),2011.0) -> 2011 | C13: Clothes | D13: 1075643
A14: 40514 | B14: =IFERROR(__xludf.DUMMYFUNCTION("YEAR(TO_DATE(A14))"),2010.0) -> 2010 | C14: Snacks | D14: 288528.78
A15: 40413 | B15: =IFERROR(__xludf.DUMMYFUNCTION("YEAR(TO_DATE(A15))"),2010.0) -> 2010 | C15: Cosmetics | D15: 4179632
A16: 40721 | B16: =IFERROR(__xludf.DUMMYFUNCTION("YEAR(TO_DATE(A16))"),2011.0) -> 2011 | C16: Cosmetics | D16: 2189934.8
A17: 41392 | B17: =IFERROR(__xludf.DUMMYFUNCTION("YEAR(TO_DATE(A17))"),2013.0) -> 2013 | C17: Beverages | D17: 107426.8
A18: 42592 | B18: =IFERROR(__xludf.DUMMYFUNCTION("YEAR(TO_DATE(A18))"),2016.0) -> 2016 | C18: Office Supplies | D18: 873923.82
A19: 40494 | B19: =IFERROR(__xludf.DUMMYFUNCTION("YEAR(TO_DATE(A19))"),2010.0) -> 2010 | C19: Meat | D19: 364934.85
A20: 41191 | B20: =IFERROR(__xludf.DUMMYFUNCTION("YEAR(TO_DATE(A20))"),2012.0) -> 2012 | C20: Beverages | D20: 53333.8
A21: 41305 | B21: =IFERROR(__xludf.DUMMYFUNCTION("YEAR(TO_DATE(A21))"),2013.0) -> 2013 | C21: Meat | D21: 536644.08
A22: 40999 | B22: =IFERROR(__xludf.DUMMYFUNCTION("YEAR(TO_DATE(A22))"),2012.0) -> 2012 | C22: Household | D22: 3666129.2
A23: 41470 | B23: =IFERROR(__xludf.DUMMYFUNCTION("YEAR(TO_DATE(A23))"),2013.0) -> 2013 | C23: Baby Food | D23: 11742.88
A24: 42910 | B24: =IFERROR(__xludf.DUMMYFUNCTION("YEAR(TO_DATE(A24))"),2017.0) -> 2017 | C24: Baby Food | D24: 276978.8
A25: 42906 | B25: =IFERROR(__xludf.DUMMYFUNCTION("YEAR(TO_DATE(A25))"),2017.0) -> 2017 | C25: Clothes | D25: 536455.52
A26: 42061 | B26: =IFERROR(__xludf.DUMMYFUNCTION("YEAR(TO_DATE(A26))"),2015.0) -> 2015 | C26: Meat | D26: 758558.22
A27: 40334 | B27: =IFERROR(__xludf.DUMMYFUNCTION("YEAR(TO_DATE(A27))"),2010.0) -> 2010 | C27: Personal Care | D27: 361164.87
A28: 41781 | B28: =IFERROR(__xludf.DUMMYFUNCTION("YEAR(TO_DATE(A28))"),2014.0) -> 2014 | C28: Household | D28: 2156507.3
A29: 41009 | B29: =IFERROR(__xludf.DUMMYFUNCTION("YEAR(TO_DATE(A29))"),2012.0) -> 2012 | C29: Cosmetics | D29: 4275816
A30: 42074 | B30: =IFERROR(__xludf.DUMMYFUNCTION("YEAR(TO_DATE(A30))"),2015.0) -> 2015 | C30: Beverages | D30: 73310.25
A31: 41090 | B31: =IFERROR(__xludf.DUMMYFUNCTION("YEAR(TO_DATE(A31))"),2012.0) -> 2012 | C31: Cosmetics | D31: 3006187.2
A32: 40301 | B32: =IFERROR(__xludf.DUMMYFUNCTION("YEAR(TO_DATE(A32))"),2010.0) -> 2010 | C32: Snacks | D32: 556306.68
A33: 41238 | B33: =IFERROR(__xludf.DUMMYFUNCTION("YEAR(TO_DATE(A33))"),2012.0) -> 2012 | C33: Beverages | D33: 278341.7
A34: 41340 | B34: =IFERROR(__xludf.DUMMYFUNCTION("YEAR(TO_DATE(A34))"),2013.0) -> 2013 | C34: Baby Food | D34: 1599839.8
A35: 42658 | B35: =IFERROR(__xludf.DUMMYFUNCTION("YEAR(TO_DATE(A35))"),2016.0) -> 2016 | C35: Vegetables | D35: 851797.74
A36: 42550 | B36: =IFERROR(__xludf.DUMMYFUNCTION("YEAR(TO_DATE(A36))"),2016.0) -> 2016 | C36: Fruits | D36: 68668.8
A37: 40918 | B37: =IFERROR(__xludf.DUMMYFUNCTION("YEAR(TO_DATE(A37))"),2012.0) -> 2012 | C37: Baby Food | D37: 1159737
A38: 40409 | B38: =IFERROR(__xludf.DUMMYFUNCTION("YEAR(TO_DATE(A38))"),2010.0) -> 2010 | C38: Beverages | D38: 377464.75
A39: 40448 | B39: =IFERROR(__xludf.DUMMYFUNCTION("YEAR(TO_DATE(A39))"),2010.0) -> 2010 | C39: Baby Food | D39: 180482.96
A40: 42083 | B40: =IFERROR(__xludf.DUMMYFUNCTION("YEAR(TO_DATE(A40))"),2015.0) -> 2015 | C40: Cereal | D40: 1052361.2
A41: 42484 | B41: =IFERROR(__xludf.DUMMYFUNCTION("YEAR(TO_DATE(A41))"),2016.0) -> 2016 | C41: Beverages | D41: 167688.3
A42: 40201 | B42: =IFERROR(__xludf.DUMMYFUNCTION("YEAR(TO_DATE(A42))"),2010.0) -> 2010 | C42: Snacks | D42: 1380543.8
A43: 40819 | B43: =IFERROR(__xludf.DUMMYFUNCTION("YEAR(TO_DATE(A43))"),2011.0) -> 2011 | C43: Meat | D43: 791043.75
A44: 40450 | B44: =IFERROR(__xludf.DUMMYFUNCTION("YEAR(TO_DATE(A44))"),2010.0) -> 2010 | C44: Household | D44: 5639530.5
A45: 42598 | B45: =IFERROR(__xludf.DUMMYFUNCTION("YEAR(TO_DATE(A45))"),2016.0) -> 2016 | C45: Meat | D45: 1553399
A46: 40638 | B46: =IFERROR(__xludf.DUMMYFUNCTION("YEAR(TO_DATE(A46))"),2011.0) -> 2011 | C46: Cereal | D46: 434232.7
A47: 42667 | B47: =IFERROR(__xludf.DUMMYFUNCTION("YEAR(TO_DATE(A47))"),2016.0) -> 2016 | C47: Baby Food | D47: 1830357.6
A48: 40578 | B48: =IFERROR(__xludf.DUMMYFUNCTION("YEAR(TO_DATE(A48))"),2011.0) -> 2011 | C48: Snacks | D48: 923719.32
A49: 41729 | B49: =IFERROR(__xludf.DUMMYFUNCTION("YEAR(TO_DATE(A49))"),2014.0) -> 2014 | C49: Office Supplies | D49: 1966654.2
A50: 40256 | B50: =IFERROR(__xludf.DUMMYFUNCTION("YEAR(TO_DATE(A50))"),2010.0) -> 2010 | C50: Cereal | D50: 1908484.6
A51: 42689 | B51: =IFERROR(__xludf.DUMMYFUNCTION("YEAR(TO_DATE(A51))"),2016.0) -> 2016 | C51: Household | D51: 2905638
A52: 42433 | B52: =IFERROR(__xludf.DUMMYFUNCTION("YEAR(TO_DATE(A52))"),2016.0) -> 2016 | C52: Fruits | D52: 49057.14
A53: 41623 | B53: =IFERROR(__xludf.DUMMYFUNCTION("YEAR(TO_DATE(A53))"),2013.0) -> 2013 | C53: Vegetables | D53: 100601.18
A54: 42426 | B54: =IFERROR(__xludf.DUMMYFUNCTION("YEAR(TO_DATE(A54))"),2016.0) -> 2016 | C54: Cosmetics | D54: 3274190.8
A55: 41985 | B55: =IFERROR(__xludf.DUMMYFUNCTION("YEAR(TO_DATE(A55))"),2014.0) -> 2014 | C55: Personal Care | D55: 358794.7
A56: 42596 | B56: =IFERROR(__xludf.DUMMYFUNCTION("YEAR(TO_DATE(A56))"),2016.0) -> 2016 | C56: Household | D56: 5024053.9
A57: 40191 | B57: =IFERROR(__xludf.DUMMYFUNCTION("YEAR(TO_DATE(A57))"),2010.0) -> 2010 | C57: Beverages | D57: 59549.75
A58: 41786 | B58: =IFERROR(__xludf.DUMMYFUNCTION("YEAR(TO_DATE(A58))"),2014.0) -> 2014 | C58: Fruits | D58: 9171.39
A59: 42869 | B59: =IFERROR(__xludf.DUMMYFUNCTION("YEAR(TO_DATE(A59))"),2017.0) -> 2017 | C59: Clothes | D59: 276587.68
A60: 41556 | B60: =IFERROR(__xludf.DUMMYFUNCTION("YEAR(TO_DATE(A60))"),2013.0) -> 2013 | C60: Beverages | D60: 432127.15
A61: 41336 | B61: =IFERROR(__xludf.DUMMYFUNCTION("YEAR(TO_DATE(A61))"),2013.0) -> 2013 | C61: Vegetables | D61: 1015563.5
A62: 40681 | B62: =IFERROR(__xludf.DUMMYFUNCTION("YEAR(TO_DATE(A62))"),2011.0) -> 2011 | C62: Clothes | D62: 73982.56
A63: 40958 | B63: =IFERROR(__xludf.DUMMYFUNCTION("YEAR(TO_DATE(A63))"),2012.0) -> 2012 | C63: Household | D63: 2536752.9
A64: 40625 | B64: =IFERROR(__xludf.DUMMYFUNCTION("YEAR(TO_DATE(A64))"),2011.0) -> 2011 | C64: Fruits | D64: 82719.78
A65: 40931 | B65: =IFERROR(__xludf.DUMMYFUNCTION("YEAR(TO_DATE(A65))"),2012.0) -> 2012 | C65: Baby Food | D65: 201926.48
A66: 40602 | B66: =IFERROR(__xludf.DUMMYFUNCTION("YEAR(TO_DATE(A66))"),2011.0) -> 2011 | C66: Snacks | D66: 310805.46
A67: 40181 | B67: =IFERROR(__xludf.DUMMYFUNCTION("YEAR(TO_DATE(A67))"),2010.0) -> 2010 | C67: Clothes | D67: 34204.64
A68: 42157 | B68: =IFERROR(__xludf.DUMMYFUNCTION("YEAR(TO_DATE(A68))"),2015.0) -> 2015 | C68: Meat | D68: 2988668.8
A69: 41972 | B69: =IFERROR(__xludf.DUMMYFUNCTION("YEAR(TO_DATE(A69))"),2014.0) -> 2014 | C69: Fruits | D69: 85966.62
A70: 40604 | B70: =IFERROR(__xludf.DUMMYFUNCTION("YEAR(TO_DATE(A70))"),2011.0) -> 2011 | C70: Snacks | D70: 607115.82
A71: 41310 | B71: =IFERROR(__xludf.DUMMYFUNCTION("YEAR(TO_DATE(A71))"),2013.0) -> 2013 | C71: Cereal | D71: 740520
A72: 40699 | B72: =IFERROR(__xludf.DUMMYFUNCTION("YEAR(TO_DATE(A72))"),2011.0) -> 2011 | C72: Beverages | D72: 313739.4
A73: 42080 | B73: =IFERROR(__xludf.DUMMYFUNCTION("YEAR(TO_DATE(A73))"),2015.0) -> 2015 | C73: Fruits | D73: 32878.92
A74: 40198 | B74: =IFERROR(__xludf.DUMMYFUNCTION("YEAR(TO_DATE(A74))"),2010.0) -> 2010 | C74: Cereal | D74: 1533493.5
A75: 41155 | B75: =IFERROR(__xludf.DUMMYFUNCTION("YEAR(TO_DATE(A75))"),2012.0) -> 2012 | C75: Household | D75: 702351.77
A76: 42711 | B76: =IFERROR(__xludf.DUMMYFUNCTION("YEAR(TO_DATE(A76))"),2016.0) -> 2016 | C76: Vegetables | D76: 939303.82
A77: 40796 | B77: =IFERROR(__xludf.DUMMYFUNCTION("YEAR(TO_DATE(A77))"),2011.0) -> 2011 | C77: Cereal | D77: 1037962.2
A78: 42256 | B78: =IFERROR(__xludf.DUMMYFUNCTION("YEAR(TO_DATE(A78))"),2015.0) -> 2015 | C78: Household | D78: 4985962.5
A79: 42644 | B79: =IFERROR(__xludf.DUMMYFUNCTION("YEAR(TO_DATE(A79))"),2016.0) -> 2016 | C79: Meat | D79: 144286.38
A80: 40194 | B80: =IFERROR(__xludf.DUMMYFUNCTION("YEAR(TO_DATE(A80))"),2010.0) -> 2010 | C80: Personal Care | D80: 290877.07
A81: 41085 | B81: =IFERROR(__xludf.DUMMYFUNCTION("YEAR(TO_DATE(A81))"),2012.0) -> 2012 | C81: Meat | D81: 2218719.5
A82: 41486 | B82: =IFERROR(__xludf.DUMMYFUNCTION("YEAR(TO_DATE(A82))"),2013.0) -> 2013 | C82: Snacks | D82: 266557.26
A83: 42317 | B83: =IFERROR(__xludf.DUMMYFUNCTION("YEAR(TO_DATE(A83))"),2015.0) -> 2015 | C83: Meat | D83: 3117767.1
A84: 42710 | B84: =IFERROR(__xludf.DUMMYFUNCTION("YEAR(TO_DATE(A84))"),2016.0) -> 2016 | C84: Personal Care | D84: 526913.31
A85: 40219 | B85: =IFERROR(__xludf.DUMMYFUNCTION("YEAR(TO_DATE(A85))"),2010.0) -> 2010 | C85: Baby Food | D85: 1272060.2
A86: 40522 | B86: =IFERROR(__xludf.DUMMYFUNCTION("YEAR(TO_DATE(A86))"),2010.0) -> 2010 | C86: Personal Care | D86: 375385.89
A87: 42505 | B87: =IFERROR(__xludf.DUMMYFUNCTION("YEAR(TO_DATE(A87))"),2016.0) -> 2016 | C87: Vegetables | D87: 1406875.9
A88: 41854 | B88: =IFERROR(__xludf.DUMMYFUNCTION("YEAR(TO_DATE(A88))"),2014.0) -> 2014 | C88: Office Supplies | D88: 4859329
A89: 42787 | B89: =IFERROR(__xludf.DUMMYFUNCTION("YEAR(TO_DATE(A89))"),2017.0) -> 2017 | C89: Clothes | D89: 594046.08
A90: 42902 | B90: =IFERROR(__xludf.DUMMYFUNCTION("YEAR(TO_DATE(A90))"),2017.0) -> 2017 | C90: Snacks | D90: 1146486.1
A91: 40477 | B91: =IFERROR(__xludf.DUMMYFUNCTION("YEAR(TO_DATE(A91))"),2010.0) -> 2010 | C91: Meat | D91: 4166163.8
A92: 40311 | B92: =IFERROR(__xludf.DUMMYFUNCTION("YEAR(TO_DATE(A92))"),2010.0) -> 2010 | C92: Cereal | D92: 1707721.4
A93: 42925 | B93: =IFERROR(__xludf.DUMMYFUNCTION("YEAR(TO_DATE(A93))"),2017.0) -> 2017 | C93: Personal Care | D93: 98484.65
A94: 42267 | B94: =IFERROR(__xludf.DUMMYFUNCTION("YEAR(TO_DATE(A94))"),2015.0) -> 2015 | C94: Household | D94: 1180833.1
A95: 40653 | B95: =IFERROR(__xludf.DUMMYFUNCTION("YEAR(TO_DATE(A95))"),2011.0) -> 2011 | C95: Fruits | D95: 81478.89
A96: 41001 | B96: =IFERROR(__xludf.DUMMYFUNCTION("YEAR(TO_DATE(A96))"),2012.0) -> 2012 | C96: Beverages | D96: 420549.35
A97: 40761 | B97: =IFERROR(__xludf.DUMMYFUNCTION("YEAR(TO_DATE(A97))"),2011.0) -> 2011 | C97: Fruits | D97: 28381.86
A98: 40234 | B98: =IFERROR(__xludf.DUMMYFUNCTION("YEAR(TO_DATE(A98))"),2010.0) -> 2010 | C98: Office Supplies | D98: 4344873.1
A99: 42362 | B99: =IFERROR(__xludf.DUMMYFUNCTION("YEAR(TO_DATE(A99))"),2015.0) -> 2015 | C99: Cereal | D99: 1770871.3
A100: 40668 | B100: =IFERROR(__xludf.DUMMYFUNCTION("YEAR(TO_DATE(A100))"),2011.0) -> 2011 | C100: Vegetables | D100: 957020.72
...

Sheet 9aa. Product Sales by Year Pivo

Sheet 9ab.Product Sales by Month 
A1: Units Sold by Month | B1: Product Type
A2: # of Month | B2: Baby Food | C2: Beverages | D2: Cereal | E2: Clothes | F2: Cosmetics | G2: Fruits | H2: Household | I2: Meat | J2: Office Supplies | K2: Personal Care | L2: Snacks | M2: Vegetables
A3: 1 | B3: 34833 | C3: 7460 | D3: 34419 | E3: 32003 | F3: 51256 | G3: 15508 | H3: 13773 | I3: 16188 | J3: 22952 | K3: 25371 | L3: 36604 | M3: 15612
A4: 2 | C4: 41349 | D4: 19171 | E4: 4153 | F4: 11712 | G4: 8725 | H4: 25968 | I4: 21589 | J4: 26856 | K4: 24130 | L4: 22830 | M4: 18194
A5: 3 | B5: 16860 | C5: 25299 | D5: 15408 | E5: 29963 | F5: 28243 | G5: 33362 | H5: 13862 | I5: 18293 | J5: 20149 | K5: 25357 | L5: 22097 | M5: 30944
A6: 4 | B6: 15362 | C6: 17993 | D6: 2111 | E6: 70597 | F6: 15662 | G6: 15923 | H6: 31478 | I6: 17075 | J6: 18853 | K6: 30137 | L6: 22352 | M6: 16473
A7: 5 | B7: 11847 | C7: 21159 | D7: 23154 | E7: 23947 | F7: 19808 | G7: 9603 | H7: 12873 | I7: 26210 | J7: 41995 | K7: 12429 | L7: 24461 | M7: 32568
A8: 6 | B8: 13444 | C8: 21344 | D8: 8630 | E8: 33974 | F8: 24669 | G8: 14715 | H8: 27567 | I8: 13702 | J8: 11315 | K8: 40311 | L8: 15176 | M8: 18830
A9: 7 | B9: 23188 | C9: 17713 | D9: 33864 | E9: 19372 | F9: 30540 | G9: 29283 | H9: 21730 | I9: 30977 | J9: 25032 | K9: 36855 | L9: 24841 | M9: 13326
A10: 8 | B10: 20581 | C10: 34156 | D10: 19400 | E10: 12598 | F10: 661 | G10: 11507 | H10: 27779 | I10: 17245 | J10: 10405 | L10: 22263 | M10: 28331
A11: 9 | B11: 21147 | C11: 13838 | D11: 26194 | E11: 17896 | F11: 20427 | G11: 23884 | H11: 26731 | I11: 2502 | J11: 12209 | K11: 17687 | L11: 25384 | M11: 16157
A12: 10 | B12: 27169 | C12: 44769 | D12: 24342 | E12: 22545 | F12: 34382 | G12: 59237 | H12: 10010 | I12: 16808 | J12: 14279 | K12: 12323 | L12: 8139 | M12: 31076
A13: 11 | B13: 9052 | C13: 29572 | D13: 25818 | E13: 15433 | F13: 8556 | G13: 17696 | H13: 11351 | I13: 36100 | J13: 23548 | L13: 15459 | M13: 24005
A14: 12 | B14: 13443 | C14: 26078 | D14: 19775 | E14: 2457 | F14: 9676 | G14: 18059 | H14: 17411 | I14: 22568 | J14: 21789 | K14: 21862 | L14: 12577 | M14: 26952

Sheet 9ba.Country Sales by Year 
A1: Order Date | B1: Year | C1: Country Name | D1: Total Revenue
A2: 41047 | B2: =IFERROR(__xludf.DUMMYFUNCTION("YEAR(TO_DATE(A2))"),2012.0) -> 2012 | C2: Albania | D2: 1447182.3
A3: 42245 | B3: =IFERROR(__xludf.DUMMYFUNCTION("YEAR(TO_DATE(A3))"),2015.0) -> 2015 | C3: Albania | D3: 535132.8
A4: 42198 | B4: =IFERROR(__xludf.DUMMYFUNCTION("YEAR(TO_DATE(A4))"),2015.0) -> 2015 | C4: Albania | D4: 5714367.8
A5: 41984 | B5: =IFERROR(__xludf.DUMMYFUNCTION("YEAR(TO_DATE(A5))"),2014.0) -> 2014 | C5: Albania | D5: 191128.6
A6: 42385 | B6: =IFERROR(__xludf.DUMMYFUNCTION("YEAR(TO_DATE(A6))"),2016.0) -> 2016 | C6: Albania | D6: 938278.08
A7: 42930 | B7: =IFERROR(__xludf.DUMMYFUNCTION("YEAR(TO_DATE(A7))"),2017.0) -> 2017 | C7: Albania | D7: 1168804.2
A8: 41858 | B8: =IFERROR(__xludf.DUMMYFUNCTION("YEAR(TO_DATE(A8))"),2014.0) -> 2014 | C8: Albania | D8: 44061.16
A9: 42072 | B9: =IFERROR(__xludf.DUMMYFUNCTION("YEAR(TO_DATE(A9))"),2015.0) -> 2015 | C9: Albania | D9: 128076.16
A10: 41187 | B10: =IFERROR(__xludf.DUMMYFUNCTION("YEAR(TO_DATE(A10))"),2012.0) -> 2012 | C10: Albania | D10: 818058.6
A11: 40532 | B11: =IFERROR(__xludf.DUMMYFUNCTION("YEAR(TO_DATE(A11))"),2010.0) -> 2010 | C11: Albania | D11: 3698206.2
A12: 42643 | B12: =IFERROR(__xludf.DUMMYFUNCTION("YEAR(TO_DATE(A12))"),2016.0) -> 2016 | C12: Albania | D12: 4205426.8
A13: 40640 | B13: =IFERROR(__xludf.DUMMYFUNCTION("YEAR(TO_DATE(A13))"),2011.0) -> 2011 | C13: Albania | D13: 1075643
A14: 40514 | B14: =IFERROR(__xludf.DUMMYFUNCTION("YEAR(TO_DATE(A14))"),2010.0) -> 2010 | C14: Albania | D14: 288528.78
A15: 40413 | B15: =IFERROR(__xludf.DUMMYFUNCTION("YEAR(TO_DATE(A15))"),2010.0) -> 2010 | C15: Albania | D15: 4179632
A16: 40721 | B16: =IFERROR(__xludf.DUMMYFUNCTION("YEAR(TO_DATE(A16))"),2011.0) -> 2011 | C16: Albania | D16: 2189934.8
A17: 41392 | B17: =IFERROR(__xludf.DUMMYFUNCTION("YEAR(TO_DATE(A17))"),2013.0) -> 2013 | C17: Albania | D17: 107426.8
A18: 42592 | B18: =IFERROR(__xludf.DUMMYFUNCTION("YEAR(TO_DATE(A18))"),2016.0) -> 2016 | C18: Albania | D18: 873923.82
A19: 40494 | B19: =IFERROR(__xludf.DUMMYFUNCTION("YEAR(TO_DATE(A19))"),2010.0) -> 2010 | C19: Albania | D19: 364934.85
A20: 41191 | B20: =IFERROR(__xludf.DUMMYFUNCTION("YEAR(TO_DATE(A20))"),2012.0) -> 2012 | C20: Albania | D20: 53333.8
A21: 41305 | B21: =IFERROR(__xludf.DUMMYFUNCTION("YEAR(TO_DATE(A21))"),2013.0) -> 2013 | C21: Albania | D21: 536644.08
A22: 40999 | B22: =IFERROR(__xludf.DUMMYFUNCTION("YEAR(TO_DATE(A22))"),2012.0) -> 2012 | C22: Albania | D22: 3666129.2
A23: 41470 | B23: =IFERROR(__xludf.DUMMYFUNCTION("YEAR(TO_DATE(A23))"),2013.0) -> 2013 | C23: Andorra | D23: 11742.88
A24: 42910 | B24: =IFERROR(__xludf.DUMMYFUNCTION("YEAR(TO_DATE(A24))"),2017.0) -> 2017 | C24: Andorra | D24: 276978.8
A25: 42906 | B25: =IFERROR(__xludf.DUMMYFUNCTION("YEAR(TO_DATE(A25))"),2017.0) -> 2017 | C25: Andorra | D25: 536455.52
A26: 42061 | B26: =IFERROR(__xludf.DUMMYFUNCTION("YEAR(TO_DATE(A26))"),2015.0) -> 2015 | C26: Andorra | D26: 758558.22
A27: 40334 | B27: =IFERROR(__xludf.DUMMYFUNCTION("YEAR(TO_DATE(A27))"),2010.0) -> 2010 | C27: Andorra | D27: 361164.87
A28: 41781 | B28: =IFERROR(__xludf.DUMMYFUNCTION("YEAR(TO_DATE(A28))"),2014.0) -> 2014 | C28: Andorra | D28: 2156507.3
A29: 41009 | B29: =IFERROR(__xludf.DUMMYFUNCTION("YEAR(TO_DATE(A29))"),2012.0) -> 2012 | C29: Andorra | D29: 4275816
A30: 42074 | B30: =IFERROR(__xludf.DUMMYFUNCTION("YEAR(TO_DATE(A30))"),2015.0) -> 2015 | C30: Andorra | D30: 73310.25
A31: 41090 | B31: =IFERROR(__xludf.DUMMYFUNCTION("YEAR(TO_DATE(A31))"),2012.0) -> 2012 | C31: Andorra | D31: 3006187.2
A32: 40301 | B32: =IFERROR(__xludf.DUMMYFUNCTION("YEAR(TO_DATE(A32))"),2010.0) -> 2010 | C32: Andorra | D32: 556306.68
A33: 41238 | B33: =IFERROR(__xludf.DUMMYFUNCTION("YEAR(TO_DATE(A33))"),2012.0) -> 2012 | C33: Andorra | D33: 278341.7
A34: 41340 | B34: =IFERROR(__xludf.DUMMYFUNCTION("YEAR(TO_DATE(A34))"),2013.0) -> 2013 | C34: Andorra | D34: 1599839.8
A35: 42658 | B35: =IFERROR(__xludf.DUMMYFUNCTION("YEAR(TO_DATE(A35))"),2016.0) -> 2016 | C35: Andorra | D35: 851797.74
A36: 42550 | B36: =IFERROR(__xludf.DUMMYFUNCTION("YEAR(TO_DATE(A36))"),2016.0) -> 2016 | C36: Andorra | D36: 68668.8
A37: 40918 | B37: =IFERROR(__xludf.DUMMYFUNCTION("YEAR(TO_DATE(A37))"),2012.0) -> 2012 | C37: Andorra | D37: 1159737
A38: 40409 | B38: =IFERROR(__xludf.DUMMYFUNCTION("YEAR(TO_DATE(A38))"),2010.0) -> 2010 | C38: Andorra | D38: 377464.75
A39: 40448 | B39: =IFERROR(__xludf.DUMMYFUNCTION("YEAR(TO_DATE(A39))"),2010.0) -> 2010 | C39: Andorra | D39: 180482.96
A40: 42083 | B40: =IFERROR(__xludf.DUMMYFUNCTION("YEAR(TO_DATE(A40))"),2015.0) -> 2015 | C40: Andorra | D40: 1052361.2
A41: 42484 | B41: =IFERROR(__xludf.DUMMYFUNCTION("YEAR(TO_DATE(A41))"),2016.0) -> 2016 | C41: Andorra | D41: 167688.3
A42: 40201 | B42: =IFERROR(__xludf.DUMMYFUNCTION("YEAR(TO_DATE(A42))"),2010.0) -> 2010 | C42: Andorra | D42: 1380543.8
A43: 40819 | B43: =IFERROR(__xludf.DUMMYFUNCTION("YEAR(TO_DATE(A43))"),2011.0) -> 2011 | C43: Andorra | D43: 791043.75
A44: 40450 | B44: =IFERROR(__xludf.DUMMYFUNCTION("YEAR(TO_DATE(A44))"),2010.0) -> 2010 | C44: Andorra | D44: 5639530.5
A45: 42598 | B45: =IFERROR(__xludf.DUMMYFUNCTION("YEAR(TO_DATE(A45))"),2016.0) -> 2016 | C45: Andorra | D45: 1553399
A46: 40638 | B46: =IFERROR(__xludf.DUMMYFUNCTION("YEAR(TO_DATE(A46))"),2011.0) -> 2011 | C46: Andorra | D46: 434232.7
A47: 42667 | B47: =IFERROR(__xludf.DUMMYFUNCTION("YEAR(TO_DATE(A47))"),2016.0) -> 2016 | C47: Andorra | D47: 1830357.6
A48: 40578 | B48: =IFERROR(__xludf.DUMMYFUNCTION("YEAR(TO_DATE(A48))"),2011.0) -> 2011 | C48: Andorra | D48: 923719.32
A49: 41729 | B49: =IFERROR(__xludf.DUMMYFUNCTION("YEAR(TO_DATE(A49))"),2014.0) -> 2014 | C49: Andorra | D49: 1966654.2
A50: 40256 | B50: =IFERROR(__xludf.DUMMYFUNCTION("YEAR(TO_DATE(A50))"),2010.0) -> 2010 | C50: Andorra | D50: 1908484.6
A51: 42689 | B51: =IFERROR(__xludf.DUMMYFUNCTION("YEAR(TO_DATE(A51))"),2016.0) -> 2016 | C51: Andorra | D51: 2905638
A52: 42433 | B52: =IFERROR(__xludf.DUMMYFUNCTION("YEAR(TO_DATE(A52))"),2016.0) -> 2016 | C52: Andorra | D52: 49057.14
A53: 41623 | B53: =IFERROR(__xludf.DUMMYFUNCTION("YEAR(TO_DATE(A53))"),2013.0) -> 2013 | C53: Andorra | D53: 100601.18
A54: 42426 | B54: =IFERROR(__xludf.DUMMYFUNCTION("YEAR(TO_DATE(A54))"),2016.0) -> 2016 | C54: Andorra | D54: 3274190.8
A55: 41985 | B55: =IFERROR(__xludf.DUMMYFUNCTION("YEAR(TO_DATE(A55))"),2014.0) -> 2014 | C55: Andorra | D55: 358794.7
A56: 42596 | B56: =IFERROR(__xludf.DUMMYFUNCTION("YEAR(TO_DATE(A56))"),2016.0) -> 2016 | C56: Andorra | D56: 5024053.9
A57: 40191 | B57: =IFERROR(__xludf.DUMMYFUNCTION("YEAR(TO_DATE(A57))"),2010.0) -> 2010 | C57: Andorra | D57: 59549.75
A58: 41786 | B58: =IFERROR(__xludf.DUMMYFUNCTION("YEAR(TO_DATE(A58))"),2014.0) -> 2014 | C58: Andorra | D58: 9171.39
A59: 42869 | B59: =IFERROR(__xludf.DUMMYFUNCTION("YEAR(TO_DATE(A59))"),2017.0) -> 2017 | C59: Andorra | D59: 276587.68
A60: 41556 | B60: =IFERROR(__xludf.DUMMYFUNCTION("YEAR(TO_DATE(A60))"),2013.0) -> 2013 | C60: Andorra | D60: 432127.15
A61: 41336 | B61: =IFERROR(__xludf.DUMMYFUNCTION("YEAR(TO_DATE(A61))"),2013.0) -> 2013 | C61: Andorra | D61: 1015563.5
A62: 40681 | B62: =IFERROR(__xludf.DUMMYFUNCTION("YEAR(TO_DATE(A62))"),2011.0) -> 2011 | C62: Andorra | D62: 73982.56
A63: 40958 | B63: =IFERROR(__xludf.DUMMYFUNCTION("YEAR(TO_DATE(A63))"),2012.0) -> 2012 | C63: Armenia | D63: 2536752.9
A64: 40625 | B64: =IFERROR(__xludf.DUMMYFUNCTION("YEAR(TO_DATE(A64))"),2011.0) -> 2011 | C64: Armenia | D64: 82719.78
A65: 40931 | B65: =IFERROR(__xludf.DUMMYFUNCTION("YEAR(TO_DATE(A65))"),2012.0) -> 2012 | C65: Armenia | D65: 201926.48
A66: 40602 | B66: =IFERROR(__xludf.DUMMYFUNCTION("YEAR(TO_DATE(A66))"),2011.0) -> 2011 | C66: Armenia | D66: 310805.46
A67: 40181 | B67: =IFERROR(__xludf.DUMMYFUNCTION("YEAR(TO_DATE(A67))"),2010.0) -> 2010 | C67: Armenia | D67: 34204.64
A68: 42157 | B68: =IFERROR(__xludf.DUMMYFUNCTION("YEAR(TO_DATE(A68))"),2015.0) -> 2015 | C68: Armenia | D68: 2988668.8
A69: 41972 | B69: =IFERROR(__xludf.DUMMYFUNCTION("YEAR(TO_DATE(A69))"),2014.0) -> 2014 | C69: Armenia | D69: 85966.62
A70: 40604 | B70: =IFERROR(__xludf.DUMMYFUNCTION("YEAR(TO_DATE(A70))"),2011.0) -> 2011 | C70: Armenia | D70: 607115.82
A71: 41310 | B71: =IFERROR(__xludf.DUMMYFUNCTION("YEAR(TO_DATE(A71))"),2013.0) -> 2013 | C71: Armenia | D71: 740520
A72: 40699 | B72: =IFERROR(__xludf.DUMMYFUNCTION("YEAR(TO_DATE(A72))"),2011.0) -> 2011 | C72: Armenia | D72: 313739.4
A73: 42080 | B73: =IFERROR(__xludf.DUMMYFUNCTION("YEAR(TO_DATE(A73))"),2015.0) -> 2015 | C73: Armenia | D73: 32878.92
A74: 40198 | B74: =IFERROR(__xludf.DUMMYFUNCTION("YEAR(TO_DATE(A74))"),2010.0) -> 2010 | C74: Armenia | D74: 1533493.5
A75: 41155 | B75: =IFERROR(__xludf.DUMMYFUNCTION("YEAR(TO_DATE(A75))"),2012.0) -> 2012 | C75: Armenia | D75: 702351.77
A76: 42711 | B76: =IFERROR(__xludf.DUMMYFUNCTION("YEAR(TO_DATE(A76))"),2016.0) -> 2016 | C76: Armenia | D76: 939303.82
A77: 40796 | B77: =IFERROR(__xludf.DUMMYFUNCTION("YEAR(TO_DATE(A77))"),2011.0) -> 2011 | C77: Armenia | D77: 1037962.2
A78: 42256 | B78: =IFERROR(__xludf.DUMMYFUNCTION("YEAR(TO_DATE(A78))"),2015.0) -> 2015 | C78: Armenia | D78: 4985962.5
A79: 42644 | B79: =IFERROR(__xludf.DUMMYFUNCTION("YEAR(TO_DATE(A79))"),2016.0) -> 2016 | C79: Armenia | D79: 144286.38
A80: 40194 | B80: =IFERROR(__xludf.DUMMYFUNCTION("YEAR(TO_DATE(A80))"),2010.0) -> 2010 | C80: Armenia | D80: 290877.07
A81: 41085 | B81: =IFERROR(__xludf.DUMMYFUNCTION("YEAR(TO_DATE(A81))"),2012.0) -> 2012 | C81: Armenia | D81: 2218719.5
A82: 41486 | B82: =IFERROR(__xludf.DUMMYFUNCTION("YEAR(TO_DATE(A82))"),2013.0) -> 2013 | C82: Armenia | D82: 266557.26
A83: 42317 | B83: =IFERROR(__xludf.DUMMYFUNCTION("YEAR(TO_DATE(A83))"),2015.0) -> 2015 | C83: Armenia | D83: 3117767.1
A84: 42710 | B84: =IFERROR(__xludf.DUMMYFUNCTION("YEAR(TO_DATE(A84))"),2016.0) -> 2016 | C84: Armenia | D84: 526913.31
A85: 40219 | B85: =IFERROR(__xludf.DUMMYFUNCTION("YEAR(TO_DATE(A85))"),2010.0) -> 2010 | C85: Armenia | D85: 1272060.2
A86: 40522 | B86: =IFERROR(__xludf.DUMMYFUNCTION("YEAR(TO_DATE(A86))"),2010.0) -> 2010 | C86: Armenia | D86: 375385.89
A87: 42505 | B87: =IFERROR(__xludf.DUMMYFUNCTION("YEAR(TO_DATE(A87))"),2016.0) -> 2016 | C87: Armenia | D87: 1406875.9
A88: 41854 | B88: =IFERROR(__xludf.DUMMYFUNCTION("YEAR(TO_DATE(A88))"),2014.0) -> 2014 | C88: Armenia | D88: 4859329
A89: 42787 | B89: =IFERROR(__xludf.DUMMYFUNCTION("YEAR(TO_DATE(A89))"),2017.0) -> 2017 | C89: Armenia | D89: 594046.08
A90: 42902 | B90: =IFERROR(__xludf.DUMMYFUNCTION("YEAR(TO_DATE(A90))"),2017.0) -> 2017 | C90: Armenia | D90: 1146486.1
A91: 40477 | B91: =IFERROR(__xludf.DUMMYFUNCTION("YEAR(TO_DATE(A91))"),2010.0) -> 2010 | C91: Armenia | D91: 4166163.8
A92: 40311 | B92: =IFERROR(__xludf.DUMMYFUNCTION("YEAR(TO_DATE(A92))"),2010.0) -> 2010 | C92: Austria | D92: 1707721.4
A93: 42925 | B93: =IFERROR(__xludf.DUMMYFUNCTION("YEAR(TO_DATE(A93))"),2017.0) -> 2017 | C93: Austria | D93: 98484.65
A94: 42267 | B94: =IFERROR(__xludf.DUMMYFUNCTION("YEAR(TO_DATE(A94))"),2015.0) -> 2015 | C94: Austria | D94: 1180833.1
A95: 40653 | B95: =IFERROR(__xludf.DUMMYFUNCTION("YEAR(TO_DATE(A95))"),2011.0) -> 2011 | C95: Austria | D95: 81478.89
A96: 41001 | B96: =IFERROR(__xludf.DUMMYFUNCTION("YEAR(TO_DATE(A96))"),2012.0) -> 2012 | C96: Austria | D96: 420549.35
A97: 40761 | B97: =IFERROR(__xludf.DUMMYFUNCTION("YEAR(TO_DATE(A97))"),2011.0) -> 2011 | C97: Austria | D97: 28381.86
A98: 40234 | B98: =IFERROR(__xludf.DUMMYFUNCTION("YEAR(TO_DATE(A98))"),2010.0) -> 2010 | C98: Austria | D98: 4344873.1
A99: 42362 | B99: =IFERROR(__xludf.DUMMYFUNCTION("YEAR(TO_DATE(A99))"),2015.0) -> 2015 | C99: Austria | D99: 1770871.3
A100: 40668 | B100: =IFERROR(__xludf.DUMMYFUNCTION("YEAR(TO_DATE(A100))"),2011.0) -> 2011 | C100: Austria | D100: 957020.72
...

Sheet 9ba. Country Sales by Year Pivo

Sheet 9bb.Country Sales by Month
A1: Order Date | B1: Month | C1: Country Name | D1: Product ID | E1: Product | F1: Units Sold | G1: Total Revenue | H1: Total Profit
A2: 41047 | B2: =TEXT(A2, "YYYY-MM") -> 2012-05 | C2: Albania | D2: 7331 | E2: =VLOOKUP(D2, Products!$A$1:$B$13, 2, FALSE) -> Baby Food | F2: 5669 | G2: 1447182.3 | H2: 543430.34
A3: 42245 | B3: =TEXT(A3, "YYYY-MM") -> 2015-08 | C3: Albania | D3: 8293 | E3: =VLOOKUP(D3, Products!$A$1:$B$13, 2, FALSE) -> Cosmetics | F3: 1224 | G3: 535132.8 | H3: 212816.88
A4: 42198 | B4: =TEXT(A4, "YYYY-MM") -> 2015-07 | C4: Albania | D4: 8681 | E4: =VLOOKUP(D4, Products!$A$1:$B$13, 2, FALSE) -> Office Supplies | F4: 8775 | G4: 5714367.8 | H4: 1107843.8
A5: 41984 | B5: =TEXT(A5, "YYYY-MM") -> 2014-12 | C5: Albania | D5: 1270 | E5: =VLOOKUP(D5, Products!$A$1:$B$13, 2, FALSE) -> Beverages | F5: 4028 | G5: 191128.6 | H5: 63078.48
A6: 42385 | B6: =TEXT(A6, "YYYY-MM") -> 2016-01 | C6: Albania | D6: 2455 | E6: =VLOOKUP(D6, Products!$A$1:$B$13, 2, FALSE) -> Clothes | F6: 8586 | G6: 938278.08 | H6: 630555.84
A7: 42930 | B7: =TEXT(A7, "YYYY-MM") -> 2017-07 | C7: Albania | D7: 7940 | E7: =VLOOKUP(D7, Products!$A$1:$B$13, 2, FALSE) -> Household | F7: 1749 | G7: 1168804.2 | H7: 289861.77
A8: 41858 | B8: =TEXT(A8, "YYYY-MM") -> 2014-08 | C8: Albania | D8: 5988 | E8: =VLOOKUP(D8, Products!$A$1:$B$13, 2, FALSE) -> Vegetables | F8: 286 | G8: 44061.16 | H8: 18055.18
A9: 42072 | B9: =TEXT(A9, "YYYY-MM") -> 2015-03 | C9: Albania | D9: 2455 | E9: =VLOOKUP(D9, Products!$A$1:$B$13, 2, FALSE) -> Clothes | F9: 1172 | G9: 128076.16 | H9: 86071.68
A10: 41187 | B10: =TEXT(A10, "YYYY-MM") -> 2012-10 | C10: Albania | D10: 5988 | E10: =VLOOKUP(D10, Products!$A$1:$B$13, 2, FALSE) -> Vegetables | F10: 5310 | G10: 818058.6 | H10: 335220.3
A11: 40532 | B11: =TEXT(A11, "YYYY-MM") -> 2010-12 | C11: Albania | D11: 7940 | E11: =VLOOKUP(D11, Products!$A$1:$B$13, 2, FALSE) -> Household | F11: 5534 | G11: 3698206.2 | H11: 917149.82
A12: 42643 | B12: =TEXT(A12, "YYYY-MM") -> 2016-09 | C12: Albania | D12: 8293 | E12: =VLOOKUP(D12, Products!$A$1:$B$13, 2, FALSE) -> Cosmetics | F12: 9619 | G12: 4205426.8 | H12: 1672455.5
A13: 40640 | B13: =TEXT(A13, "YYYY-MM") -> 2011-04 | C13: Albania | D13: 2455 | E13: =VLOOKUP(D13, Products!$A$1:$B$13, 2, FALSE) -> Clothes | F13: 9843 | G13: 1075643 | H13: 722869.92
... A241: 41416 | B241: =TEXT(A241, "YYYY-MM") -> 2013-05 | C241: Croatia | D241: 8681 | E241: =VLOOKUP(D241, Products!$A$1:$B$13, 2, FALSE) -> Office Supplies | F241: 4602 | G241: 2996868.4 | H241: 581002.5
A242: 41764 | B242: =TEXT(A242, "YYYY-MM") -> 2014-05 | C242: Croatia | D242: 3127 | E242: =VLOOKUP(D242, Products!$A$1:$B$13, 2, FALSE) -> Personal Care | G242: 0 | H242: 0
A243: 41234 | B243: =TEXT(A243, "YYYY-MM") -> 2012-11 | C243: Croatia | D243: 8681 | E243: =VLOOKUP(D243, Products!$A$1:$B$13, 2, FALSE) -> Office Supplies | F243: 2908 | G243: 1893718.7 | H243: 367135
A244: 40954 | B244: =TEXT(A244, "YYYY-MM") -> 2012-02 | C244: Croatia | D244: 8293 | E244: =VLOOKUP(D244, Products!$A$1:$B$13, 2, FALSE) -> Cosmetics | F244: 6267 | G244: 2739932.4 | H244: 1089643.3
A245: 41362 | B245: =TEXT(A245, "YYYY-MM") -> 2013-03 | C245: Croatia | D245: 3127 | E245: =VLOOKUP(D245, Products!$A$1:$B$13, 2, FALSE) -> Personal Care | F245: 523 | G245: 42744.79 | H245: 13106.38
A246: 40605 | B246: =TEXT(A246, "YYYY-MM") -> 2011-03 | C246: Croatia | D246: 8969 | E246: =VLOOKUP(D246, Products!$A$1:$B$13, 2, FALSE) -> Snacks | F246: 347 | G246: 52945.26 | H246: 19133.58
A247: 40533 | B247: =TEXT(A247, "YYYY-MM") -> 2010-12 | C247: Croatia | D247: 8875 | E247: =VLOOKUP(D247, Products!$A$1:$B$13, 2, FALSE) -> Meat | F247: 8753 | G247: 3692803.2 | H247: 500671.6
A248: 42515 | B248: =TEXT(A248, "YYYY-MM") -> 2016-05 | C248: Croatia | D248: 7940 | E248: =VLOOKUP(D248, Products!$A$1:$B$13, 2, FALSE) -> Household | F248: 1362 | G248: 910183.74 | H248: 225724.26
A249: 40338 | B249: =TEXT(A249, "YYYY-MM") -> 2010-06 | C249: Croatia | D249: 8681 | E249: =VLOOKUP(D249, Products!$A$1:$B$13, 2, FALSE) -> Office Supplies | F249: 1522 | G249: 991141.62 | H249: 192152.5
A250: 41390 | B250: =TEXT(A250, "YYYY-MM") -> 2013-04 | C250: Croatia | D250: 7940 | E250: =VLOOKUP(D250, Products!$A$1:$B$13, 2, FALSE) -> Household | F250: 9680 | G250: 6468853.6 | H250: 1604266.4
A251: 41452 | B251: =TEXT(A251, "YYYY-MM") -> 2013-06 | C251: Croatia | D251: 7331 | E251: =VLOOKUP(D251, Products!$A$1:$B$13, 2, FALSE) -> Baby Food | F251: 1539 | G251: 392875.92 | H251: 147528.54
A252: 42530 | B252: =TEXT(A252, "YYYY-MM") -> 2016-06 | C252: Croatia | D252: 2455 | E252: =VLOOKUP(D252, Products!$A$1:$B$13, 2, FALSE) -> Clothes | F252: 8841 | G252: 966144.48 | H252: 649283.04
A253: 41652 | B253: =TEXT(A253, "YYYY-MM") -> 2014-01 | C253: Croatia | D253: 2455 | E253: =VLOOKUP(D253, Products!$A$1:$B$13, 2, FALSE) -> Clothes | F253: 4958 | G253: 541810.24 | H253: 364115.52
A254: 42772 | B254: =TEXT(A254, "YYYY-MM") -> 2017-02 | C254: Croatia | D254: 1270 | E254: =VLOOKUP(D254, Products!$A$1:$B$13, 2, FALSE) -> Beverages | F254: 4674 | G254: 221781.3 | H254: 73194.84
... A1111: 40859 | B1111: =TEXT(A1111, "YYYY-MM") -> 2011-11 | C1111: Spain | D1111: 5988 | E1111: =VLOOKUP(D1111, Products!$A$1:$B$13, 2, FALSE) -> Vegetables | F1111: 4419 | G1111: 680791.14 | H1111: 278971.47
A1112: 41779 | B1112: =TEXT(A1112, "YYYY-MM") -> 2014-05 | C1112: Spain | D1112: 8875 | E1112: =VLOOKUP(D1112, Products!$A$1:$B$13, 2, FALSE) -> Meat | G1112: 0 | H1112: 0
A1113: 41249 | B1113: =TEXT(A1113, "YYYY-MM") -> 2012-12 | C1113: Spain | D1113: 4594 | E1113: =VLOOKUP(D1113, Products!$A$1:$B$13, 2, FALSE) -> Fruits | F1113: 3103 | G1113: 28950.99 | H1113: 7478.23
A1114: 40647 | B1114: =TEXT(A1114, "YYYY-MM") -> 2011-04 | C1114: Spain | D1114: 5988 | E1114: =VLOOKUP(D1114, Products!$A$1:$B$13, 2, FALSE) -> Vegetables | F1114: 3545 | G1114: 546142.7 | H1114: 223795.85
A1115: 41022 | B1115: =TEXT(A1115, "YYYY-MM") -> 2012-04 | C1115: Spain | D1115: 7940 | E1115: =VLOOKUP(D1115, Products!$A$1:$B$13, 2, FALSE) -> Household | F1115: 2819 | G1115: 1883853.1 | H1115: 467192.87
A1116: 42785 | B1116: =TEXT(A1116, "YYYY-MM") -> 2017-02 | C1116: Spain | D1116: 8969 | E1116: =VLOOKUP(D1116, Products!$A$1:$B$13, 2, FALSE) -> Snacks | F1116: 4844 | G1116: 739097.52 | H1116: 267098.16
A1117: 41137 | B1117: =TEXT(A1117, "YYYY-MM") -> 2012-08 | C1117: Spain | D1117: 2455 | E1117: =VLOOKUP(D1117, Products!$A$1:$B$13, 2, FALSE) -> Clothes | F1117: 4897 | G1117: 535144.16 | H1117: 359635.68
A1118: 40528 | B1118: =TEXT(A1118, "YYYY-MM") -> 2010-12 | C1118: Spain | D1118: 5988 | E1118: =VLOOKUP(D1118, Products!$A$1:$B$13, 2, FALSE) -> Vegetables | F1118: 9501 | G1118: 1463724.1 | H1118: 599798.13
A1119: 42738 | B1119: =TEXT(A1119, "YYYY-MM") -> 2017-01 | C1119: Spain | D1119: 8293 | E1119: =VLOOKUP(D1119, Products!$A$1:$B$13, 2, FALSE) -> Cosmetics | F1119: 2394 | G1119: 1046656.8 | H1119: 416244.78
A1120: 42008 | B1120: =TEXT(A1120, "YYYY-MM") -> 2015-01 | C1120: Spain | D1120: 2103 | E1120: =VLOOKUP(D1120, Products!$A$1:$B$13, 2, FALSE) -> Cereal | F1120: 5222 | G1120: 1074165.4 | H1120: 462616.98
A1121: 42156 | B1121: =TEXT(A1121, "YYYY-MM") -> 2015-06 | C1121: Spain | D1121: 5988 | E1121: =VLOOKUP(D1121, Products!$A$1:$B$13, 2, FALSE) -> Vegetables | F1121: 6142 | G1121: 946236.52 | H1121: 387744.46
A1122: 40876 | B1122: =TEXT(A1122, "YYYY-MM") -> 2011-11 | C1122: Spain | D1122: 8875 | E1122: =VLOOKUP(D1122, Products!$A$1:$B$13, 2, FALSE) -> Meat | F1122: 7701 | G1122: 3248974.9 | H1122: 440497.2
A1123: 42301 | B1123: =TEXT(A1123, "YYYY-MM") -> 2015-10 | C1123: Spain | D1123: 4594 | E1123: =VLOOKUP(D1123, Products!$A$1:$B$13, 2, FALSE) -> Fruits | F1123: 3540 | G1123: 33028.2 | H1123: 8531.4
A1124: 41593 | B1124: =TEXT(A1124, "YYYY-MM") -> 2013-11 | C1124: Spain | D1124: 8875 | E1124: =VLOOKUP(D1124, Products!$A$1:$B$13, 2, FALSE) -> Meat | F1124: 9336 | G1124: 3938765 | H1124: 534019.2
... A1331: 41071 | B1331: =TEXT(A1331, "YYYY-MM") -> 2012-06 | C1331: Unknown Country | D1331: 4594 | E1331: =VLOOKUP(D1331, Products!$A$1:$B$13, 2, FALSE) -> Fruits | F1331: 6362 | G1331: 59357.46 | H1331: 15332.42

Sheet 9bb.Country Sales by Month Pivo

Sheet 9d.Year-on-year Average Sales
A1: Year-over-year trends | B1: Year
A2: Month | B2: 2014 | C2: 2015 | D2: 2016 | E2: 2017
A3: 1 | B3: 5141.6667 | C3: 5061 | D3: 5798 | E3: 6340.3333
A4: 2 | B4: 4025.75 | C4: 3198 | D4: 5035.875 | E4: 4472.875
A5: 3 | B5: 4701 | C5: 3506.1429 | D5: 4035 | E5: 5484.4
A6: 4 | B6: 5150.875 | C6: 4217 | D6: 3932 | E6: 3637.2
A7: 5 | B7: 6102.2 | C7: 3645.4444 | D7: 4332.125 | E7: 2388.7273
A8: 6 | B8: 5411.5 | C8: 5973.5 | D8: 3473 | E8: 4229.625
A9: 7 | B9: 4316.875 | C9: 4230.2857 | D9: 6260.2222 | E9: 5633.4444
A10: 8 | B10: 4367.8889 | C10: 5938.7778 | D10: 2617
A11: 9 | B11: 5367.5 | C11: 4893.3333 | D11: 3500
A12: 10 | B12: 3778 | C12: 5737.6667 | D12: 3121.4
A13: 11 | B13: 3297.5 | C13: 5076.1429 | D13: 4589.8333
A14: 12 | B14: 5703.4 | C14: 3072.8571 | D14: 4994

Sheet 8d.Profit v. Interval Pivot

Sheet 8c.Region Interval Table
A1: Country Region | B1: # of Days Shipment Turnaround
A2: Europe | B2: =events!D2-D1331 -> 35
A3: Europe | B3: =events!D3-D1332 -> 47
A4: Europe | B4: =events!D4-D1333 -> 16
A5: Europe | B5: =events!D5-D1334 -> 44
A6: Europe | B6: =events!D6-D1335 -> 49
A7: Europe | B7: =events!D7-D1336 -> 2
A8: Europe | B8: =events!D8-D1337 -> 18
A9: Europe | B9: =events!D9-D1338 -> 12
A10: Europe | B10: =events!D10-D1339 -> 29
A11: Europe | B11: =events!D11-D1340 -> 4
A12: Europe | B12: =events!D12-D1341 -> 9
A13: Europe | B13: =events!D13-D1342 -> 11
... A1331: Unknown Country | B1331: =events!D1331-D2660 -> 27

Sheet 8c.Region Interval Pivot

Sheet 8b.Country Interval Table
A1: Country Name | B1: # of Days Shipment Turnaround
A2: Albania | B2: =events!D2-D1331 -> 35
A3: Albania | B3: =events!D3-D1332 -> 47
A4: Albania | B4: =events!D4-D1333 -> 16
A5: Albania | B5: =events!D5-D1334 -> 44
A6: Albania | B6: =events!D6-D1335 -> 49
A7: Albania | B7: =events!D7-D1336 -> 2
A8: Albania | B8: =events!D8-D1337 -> 18
A9: Albania | B9: =events!D9-D1338 -> 12
A10: Albania | B10: =events!D10-D1339 -> 29
A11: Albania | B11: =events!D11-D1340 -> 4
A12: Albania | B12: =events!D12-D1341 -> 9
A13: Albania | B13: =events!D13-D1342 -> 11
... A1331: Unknown Country | B1331: =events!D1331-D2660 -> 27

Sheet 8b.Country Interval Pivot

Sheet 8a. Product Interval Table
A1: Product ID | B1: Product Category | C1: Order Turnaround Days | D1: Product | E1: Average
A2: 7331 | B2: =VLOOKUP(A2,'5.Product popularity'!A:B,2,False) -> Baby Food | C2: 8 | D2: {=UNIQUE(B11:B1340)} -> Household | E2: 20.721739
A3: 8293 | B3: =VLOOKUP(A3,'5.Product popularity'!A:B,2,False) -> Cosmetics | C3: 47 | D3: Cosmetics | E3: 23.104762
A4: 8681 | B4: =VLOOKUP(A4,'5.Product popularity'!A:B,2,False) -> Office Supplies | C4: 16 | D4: Clothes | E4: 23.491228
A5: 1270 | B5: =VLOOKUP(A5,'5.Product popularity'!A:B,2,False) -> Beverages | C5: 44 | D5: Snacks | E5: 23.938144
A6: 2455 | B6: =VLOOKUP(A6,'5.Product popularity'!A:B,2,False) -> Clothes | C6: 49 | D6: Beverages | E6: 24.123967
A7: 7940 | B7: =VLOOKUP(A7,'5.Product popularity'!A:B,2,False) -> Household | C7: 2 | D7: Office Supplies | E7: 24.419643
A8: 5988 | B8: =VLOOKUP(A8,'5.Product popularity'!A:B,2,False) -> Vegetables | C8: 18 | D8: Meat | E8: 25.543689
A9: 2455 | B9: =VLOOKUP(A9,'5.Product popularity'!A:B,2,False) -> Clothes | C9: 12 | D9: Baby Food | E9: 25.846847
A10: 5988 | B10: =VLOOKUP(A10,'5.Product popularity'!A:B,2,False) -> Vegetables | C10: 29 | D10: Personal Care | E10: 25.912281
A11: 7940 | B11: =VLOOKUP(A11,'5.Product popularity'!A:B,2,False) -> Household | C11: 4 | D11: Vegetables | E11: 26.098214
A12: 8293 | B12: =VLOOKUP(A12,'5.Product popularity'!A:B,2,False) -> Cosmetics | C12: 9 | D12: Fruits | E12: 26.707317
A13: 2455 | B13: =VLOOKUP(A13,'5.Product popularity'!A:B,2,False) -> Clothes | C13: 11 | D13: Cereal | E13: 27.184466
A14: 8969 | B14: =VLOOKUP(A14,'5.Product popularity'!A:B,2,False) -> Snacks | C14: 5
A15: 8293 | B15: =VLOOKUP(A15,'5.Product popularity'!A:B,2,False) -> Cosmetics | C15: 33
A16: 8293 | B16: =VLOOKUP(A16,'5.Product popularity'!A:B,2,False) -> Cosmetics | C16: 46
A17: 1270 | B17: =VLOOKUP(A17,'5.Product popularity'!A:B,2,False) -> Beverages | C17: 27
A18: 8681 | B18: =VLOOKUP(A18,'5.Product popularity'!A:B,2,False) -> Office Supplies | C18: 27
A19: 8875 | B19: =VLOOKUP(A19,'5.Product popularity'!A:B,2,False) -> Meat | C19: 39
A20: 1270 | B20: =VLOOKUP(A20,'5.Product popularity'!A:B,2,False) -> Beverages | C20: 20
A21: 8875 | B21: =VLOOKUP(A21,'5.Product popularity'!A:B,2,False) -> Meat | C21: 41
A22: 7940 | B22: =VLOOKUP(A22,'5.Product popularity'!A:B,2,False) -> Household | C22: 36
A23: 7331 | B23: =VLOOKUP(A23,'5.Product popularity'!A:B,2,False) -> Baby Food | C23: 45
A24: 7331 | B24: =VLOOKUP(A24,'5.Product popularity'!A:B,2,False) -> Baby Food | C24: 50
A25: 2455 | B25: =VLOOKUP(A25,'5.Product popularity'!A:B,2,False) -> Clothes | C25: 46
... A1331: 4594 | B1331: =VLOOKUP(A1331,'5.Product popularity'!A:B,2,False) -> Fruits | C1331: 27

Sheet 8a.Product Interval Pivot

Sheet 7.Sales Channels
A1: Sales Channels | B1: # of Units Sold | C1: Percentage of Total Sales
A2: Online | B2: =SUMIF(events!M:M,A2,events!N:N) -> 3256161 | C2: =B2/SUM(events!N:N) -> 0.49511885
A3: Offline | B3: =SUMIF(events!M:M,A3,events!N:N) -> 3320363 | C3: =B3/SUM(events!N:N) -> 0.50488115

Sheet countries
A1: Name | B1: alpha-2 | C1: alpha-3 | D1: Country Name | E1: region | F1: sub-region
A2: Afghanistan | B2: AF | C2: AFG | D2: Afghanistan | E2: Asia | F2: Southern Asia
A3: Åland Islands | B3: AX | C3: ALA | D3: Åland Islands | E3: Europe | F3: Northern Europe
A4: Albania | B4: AL | C4: ALB | D4: Albania | E4: Europe | F4: Southern Europe
A5: Algeria | B5: DZ | C5: DZA | D5: Algeria | E5: Africa | F5: Northern Africa
A6: American Samoa | B6: AS | C6: ASM | D6: American Samoa | E6: Oceania | F6: Polynesia
A7: Andorra | B7: AD | C7: AND | D7: Andorra | E7: Europe | F7: Southern Europe
A8: Angola | B8: AO | C8: AGO | D8: Angola | E8: Africa | F8: Sub-Saharan Africa
A9: Anguilla | B9: AI | C9: AIA | D9: Anguilla | E9: Americas | F9: Latin America and the Caribbean
A10: Antarctica | B10: AQ | C10: ATA | D10: Antarctica
A11: Antigua and Barbuda | B11: AG | C11: ATG | D11: Antigua and Barbuda | E11: Americas | F11: Latin America and the Caribbean
A12: Argentina | B12: AR | C12: ARG | D12: Argentina | E12: Americas | F12: Latin America and the Caribbean
A13: Armenia | B13: AM | C13: ARM | D13: Armenia | E13: Asia | F13: Western Asia
A14: Aruba | B14: AW | C14: ABW | D14: Aruba | E14: Americas | F14: Latin America and the Caribbean
A15: Australia | B15: AU | C15: AUS | D15: Australia | E15: Oceania | F15: Australia and New Zealand
A16: Austria | B16: AT | C16: AUT | D16: Austria | E16: Europe | F16: Western Europe
A17: Azerbaijan | B17: AZ | C17: AZE | D17: Azerbaijan | E17: Asia | F17: Western Asia
A18: Bahamas | B18: BS | C18: BHS | D18: Bahamas | E18: Americas | F18: Latin America and the Caribbean
A19: Bahrain | B19: BH | C19: BHR | D19: Bahrain | E19: Asia | F19: Western Asia
A20: Bangladesh | B20: BD | C20: BGD | D20: Bangladesh | E20: Asia | F20: Southern Asia
A21: Barbados | B21: BB | C21: BRB | D21: Barbados | E21: Americas | F21: Latin America and the Caribbean
A22: Belarus | B22: BY | C22: BLR | D22: Belarus | E22: Europe | F22: Eastern Europe
... A250: Zimbabwe | B250: ZW | C250: ZWE | D250: Zimbabwe | E250: Africa | F250: Sub-Saharan Africa

Sheet 6a.Top 20 countries analytics
A1: Country Name | B1: Total Revenue | C1: Total Cost | D1: Total Profit
A2: Afghanistan | B2: =VLOOKUP(A2,events!I2:S1331,9,FALSE) -> #N/A
A3: Åland Islands | B3: =VLOOKUP(A3,events!I3:S1332,9,FALSE) -> #N/A
A4: Monaco | B4: =VLOOKUP(A4,events!I148:S1477,9,FALSE) -> 6261689.9 | C4: =VLOOKUP(A4,events!I148:S1477,10,FALSE) -> 4708799.8 | D4: =VLOOKUP(A4,events!$I$2:$S$1331,11,FALSE) -> 1552890.1
A5: Algeria | B5: =VLOOKUP(A5,events!I5:S1334,9,FALSE) -> #N/A
A6: American Samoa | B6: =VLOOKUP(A6,events!I6:S1335,9,FALSE) -> #N/A
A7: Albania | B7: =VLOOKUP(A7,events!I4:S1333,9,FALSE) -> 5714367.8 | C7: =VLOOKUP(A7,events!I4:S1333,10,FALSE) -> 4606524 | D7: =VLOOKUP(A7,events!$I$2:$S$1331,11,FALSE) -> 543430.34
A8: Angola | B8: =VLOOKUP(A8,events!I8:S1337,9,FALSE) -> #N/A
A9: Anguilla | B9: =VLOOKUP(A9,events!I9:S1338,9,FALSE) -> #N/A
A10: Antarctica | B10: =VLOOKUP(A10,events!I10:S1339,9,FALSE) -> #N/A
A11: Antigua and Barbuda | B11: =VLOOKUP(A11,events!I11:S1340,9,FALSE) -> #N/A
A12: Argentina | B12: =VLOOKUP(A12,events!I12:S1341,9,FALSE) -> #N/A
A13: Ukraine | B13: =VLOOKUP(A13,events!I234:S1563,9,FALSE) -> 4803325 | C13: =VLOOKUP(A13,events!I234:S1563,10,FALSE) -> 3872105 | D13: =VLOOKUP(A13,events!$I$2:$S$1331,11,FALSE) -> 931220
A14: Aruba | B14: =VLOOKUP(A14,events!I14:S1343,9,FALSE) -> #N/A
A15: Australia | B15: =VLOOKUP(A15,events!I15:S1344,9,FALSE) -> #N/A
A16: Cyprus | B16: =VLOOKUP(A16,events!I60:S1389,9,FALSE) -> 3840464.7 | C16: =VLOOKUP(A16,events!I60:S1389,10,FALSE) -> 3319773.1 | D16: =VLOOKUP(A16,events!$I$2:$S$1331,11,FALSE) -> 520691.6
A17: Azerbaijan | B17: =VLOOKUP(A17,events!I17:S1346,9,FALSE) -> #N/A
A18: Bahamas | B18: =VLOOKUP(A18,events!I18:S1347,9,FALSE) -> #N/A
A19: Bahrain | B19: =VLOOKUP(A19,events!I19:S1348,9,FALSE) -> #N/A
A20: Bangladesh | B20: =VLOOKUP(A20,events!I20:S1349,9,FALSE) -> #N/A
A21: Barbados | B21: =VLOOKUP(A21,events!I21:S1350,9,FALSE) -> #N/A
A22: Hungary | B22: =VLOOKUP(A22,events!I103:S1432,9,FALSE) -> 2544631 | C22: =VLOOKUP(A22,events!I103:S1432,10,FALSE) -> 1589098.6 | D22: =VLOOKUP(A22,events!$I$2:$S$1331,11,FALSE) -> 955532.48
A23: Armenia | B23: =VLOOKUP(A23,events!I13:S1342,9,FALSE) -> 2536752.9 | C23: =VLOOKUP(A23,events!I13:S1342,10,FALSE) -> 1907641.8 | D23: =VLOOKUP(A23,events!$I$2:$S$1331,11,FALSE) -> 629111.08
A24: Belize | B24: =VLOOKUP(A24,events!I24:S1353,9,FALSE) -> #N/A
A25: Benin | B25: =VLOOKUP(A25,events!I25:S1354,9,FALSE) -> #N/A
A26: Bermuda | B26: =VLOOKUP(A26,events!I26:S1355,9,FALSE) -> #N/A
A27: Bhutan | B27: =VLOOKUP(A27,events!I27:S1356,9,FALSE) -> #N/A
A28: Bolivia (Plurinational State of) | B28: =VLOOKUP(A28,events!I28:S1357,9,FALSE) -> #N/A
A29: Bonaire, Sint Eustatius and Saba | B29: =VLOOKUP(A29,events!I29:S1358,9,FALSE) -> #N/A
A30: Romania | B30: =VLOOKUP(A30,events!I184:S1513,9,FALSE) -> 2303902 | C30: =VLOOKUP(A30,events!I184:S1513,10,FALSE) -> 1438765.5 | D30: =VLOOKUP(A30,events!$I$2:$S$1331,11,FALSE) -> 865136.5
A31: Botswana | B31: =VLOOKUP(A31,events!I31:S1360,9,FALSE) -> #N/A
A32: Bouvet Island | B32: =VLOOKUP(A32,events!I32:S1361,9,FALSE) -> #N/A
A33: Brazil | B33: =VLOOKUP(A33,events!I33:S1362,9,FALSE) -> #N/A
A34: British Indian Ocean Territory | B34: =VLOOKUP(A34,events!I34:S1363,9,FALSE) -> #N/A
A35: Brunei Darussalam | B35: =VLOOKUP(A35,events!I35:S1364,9,FALSE) -> #N/A
A36: Switzerland | B36: =VLOOKUP(A36,events!I217:S1546,9,FALSE) -> 2021307 | C36: =VLOOKUP(A36,events!I217:S1546,10,FALSE) -> 1262287.6 | D36: =VLOOKUP(A36,events!$I$2:$S$1331,11,FALSE) -> 759019.48
A37: Burkina Faso | B37: =VLOOKUP(A37,events!I37:S1366,9,FALSE) -> #N/A
A38: Burundi | B38: =VLOOKUP(A38,events!I38:S1367,9,FALSE) -> #N/A
A39: Cabo Verde | B39: =VLOOKUP(A39,events!I39:S1368,9,FALSE) -> #N/A
A40: Cambodia | B40: =VLOOKUP(A40,events!I40:S1369,9,FALSE) -> #N/A
A41: Cameroon | B41: =VLOOKUP(A41,events!I41:S1370,9,FALSE) -> #N/A
A42: Canada | B42: =VLOOKUP(A42,events!I42:S1371,9,FALSE) -> #N/A
A43: Cayman Islands | B43: =VLOOKUP(A43,events!I43:S1372,9,FALSE) -> #N/A
A44: Central African Republic | B44: =VLOOKUP(A44,events!I44:S1373,9,FALSE) -> #N/A
A45: Chad | B45: =VLOOKUP(A45,events!I45:S1374,9,FALSE) -> #N/A
A46: Chile | B46: =VLOOKUP(A46,events!I46:S1375,9,FALSE) -> #N/A
A47: China | B47: =VLOOKUP(A47,events!I47:S1376,9,FALSE) -> #N/A
A48: Christmas Island | B48: =VLOOKUP(A48,events!I48:S1377,9,FALSE) -> #N/A
... A56: Côte d'Ivoire | B56: =VLOOKUP(A56,events!I56:S1385,9,FALSE) -> #N/A
A57: Austria | B57: =VLOOKUP(A57,events!I16:S1345,9,FALSE) -> 1707721.4 | C57: =VLOOKUP(A57,events!I16:S1345,10,FALSE) -> 972247.22 | D57: =VLOOKUP(A57,events!$I$2:$S$1331,11,FALSE) -> 735474.18
A58: Cuba | B58: =VLOOKUP(A58,events!I58:S1387,9,FALSE) -> #N/A
A59: Curaçao | B59: =VLOOKUP(A59,events!I59:S1388,9,FALSE) -> #N/A
A60: Germany | B60: =VLOOKUP(A60,events!I85:S1414,9,FALSE) -> 1504695.5 | C60: =VLOOKUP(A60,events!I85:S1414,10,FALSE) -> 856659.65 | D60: =VLOOKUP(A60,events!$I$2:$S$1331,11,FALSE) -> 648035.85
A61: Macedonia | B61: =VLOOKUP(A61,events!I166:S1495,9,FALSE) -> 1472854.7 | C61: =VLOOKUP(A61,events!I166:S1495,10,FALSE) -> 940588.32 | D61: =VLOOKUP(A61,events!$I$2:$S$1331,11,FALSE) -> 532266.42
A62: Russia | B62: =VLOOKUP(A62,events!I185:S1514,9,FALSE) -> 1453690 | C62: =VLOOKUP(A62,events!I185:S1514,10,FALSE) -> 875572.25 | D62: =VLOOKUP(A62,events!$I$2:$S$1331,11,FALSE) -> 578117.75
A63: Djibouti | B63: =VLOOKUP(A63,events!I63:S1392,9,FALSE) -> #N/A
A64: Dominica | B64: =VLOOKUP(A64,events!I64:S1393,9,FALSE) -> #N/A
A65: Dominican Republic | B65: =VLOOKUP(A65,events!I65:S1394,9,FALSE) -> #N/A
A66: Ecuador | B66: =VLOOKUP(A66,events!I66:S1395,9,FALSE) -> #N/A
A67: Egypt | B67: =VLOOKUP(A67,events!I67:S1396,9,FALSE) -> #N/A
A68: El Salvador | B68: =VLOOKUP(A68,events!I68:S1397,9,FALSE) -> #N/A
A69: Equatorial Guinea | B69: =VLOOKUP(A69,events!I69:S1398,9,FALSE) -> #N/A
A70: Eritrea | B70: =VLOOKUP(A70,events!I70:S1399,9,FALSE) -> #N/A
A71: Slovakia | B71: =VLOOKUP(A71,events!I204:S1533,9,FALSE) -> 1445686.2 | C71: =VLOOKUP(A71,events!I204:S1533,10,FALSE) -> 1165411.2 | D71: =VLOOKUP(A71,events!$I$2:$S$1331,11,FALSE) -> 280275
A72: Eswatini | B72: =VLOOKUP(A72,events!I72:S1401,9,FALSE) -> #N/A
A73: Ethiopia | B73: =VLOOKUP(A73,events!I73:S1402,9,FALSE) -> #N/A
A74: Falkland Islands (Malvinas) | B74: =VLOOKUP(A74,events!I74:S1403,9,FALSE) -> #N/A
A75: Faroe Islands | B75: =VLOOKUP(A75,events!I75:S1404,9,FALSE) -> #N/A
A76: Fiji | B76: =VLOOKUP(A76,events!I76:S1405,9,FALSE) -> #N/A
A77: Croatia | B77: =VLOOKUP(A77,events!I57:S1386,9,FALSE) -> 1339454.2 | C77: =VLOOKUP(A77,events!I57:S1386,10,FALSE) -> 836476.74 | D77: =VLOOKUP(A77,events!$I$2:$S$1331,11,FALSE) -> 502977.42
A78: Luxembourg | B78: =VLOOKUP(A78,events!I132:S1461,9,FALSE) -> 1244745.3 | C78: =VLOOKUP(A78,events!I132:S1461,10,FALSE) -> 777331.92 | D78: =VLOOKUP(A78,events!$I$2:$S$1331,11,FALSE) -> 467413.36
A79: French Guiana | B79: =VLOOKUP(A79,events!I79:S1408,9,FALSE) -> #N/A
A80: French Polynesia | B80: =VLOOKUP(A80,events!I80:S1409,9,FALSE) -> #N/A
A81: French Southern Territories | B81: =VLOOKUP(A81,events!I81:S1410,9,FALSE) -> #N/A
A82: Gabon | B82: =VLOOKUP(A82,events!I82:S1411,9,FALSE) -> #N/A
A83: Gambia | B83: =VLOOKUP(A83,events!I83:S1412,9,FALSE) -> #N/A
A84: Finland | B84: =VLOOKUP(A84,events!I77:S1406,9,FALSE) -> 1107900.2 | C84: =VLOOKUP(A84,events!I77:S1406,10,FALSE) -> 630754.46 | D84: =VLOOKUP(A84,events!$I$2:$S$1331,11,FALSE) -> 477145.74
A85: Slovenia | B85: =VLOOKUP(A85,events!I205:S1534,9,FALSE) -> 1045372.5 | C85: =VLOOKUP(A85,events!I205:S1534,10,FALSE) -> 342845.44 | D85: =VLOOKUP(A85,events!$I$2:$S$1331,11,FALSE) -> 702527.04
A86: Ghana | B86: =VLOOKUP(A86,events!I86:S1415,9,FALSE) -> #N/A
A87: Gibraltar | B87: =VLOOKUP(A87,events!I87:S1416,9,FALSE) -> #N/A
A88: Estonia | B88: =VLOOKUP(A88,events!I71:S1400,9,FALSE) -> 714018.16 | C88: =VLOOKUP(A88,events!I71:S1400,10,FALSE) -> 445897.74 | D88: =VLOOKUP(A88,events!$I$2:$S$1331,11,FALSE) -> 268120.42
A89: Greenland | B89: =VLOOKUP(A89,events!I89:S1418,9,FALSE) -> #N/A
A90: Grenada | B90: =VLOOKUP(A90,events!I90:S1419,9,FALSE) -> #N/A
A91: Guadeloupe | B91: =VLOOKUP(A91,events!I91:S1420,9,FALSE) -> #N/A
A92: Guam | B92: =VLOOKUP(A92,events!I92:S1421,9,FALSE) -> #N/A
A93: Guatemala | B93: =VLOOKUP(A93,events!I93:S1422,9,FALSE) -> #N/A
A94: Guernsey | B94: =VLOOKUP(A94,events!I94:S1423,9,FALSE) -> #N/A
A95: Guinea | B95: =VLOOKUP(A95,events!I95:S1424,9,FALSE) -> #N/A
A96: Guinea-Bissau | B96: =VLOOKUP(A96,events!I96:S1425,9,FALSE) -> #N/A
A97: Guyana | B97: =VLOOKUP(A97,events!I97:S1426,9,FALSE) -> #N/A
A98: Haiti | B98: =VLOOKUP(A98,events!I98:S1427,9,FALSE) -> #N/A
A99: Heard Island and McDonald Islands | B99: =VLOOKUP(A99,events!I99:S1428,9,FALSE) -> #N/A
A100: Holy See | B100: =VLOOKUP(A100,events!I100:S1429,9,FALSE) -> #N/A
... A102: Hong Kong | B102: =VLOOKUP(A102,events!I102:S1431,9,FALSE) -> #N/A
A103: Ireland | B103: =VLOOKUP(A103,events!I109:S1438,9,FALSE) -> 710450 | C103: =VLOOKUP(A103,events!I109:S1438,10,FALSE) -> 427911.25 | D103: =VLOOKUP(A103,events!$I$2:$S$1331,11,FALSE) -> 282538.75
A104: Italy | B104: =VLOOKUP(A104,events!I112:S1441,9,FALSE) -> 695020.8 | C104: =VLOOKUP(A104,events!I112:S1441,10,FALSE) -> 227942.4 | D104: =VLOOKUP(A104,events!$I$2:$S$1331,11,FALSE) -> 467078.4
A105: India | B105: =VLOOKUP(A105,events!I105:S1434,9,FALSE) -> #N/A
A106: Indonesia | B106: =VLOOKUP(A106,events!I106:S1435,9,FALSE) -> #N/A
A107: Iran (Islamic Republic of) | B107: =VLOOKUP(A107,events!I107:S1436,9,FALSE) -> #N/A
A108: Iraq | B108: =VLOOKUP(A108,events!I108:S1437,9,FALSE) -> #N/A
...

Sheet 6bc.Regions sub-regions analyti
A1: Region Name | B1: Total Revenue | C1: Total Cost | D1: Total Profit | G1: Sub-Regions | H1: Total Revenue | I1: Total Cost | J1: Total Profit
A2: {=UNIQUE(events!J2:J1331)} -> Europe | B2: =SUMIF(events!J:J,A2,events!Q:Q) -> 1505652874 | C2: =SUMIF(events!J:J,A2,events!R:R) -> 1057096092 | D2: =SUMIF(events!J:J,A2,events!S:S) -> 4.4855678e+08 | G2: {=UNIQUE(events!K2:K1331)} -> Southern Europe | H2: =SUMIF(events!K:K,G2,events!Q:Q) -> 5.6203228e+08 | I2: =SUMIF(events!K:K,G2,events!R:R) -> 3.9573584e+08 | J2: =SUMIF(events!K:K,G2,events!S:S) -> 1.6629645e+08
A3: Asia | B3: =SUMIF(events!J:J,A3,events!Q:Q) -> 93330887 | C3: =SUMIF(events!J:J,A3,events!R:R) -> 68178634 | D3: =SUMIF(events!J:J,A3,events!S:S) -> 25152253 | G3: Western Asia | H3: =SUMIF(events!K:K,G3,events!Q:Q) -> 93330887 | I3: =SUMIF(events!K:K,G3,events!R:R) -> 68178634 | J3: =SUMIF(events!K:K,G3,events!S:S) -> 25152253
A4: Unknown Country | G4: Western Europe
G5: Eastern Europe | H5: =SUMIF(events!K:K,G5,events!Q:Q) -> 3.7868653e+08 | I5: =SUMIF(events!K:K,G5,events!R:R) -> 2.6741389e+08 | J5: =SUMIF(events!K:K,G5,events!S:S) -> 1.1127264e+08
G6: Northern Europe | H6: =SUMIF(events!K:K,G6,events!Q:Q) -> 2.9641078e+08 | I6: =SUMIF(events!K:K,G6,events!R:R) -> 2.0521693e+08 | J6: =SUMIF(events!K:K,G6,events!S:S) -> 91193848
G7: Unknown Country

Sheet 5.Product popularity
A1: Product ID | B1: Product Type | C1: # of units sold | D1: Total revenue | E1: Total cost | F1: Total profit
A2: 2455 | B2: Clothes | C2: 8586 | D2: 938278.08 | E2: 307722.24 | F2: 630555.84
A3: 4594 | B3: Fruits | C3: 7360 | D3: 68668.8 | E3: 50931.2 | F3: 17737.6
A4: 2103 | B4: Cereal | C4: 5116 | D4: 1052361.2 | E4: 599134.76 | F4: 453226.44
A5: 3127 | B5: Personal Care | C5: 4419 | D5: 361164.87 | E5: 250424.73 | F5: 110740.14
A6: 1270 | B6: Beverages | C6: 4028 | D6: 191128.6 | E6: 128050.12 | F6: 63078.48
A7: 8969 | B7: Snacks | C7: 1891 | D7: 288528.78 | E7: 184259.04 | F7: 104269.74
A8: 7940 | B8: Household | C8: 1749 | D8: 1168804.2 | E8: 878942.46 | F8: 289861.77
A9: 8681 | B9: Office Supplies | C9: 1342 | D9: 5714367.8 | E9: 4606524 | F9: 1107843.8
A10: 8293 | B10: Cosmetics | C10: 1224 | D10: 535132.8 | E10: 322315.92 | F10: 212816.88
A11: 8875 | B11: Meat | C11: 865 | D11: 364934.85 | E11: 315456.85 | F11: 49478
A12: 5988 | B12: Vegetables | C12: 286 | D12: 44061.16 | E12: 26005.98 | F12: 18055.18
A13: 7331 | B13: Baby Food | C13: 46 | D13: 1447182.3 | E13: 903751.98 | F13: 543430.34

Sheet 4.Business Metrics Table
A1: Country Name | B1: Units Sold | C1: Unit Price | D1: Unit Cost | E1: Total Revenue | F1: Total Cost | G1: Total Profit
A2: Albania | B2: 5669 | C2: 255.28 | D2: 159.42 | E2: 1447182.3 | F2: =B2*D2 -> 903751.98 | G2: =E2-F2 -> 543430.34 | I2: Total orders: | J2: =SUM(B2:B1331) -> 6576524
A3: Albania | B3: 1224 | C3: 437.2 | D3: 263.33 | E3: 535132.8 | F3: =B3*D3 -> 322315.92 | G3: =E3-F3 -> 212816.88 | I3: Total revenue: | J3: =SUM(E2:E1331) -> 1702129408
A4: Albania | B4: 8775 | C4: 651.21 | D4: 524.96 | E4: 5714367.8 | F4: =B4*D4 -> 4606524 | G4: =E4-F4 -> 1107843.8 | I4: Total cost: | J4: =SUM(F2:F1331) -> 1200694949
A5: Albania | B5: 4028 | C5: 47.45 | D5: 31.79 | E5: 191128.6 | F5: =B5*D5 -> 128050.12 | G5: =E5-F5 -> 63078.48 | I5: Total profit: | J5: =J3-J4 -> 501434459
A6: Albania | B6: 8586 | C6: 109.28 | D6: 35.84 | E6: 938278.08 | F6: =B6*D6 -> 307722.24 | G6: =E6-F6 -> 630555.84 | I6: Profit margin: | J6: =J5/J3 -> 0.29459244
A7: Albania | B7: 1749 | C7: 668.27 | D7: 502.54 | E7: 1168804.2 | F7: =B7*D7 -> 878942.46 | G7: =E7-F7 -> 289861.77
A8: Albania | B8: 286 | C8: 154.06 | D8: 90.93 | E8: 44061.16 | F8: =B8*D8 -> 26005.98 | G8: =E8-F8 -> 18055.18
A9: Albania | B9: 1172 | C9: 109.28 | D9: 35.84 | E9: 128076.16 | F9: =B9*D9 -> 42004.48 | G9: =E9-F9 -> 86071.68
A10: Albania | B10: 5310 | C10: 154.06 | D10: 90.93 | E10: 818058.6 | F10: =B10*D10 -> 482838.3 | G10: =E10-F10 -> 335220.3
A11: Albania | B11: 5534 | C11: 668.27 | D11: 502.54 | E11: 3698206.2 | F11: =B11*D11 -> 2781056.4 | G11: =E11-F11 -> 917149.82
A12: Albania | B12: 9619 | C12: 437.2 | D12: 263.33 | E12: 4205426.8 | F12: =B12*D12 -> 2532971.3 | G12: =E12-F12 -> 1672455.5
A13: Albania | B13: 9843 | C13: 109.28 | D13: 35.84 | E13: 1075643 | F13: =B13*D13 -> 352773.12 | G13: =E13-F13 -> 722869.92
A14: Albania | B14: 1891 | C14: 152.58 | D14: 97.44 | E14: 288528.78 | F14: =B14*D14 -> 184259.04 | G14: =E14-F14 -> 104269.74
A15: Albania | B15: 9560 | C15: 437.2 | D15: 263.33 | E15: 4179632 | F15: =B15*D15 -> 2517434.8 | G15: =E15-F15 -> 1662197.2
A16: Albania | B16: 5009 | C16: 437.2 | D16: 263.33 | E16: 2189934.8 | F16: =B16*D16 -> 1319020 | G16: =E16-F16 -> 870914.83
A17: Albania | B17: 2264 | C17: 47.45 | D17: 31.79 | E17: 107426.8 | F17: =B17*D17 -> 71972.56 | G17: =E17-F17 -> 35454.24
A18: Albania | B18: 1342 | C18: 651.21 | D18: 524.96 | E18: 873923.82 | F18: =B18*D18 -> 704496.32 | G18: =E18-F18 -> 169427.5
... A241: Croatia | B241: 4602 | C241: 651.21 | D241: 524.96 | E241: 2996868.4 | F241: =B241*D241 -> 2415865.9 | G241: =E241-F241 -> 581002.5
A242: Croatia | C242: 81.73 | D242: 56.67 | E242: 0 | F242: =B242*D242 -> 0 | G242: =E242-F242 -> 0
A243: Croatia | B243: 2908 | C243: 651.21 | D243: 524.96 | E243: 1893718.7 | F243: =B243*D243 -> 1526583.7 | G243: =E243-F243 -> 367135
A244: Croatia | B244: 6267 | C244: 437.2 | D244: 263.33 | E244: 2739932.4 | F244: =B244*D244 -> 1650289.1 | G244: =E244-F244 -> 1089643.3
A245: Croatia | B245: 523 | C245: 81.73 | D245: 56.67 | E245: 42744.79 | F245: =B245*D245 -> 29638.41 | G245: =E245-F245 -> 13106.38
A246: Croatia | B246: 347 | C246: 152.58 | D246: 97.44 | E246: 52945.26 | F246: =B246*D246 -> 33811.68 | G246: =E246-F246 -> 19133.58
A247: Croatia | B247: 8753 | C247: 421.89 | D247: 364.69 | E247: 3692803.2 | F247: =B247*D247 -> 3192131.6 | G247: =E247-F247 -> 500671.6
A248: Croatia | B248: 1362 | C248: 668.27 | D248: 502.54 | E248: 910183.74 | F248: =B248*D248 -> 684459.48 | G248: =E248-F248 -> 225724.26
A249: Croatia | B249: 1522 | C249: 651.21 | D249: 524.96 | E249: 991141.62 | F249: =B249*D249 -> 798989.12 | G249: =E249-F249 -> 192152.5
A250: Croatia | B250: 9680 | C250: 668.27 | D250: 502.54 | E250: 6468853.6 | F250: =B250*D250 -> 4864587.2 | G250: =E250-F250 -> 1604266.4
A251: Croatia | B251: 1539 | C251: 255.28 | D251: 159.42 | E251: 392875.92 | F251: =B251*D251 -> 245347.38 | G251: =E251-F251 -> 147528.54
A252: Croatia | B252: 8841 | C252: 109.28 | D252: 35.84 | E252: 966144.48 | F252: =B252*D252 -> 316861.44 | G252: =E252-F252 -> 649283.04
A253: Croatia | B253: 4958 | C253: 109.28 | D253: 35.84 | E253: 541810.24 | F253: =B253*D253 -> 177694.72 | G253: =E253-F253 -> 364115.52
A254: Croatia | B254: 4674 | C254: 47.45 | D254: 31.79 | E254: 221781.3 | F254: =B254*D254 -> 148586.46 | G254: =E254-F254 -> 73194.84
... A1111: Spain | B1111: 4419 | C1111: 154.06 | D1111: 90.93 | E1111: 680791.14 | F1111: =B1111*D1111 -> 401819.67 | G1111: =E1111-F1111 -> 278971.47
A1112: Spain | C1112: 421.89 | D1112: 364.69 | E1112: 0 | F1112: =B1112*D1112 -> 0 | G1112: =E1112-F1112 -> 0
A1113: Spain | B1113: 3103 | C1113: 9.33 | D1113: 6.92 | E1113: 28950.99 | F1113: =B1113*D1113 -> 21472.76 | G1113: =E1113-F1113 -> 7478.23
A1114: Spain | B1114: 3545 | C1114: 154.06 | D1114: 90.93 | E1114: 546142.7 | F1114: =B1114*D1114 -> 322346.85 | G1114: =E1114-F1114 -> 223795.85
A1115: Spain | B1115: 2819 | C1115: 668.27 | D1115: 502.54 | E1115: 1883853.1 | F1115: =B1115*D1115 -> 1416660.3 | G1115: =E1115-F1115 -> 467192.87
A1116: Spain | B1116: 4844 | C1116: 152.58 | D1116: 97.44 | E1116: 739097.52 | F1116: =B1116*D1116 -> 471999.36 | G1116: =E1116-F1116 -> 267098.16
A1117: Spain | B1117: 4897 | C1117: 109.28 | D1117: 35.84 | E1117: 535144.16 | F1117: =B1117*D1117 -> 175508.48 | G1117: =E1117-F1117 -> 359635.68
A1118: Spain | B1118: 9501 | C1118: 154.06 | D1118: 90.93 | E1118: 1463724.1 | F1118: =B1118*D1118 -> 863925.93 | G1118: =E1118-F1118 -> 599798.13
A1119: Spain | B1119: 2394 | C1119: 437.2 | D1119: 263.33 | E1119: 1046656.8 | F1119: =B1119*D1119 -> 630412.02 | G1119: =E1119-F1119 -> 416244.78
A1120: Spain | B1120: 5222 | C1120: 205.7 | D1120: 117.11 | E1120: 1074165.4 | F1120: =B1120*D1120 -> 611548.42 | G1120: =E1120-F1120 -> 462616.98
A1121: Spain | B1121: 6142 | C1121: 154.06 | D1121: 90.93 | E1121: 946236.52 | F1121: =B1121*D1121 -> 558492.06 | G1121: =E1121-F1121 -> 387744.46
A1122: Spain | B1122: 7701 | C1122: 421.89 | D1122: 364.69 | E1122: 3248974.9 | F1122: =B1122*D1122 -> 2808477.7 | G1122: =E1122-F1122 -> 440497.2
A1123: Spain | B1123: 3540 | C1123: 9.33 | D1123: 6.92 | E1123: 33028.2 | F1123: =B1123*D1123 -> 24496.8 | G1123: =E1123-F1123 -> 8531.4
A1124: Spain | B1124: 9336 | C1124: 421.89 | D1124: 364.69 | E1124: 3938765 | F1124: =B1124*D1124 -> 3404745.8 | G1124: =E1124-F1124 -> 534019.2
... A1331: Unknown Country | B1331: 6362 | C1331: 9.33 | D1331: 6.92 | E1331: 59357.46 | F1331: =B1331*D1331 -> 44025.04 | G1331: =E1331-F1331 -> 15332.42

Sheet 4.Business Metrics Pivot 

Sheet Visuals
